Workbook
Name W_FIAB: Supuestos!$B$7
Name W_PRECIO: Supuestos!$B$8
Name W_ESTADO: Supuestos!$B$9
Name W_ESTETICA: Supuestos!$B$10
Name W_SEGVIAL: Supuestos!$B$11
Name W_SEGURIDAD: Supuestos!$B$12
Name W_USO: Supuestos!$B$13
Name W_KMEDAD: Supuestos!$B$14
Name W_REVENTA: Supuestos!$B$15
Name W_COLOR: Supuestos!$B$16
Name W_SUMA: Supuestos!$B$17
Name ANIO_ACTUAL: Supuestos!$B$21
Name ANIO_MIN: Supuestos!$B$22
Name KM_MAX: Supuestos!$B$23
Name PRECIO_MAX: Supuestos!$B$24
Name TOTAL_MAX: Supuestos!$B$25
Name TECHO: Supuestos!$B$26
Name PEN_100: Supuestos!$B$27
Name SEG_ANIO: Supuestos!$B$28
Name SEG_KM: Supuestos!$B$29
Name MIN_N: Supuestos!$B$30
Name PRECIO_PEND: Supuestos!$B$31
Name KM_TOPE_DESDE: Supuestos!$B$32
Name KM_TOPE_PTS: Supuestos!$B$33
Name ROB_PEN: Supuestos!$B$34
Name KMA_IDEAL_MAX: Supuestos!$B$35
Name KMA_CERO: Supuestos!$B$36
Name KMA_SOSP: Supuestos!$B$37
Name KMA_PEN: Supuestos!$B$38
Name W_KMT: Supuestos!$B$39
Name W_KMA: Supuestos!$B$40
Name W_EDAD: Supuestos!$B$41
Name E_ITV: Supuestos!$B$42
Name E_LIBRO: Supuestos!$B$43
Name E_PROP: Supuestos!$B$44
Name E_CORREA: Supuestos!$B$45
Name E_FACT: Supuestos!$B$46
Name W_ET: Supuestos!$B$47
Name W_CONS: Supuestos!$B$48
Name W_SEG: Supuestos!$B$49
Name W_MANT: Supuestos!$B$50
Name NEUTRO: Supuestos!$B$51
Name SG_GAR: Supuestos!$B$52
Name SG_GAR_FULL: Supuestos!$B$53
Name SG_AMPL: Supuestos!$B$54
Name SG_KMC: Supuestos!$B$55
Name SG_REV: Supuestos!$B$56
Name SG_DEV: Supuestos!$B$57
Name SG_DEV_FULL: Supuestos!$B$58
Name SG_HIST: Supuestos!$B$59
Name SG_LEGAL_ON: Supuestos!$B$60
Name GAR_LEGAL: Supuestos!$B$61
Name SG_PART_PEN: Supuestos!$B$62
Name SV_W_NCAP: Supuestos!$B$63
Name SV_W_ESP: Supuestos!$B$64
Name RV_W_LIQ: Supuestos!$B$65
Name RV_N_FULL: Supuestos!$B$66
Name RV_W_DIAS: Supuestos!$B$67
Name RV_DIAS_FULL: Supuestos!$B$68
Name RV_DIAS_CERO: Supuestos!$B$69

Sheet Anuncios
A1: ID | B1: Plataforma | C1: URL | D1: Título | E1: Marca | F1: Modelo | G1: Motor (normalizado) | H1: Versión | I1: Cilindrada (cc) | J1: Potencia (CV) | K1: Combustible | L1: Segmento | M1: Año | N1: Km | O1: Precio (€) | P1: Cambio | Q1: Automático | R1: Vendedor | S1: Ubicación | T1: Publicado | U1: Nº fotos | V1: ITV en vigor | W1: Libro mantenimiento | X1: Correa/distrib. cambiada | Y1: Nº propietarios | Z1: Garantía | AA1: Km justificados | AB1: Garantía incluida (meses) | AC1: Garantía ampliable | AD1: Precio ampliación garantía (€) | AE1: Revisión (puntos) | AF1: Km certificados | AG1: Devolución (días) | AH1: Precio al contado (€) | AI1: Precio financiado (€) | AJ1: Precio anunciado solo financiando | AK1: Gastos de gestión del vendedor (€) | AL1: Gastos incluyen transferencia | AM1: Distancia a València (km) | AN1: Matrícula | AO1: 1.ª matriculación (anuncio) | AP1: Año 1.ª matric. | AQ1: Mes 1.ª matric. | AR1: Etiqueta DGT/anuncio | AS1: Fuente etiqueta | AT1: Año en URL/título distinto (a confirmar) | AU1: Etiqueta dudosa por año | AV1: Etiquetas posibles | AW1: Anuncio incoherente (etiqueta del anuncio) | AX1: Caja robotizada | AY1: Modelo de estetica.yaml admitido de particular | AZ1: Color (anuncio) | BA1: Color normalizado | BB1: Estética del modelo (1-5) | BC1: Entrada de estetica.yaml | BD1: Acabado alto/deportivo | BE1: Llantas (16+ / sí / chapa) | BF1: Faros xenón/LED | BG1: Cristales tintados | BH1: Correa con fecha o km | BI1: Facturas | BJ1: Neumáticos nuevos | BK1: Euro NCAP (estrellas) | BL1: ESP/ESC | BM1: Anuncios del modelo en el mercado | BN1: Días medianos hasta desaparecer | BO1: Ventas observadas del modelo | BP1: Mediana de mercado del segmento (€) | BQ1: N mercado | BR1: Nivel mediana mercado | BS1: Duplicados fusionados | BT1: Avisos | BU1: Descripción | BV1: Fuente (fichero /raw) | BW1: Edad (años) | BX1: Km/año | BY1: Seg. modelo | BZ1: Seg. modelo+año | CA1: Seg. modelo+año+km | CB1: N modelo | CC1: N modelo+año | CD1: N modelo+año+km | CE1: Mediana segmento (€) | CF1: Nivel mediana | CG1: Descuento vs mediana | CH1: Año frontera (1/0) | CI1: Año anterior frontera (1/0) | CJ1: AAAAMM para la regla | CK1: Etiqueta por regla | CL1: ETIQUETA | CM1: Etiqueta dudosa | CN1: Fiab. base modelo | CO1: Ajuste motor | CP1: Ajuste combustible | CQ1: Motor con fuente (nº entradas) | CR1: Fiab. base aplicada | CS1: P. Fiabilidad | CT1: Tope nota precio por km | CU1: P. Precio | CV1: P. km totales | CW1: P. km/año | CX1: P. edad | CY1: P. Km y edad | CZ1: Clave marca|motor | DA1: Distribución | DB1: P. Estado y mantenimiento | DC1: P. Etiqueta y ZBE | DD1: Consumo estimado l/100 km (aprox.) | DE1: P. consumo | DF1: Seguro estimado €/año (aprox.) | DG1: P. seguro | DH1: P. recambios marca | DI1: P. distribución | DJ1: P. mantenimiento | DK1: P. Coste uso | DL1: Garantía efectiva (meses) | DM1: P. Seguridad compra | DN1: P. Euro NCAP | DO1: P. ESP | DP1: P. Seguridad (NCAP + ESP) | DQ1: P. atributos | DR1: P. Estética | DS1: P. Color | DT1: P. liquidez | DU1: P. días de venta | DV1: P. Reventa y liquidez | DW1: Penalización carrocería (puntos) | DX1: PUNTUACIÓN | DY1: cc para ITP | DZ1: ITP (€) | EA1: Gastos vendedor en coste (€) | EB1: Tasa DGT (€) | EC1: Informe DGT (€) | ED1: COSTE TOTAL (€) | EE1: Coste 1er año con seguro (€) | EF1: Exceso sobre presupuesto = € a negociar | EG1: Penalización presupuesto (puntos) | EH1: Coste real estimado particular (€, informativo) | EI1: Presupuesto (sí / negociar / no) | EJ1: Puntuación redondeada (desempate) | EK1: Puesto
A2: ocasionplus:b9auzqaa | B2: ocasionplus | C2: https://www.ocasionplus.com/coches-segunda-mano/peugeot-207-14-confort-con-116183km-2008-b9auzqaa | D2: Peugeot 207 1.4 Confort (75 CV) | E2: Peugeot | F2: Peugeot 207 | G2: 1.4 | H2: Peugeot 207 1.4 Confort (75 CV) | I2: 1360 | J2: 75 | K2: gasolina | L2: utilitario | M2: 2008 | N2: 116183 | O2: 2900 | P2: manual | Q2: no | R2: profesional | S2: Valencia - Sagunto (Sagunto, 46500) | T2: 2026-10-27T00:00:00.000Z | U2: 25 | V2: sí | Y2: 0 | AC2: sí | AD2: 500 | AF2: sí | AH2: 2900 | AI2: 2900 | AJ2: no | AK2: 350 | AL2: sí | AM2: 25.5 | AN2: 8408GBN | AO2: 2008-03-03 | AP2: 2008 | AQ2: 3 | AR2: C | AS2: DGT | AU2: no | AV2: C | AX2: no | AY2: no | AZ2: Rojo | BA2: rojo | BB2: 2 | BC2: (por segmento) | BE2: chapa | BG2: sí | BK2: 5 | BM2: 125 | BO2: 0 | BP2: 3650 | BQ2: 28 | BR2: modelo+año+km | BT2: vendedor profesional: sin ITP (operación con IVA/REBU, confirmar en factura); revisar: no menciona la ITV; fiabilidad del modelo PENDIENTE de fuente (puntuación neutra) | BU2: Peugeot 207 1.4 Confort (75 CV) | BV2: https://www.ocasionplus.com/coches-segunda-mano/peugeot-207-14-confort-con-116183km-2008-b9auzqaa (payload RSC 'vehicle') /home/user/Alopecia/buscador-coches/raw/ocasionplus/fc0eb20181760918.json | BW2: =MAX(ANIO_ACTUAL-M2,0) | BX2: =N2/MAX(BW2,0.5) | BY2: =F2 | BZ2: =BY2&"|"&INT(M2/SEG_ANIO)*SEG_ANIO | CA2: =BZ2&"|"&INT(N2/SEG_KM)*SEG_KM | CB2: =COUNTIF($BY$2:$BY$209,BY2) | CC2: =COUNTIF($BZ$2:$BZ$209,BZ2) | CD2: =COUNTIF($CA$2:$CA$209,CA2) | CE2: {=IF(N(BQ2)>=MIN_N,BP2,IF(CD2>=MIN_N,MEDIAN(IF($CA$2:$CA$209=CA2,$O$2:$O$209)),IF(CC2>=MIN_N,MEDIAN(IF($BZ$2:$BZ$209=BZ2,$O$2:$O$209)),MEDIAN(IF($BY$2:$BY$209=BY2,$O$2:$O$209)))))} | CF2: =IF(N(BQ2)>=MIN_N,"mercado "&BR2,IF(CD2>=MIN_N,"modelo+año+km",IF(CC2>=MIN_N,"modelo+año","modelo"))) | CG2: =(CE2-O2)/CE2 | CH2: =IF(COUNTIFS(FR_FUEL,K2,FR_YEAR,AP2)>0,1,0) | CI2: =IF(COUNTIFS(FR_FUEL,K2,FR_YEAR,AP2-1)>0,1,0) | CJ2: =IF(N(AQ2)>0,AP2*100+AQ2,IF(AND(CH2=1,CI2=1),(AP2-1)*100+1,AP2*100+1)) | CK2: =IF(OR(K2="hibrido",K2="glp",K2="gnc",K2="phev"),"ECO",IF(K2="electrico","CERO",IF(K2="gasolina",IF(CJ2>=GAS_C_YM,"C",IF(CJ2>=GAS_B_YM,"B","A")),IF(K2="diesel",IF(CJ2>=DIE_C_YM,"C",IF(CJ2>=DIE_B_YM,"B","A")),"")))) | CL2: C | CM2: =IF(AU2="sí","sí",IF(AS2="regla",IF(AND(N(AQ2)=0,CH2=1),"sí","no"),"no")) | CN2: =IFERROR(VLOOKUP(F2,MOD_TBL,16,0),IFERROR(VLOOKUP(E2,OCU_TBL,2,0),NEUTRO)) | CO2: =SUMIFS(MOT_AJUSTE,MOT_MOTOR,G2,MOT_MARCA,E2,MOT_DESDE,"<="&M2,MOT_HASTA,">="&M2)+SUMIFS(MOT_AJUSTE,MOT_MOTOR,G2,MOT_MARCA,"(todas)",MOT_DESDE,"<="&M2,MOT_HASTA,">="&M2)+SUMIFS(MOT_AJUSTE,MOT_MOTOR,"(cualquiera)",MOT_MARCA,E2,MOT_DESDE,"<="&M2,MOT_HASTA,">="&M2) | CP2: =SUMIFS(COMB_AJUSTE,COMB_COMB,K2) | CQ2: =COUNTIFS(MOT_MOTOR,G2,MOT_MARCA,E2,MOT_DESDE,"<="&M2,MOT_HASTA,">="&M2)+COUNTIFS(MOT_MOTOR,G2,MOT_MARCA,"(todas)",MOT_DESDE,"<="&M2,MOT_HASTA,">="&M2)+COUNTIFS(MOT_MOTOR,"(cualquiera)",MOT_MARCA,E2,MOT_DESDE,"<="&M2,MOT_HASTA,">="&M2) | CR2: =IF(AND(K2="diesel",CQ2=0),MIN(CN2,NEUTRO),CN2) | CS2: =MAX(0,MIN(100,CR2+CO2+CP2-IF(AX2="sí",ROB_PEN,0))) | CT2: =100-MAX(0,N2-KM_TOPE_DESDE)/1000*KM_TOPE_PTS | CU2: =MAX(0,MIN(100,50+CG2*PRECIO_PEND,CT2)) | CV2: =MAX(0,100*(1-N2/KM_MAX)) | CW2: =IF(BX2<KMA_SOSP,IF(AA2="sí",100,KMA_PEN),IF(BX2<=KMA_IDEAL_MAX,100,MAX(0,100*(KMA_CERO-BX2)/(KMA_CERO-KMA_IDEAL_MAX)))) | CX2: =MAX(0,MIN(100,100*(M2-ANIO_MIN)/(ANIO_ACTUAL-ANIO_MIN))) | CY2: =W_KMT*CV2+W_KMA*CW2+W_EDAD*CX2 | CZ2: =E2&"|"&G2 | DA2: =IFERROR(VLOOKUP(CZ2,DIST_TBL,2,0),"") | DB2: =E_ITV*(V2="sí")+E_LIBRO*(W2="sí")+E_PROP*IF(Y2=1,1,IF(Y2=2,0.5,0))+E_CORREA*IF(OR(DA2="cadena",AND(X2="sí",BH2="sí")),1,IF(X2="sí",0.5,0))+E_FACT*(BI2="sí") | DC2: =MAX(0,MIN(100,IFERROR(VLOOKUP(CL2,ETQ_TBL,2,0),0)-IF(CM2="sí",ETQ_PEN_DUD,IF(AS2="regla",ETQ_PEN_REGLA,0)))) | DD2: =IF(K2<>"gasolina","",IFERROR(VLOOKUP(F2,CONS_MOD_TBL,2,0),IFERROR(VLOOKUP(L2,CONS_SEG_TBL,2,0),""))) | DE2: =IF(DD2="",NEUTRO,MAX(0,MIN(100,100*(CONS_REF_MAX-DD2)/(CONS_REF_MAX-CONS_REF_MIN)))) | DF2: =IFERROR(VLOOKUP(L2,SEGURO_TBL,3,0),"") | DG2: =IF(DF2="",NEUTRO,MAX(0,MIN(100,100*(SEG_REF_MAX-DF2)/(SEG_REF_MAX-SEG_REF_MIN)))) | DH2: =IFERROR(VLOOKUP(E2,MANT_MARCA_TBL,2,0)+0,NEUTRO) | DI2: =IF(DA2="",NEUTRO,IFERROR(VLOOKUP(DA2,DIST_PTS_TBL,2,0)+0,NEUTRO)) | DJ2: =(DH2+DI2)/2 | DK2: =W_CONS*DE2+W_SEG*DG2+W_MANT*DJ2 | DL2: =IF(N(AB2)>0,AB2,IF(AND(R2="profesional",SG_LEGAL_ON=1),GAR_LEGAL,0)) | DM2: =MAX(0,MIN(100,SG_GAR*MIN(1,DL2/SG_GAR_FULL)+SG_AMPL*(AC2="sí")+SG_KMC*(AF2="sí")+SG_REV*(N(AE2)>0)+SG_DEV*MIN(1,N(AG2)/SG_DEV_FULL)+SG_HIST*(W2="sí")-IF(AND(R2="particular",DL2=0),SG_PART_PEN,0))) | DN2: =IF(BK2="",NEUTRO,MAX(0,MIN(100,BK2/5*100))) | DO2: =IF(BL2="sí",100,IF(BL2="no",0,NEUTRO)) | DP2: =SV_W_NCAP*DN2+SV_W_ESP*DO2 | DQ2: =MAX(0,MIN(100,ATR_BASE+ATR_ACAB*(BD2<>"")+IF(BE2="16+",ATR_LL16,IF(BE2="sí",ATR_LL,0))+ATR_FAROS*(BF2="sí")+ATR_TINT*(BG2="sí")-ATR_CHAPA*(BE2="chapa"))) | DR2: =EST_W_MOD*(BB2-1)/4*100+EST_W_ATR*DQ2 | DS2: =IF(BA2="",NEUTRO,IFERROR(VLOOKUP(BA2,COLOR_TBL,2,0)+0,NEUTRO)) | DT2: =MAX(0,MIN(100,100*N(BM2)/RV_N_FULL)) | DU2: =IF(OR(BN2="",N(BO2)<RV_DIAS_MIN),NEUTRO,MAX(0,MIN(100,100*(RV_DIAS_CERO-BN2)/(RV_DIAS_CERO-RV_DIAS_FULL)))) | DV2: =RV_W_LIQ*DT2+RV_W_DIAS*DU2+RV_W_ETQ*DC2 | DW2: =IFERROR(VLOOKUP(L2,CARR_PEN_TBL,2,0),0) | DX2: =W_FIAB*CS2+W_PRECIO*CU2+W_KMEDAD*CY2+W_ESTADO*DB2+W_USO*DK2+W_SEGURIDAD*DM2+W_SEGVIAL*DP2+W_ESTETICA*DR2+W_COLOR*DS2+W_REVENTA*DV2-DW2-EG2 | DY2: =IF(N(I2)>0,I2,IFERROR(ROUND(_xlfn.NUMBERVALUE(LEFT(G2,FIND(" ",G2&" ")-1),".")*1000,0),99999)) | DZ2: =IF(R2="profesional",0,IF(O2<CUOTA_VALOR_MAX,IF(BW2>ITP_TRAMO_ALTO,SUMIFS(CF_CUOTA,CF_MAS,ITP_TRAMO_ALTO,CF_CCMIN,"<="&DY2,CF_CCMAX,">="&DY2),IF(BW2>ITP_TRAMO_BAJO,SUMIFS(CF_CUOTA,CF_MAS,ITP_TRAMO_BAJO,CF_CCMIN,"<="&DY2,CF_CCMAX,">="&DY2),O2*ITP_TIPO)),O2*ITP_TIPO)) | EA2: =IF(R2="profesional",N(AK2),0) | EB2: =IF(AND(R2="profesional",ISNUMBER(AK2),AL2="sí"),0,TASA_DGT) | EC2: =INFORME_DGT | ED2: =O2+EA2+DZ2+EB2+EC2 | EE2: =ED2+N(DF2) | EF2: =MAX(0,ED2-TOTAL_MAX) | EG2: =EF2/100*PEN_100 | EH2: =IF(R2="particular",ED2+IF(AND(DA2<>"cadena",X2<>"sí"),RES_CORREA,0)+IF(AND(BJ2<>"sí",BW2>=RES_NEUM_EDAD),RES_NEUM,0),"") | EI2: =IF(ED2<=TOTAL_MAX,"sí",IF(ED2<=TECHO,"negociar","no")) | EJ2: =ROUND(DX2,9) | EK2: =IF(EI2<>"no",SUMPRODUCT(($EI$2:$EI$209<>"no")*($EJ$2:$EJ$209>EJ2))+SUMPRODUCT(($EI$2:EI2<>"no")*($EJ$2:EJ2=EJ2)),"")
A3: autoscout24:827f958f-8688-4b6d-8737-916b285573e8 | B3: autoscout24 | C3: https://www.autoscout24.es/anuncios/volkswagen-polo-1-2-advance-bmt-gasolina-gris-cat_ma74mo2090-827f958f-8688-4b6d-8737-916b285573e8 | D3: Volkswagen Polo 1.2 Advance BMT | E3: Volkswagen | F3: Volkswagen Polo | G3: 1.2 | H3: 1.2 Advance BMT 1.2 | I3: 1198 | J3: 69 | K3: gasolina | L3: utilitario | M3: 2011 | N3: 211000 | O3: 4400 | P3: manual | Q3: no | R3: profesional | S3: Star Car Valencia — ALDAIA (46960) | U3: 8 | Z3: sí | AB3: 24 | AH3: 4400 | AM3: 6.8 | AO3: 2011-07 | AP3: 2011 | AQ3: 7 | AS3: regla | AU3: no | AV3: C | AX3: no | AY3: no | AZ3: Gris | BA3: gris_medio | BB3: 2 | BC3: (por segmento) | BK3: 5 | BL3: sí | BM3: 321 | BN3: 0.051261574 | BO3: 3 | BP3: 4900 | BQ3: 9 | BR3: modelo+año+km | BT3: vendedor profesional: sin ITP (operación con IVA/REBU, confirmar en factura); gastos de gestión del vendedor no indicados: se suma la tasa DGT; preguntar el precio final; etiqueta C deducida por fecha (sin matrícula ni dato del anuncio) | BU3: <strong>Precio al contado: 4400 euros</strong> <br /><br /><strong>Condiciones de la financiación</strong> <br /><br />REQUISITOS<br />LTIMA NOMINA<br />TITULARIDAD BANCARIA<br />DNI<br />TELEFONO<br />⅕<br /> <br /><br />1 AÑO DE GARANTÍA o 2 AÑOS DE GARANTÍA DE MOTOR<br />POSIBILIDAD DE FINANCIACION 100%<br />MANTENIMIENTO REALIZADO<br />ENTREGA INMEDIATA<br />1ª Matriculación: 02/2011<br />Lectura cuentakilómetros: 211.407 km<br />Combustible: Gasolina<br />Potencia: 51 KW / 70 CV<br />Cilindrada: 1.198 cc<br />Caja de cambios: Cambio tipo manual<br />Fecha de vencimiento ITV: 01/2027<br /> Si necesitas cualquier coche — modelo, color, año y kilómetros — te lo traemos.<br />Dinos qué necesitas y lo tendrás. <br /><br /> El anuncio puede contener errores.<br /><br /> | BV3: https://www.autoscout24.es/anuncios/volkswagen-polo-1-2-advance-bmt-gasolina-gris-cat_ma74mo2090-827f958f-8688-4b6d-8737-916b285573e8 (__NEXT_DATA__ listingDetails) /home/user/Alopecia/buscador-coches/raw/autoscout24/d6fff8df76fd308b.json | BW3: =MAX(ANIO_ACTUAL-M3,0) | BX3: =N3/MAX(BW3,0.5) | BY3: =F3 | BZ3: =BY3&"|"&INT(M3/SEG_ANIO)*SEG_ANIO | CA3: =BZ3&"|"&INT(N3/SEG_KM)*SEG_KM | CB3: =COUNTIF($BY$2:$BY$209,BY3) | CC3: =COUNTIF($BZ$2:$BZ$209,BZ3) | CD3: =COUNTIF($CA$2:$CA$209,CA3) | CE3: {=IF(N(BQ3)>=MIN_N,BP3,IF(CD3>=MIN_N,MEDIAN(IF($CA$2:$CA$209=CA3,$O$2:$O$209)),IF(CC3>=MIN_N,MEDIAN(IF($BZ$2:$BZ$209=BZ3,$O$2:$O$209)),MEDIAN(IF($BY$2:$BY$209=BY3,$O$2:$O$209)))))} | CF3: =IF(N(BQ3)>=MIN_N,"mercado "&BR3,IF(CD3>=MIN_N,"modelo+año+km",IF(CC3>=MIN_N,"modelo+año","modelo"))) | CG3: =(CE3-O3)/CE3 | CH3: =IF(COUNTIFS(FR_FUEL,K3,FR_YEAR,AP3)>0,1,0) | CI3: =IF(COUNTIFS(FR_FUEL,K3,FR_YEAR,AP3-1)>0,1,0) | CJ3: =IF(N(AQ3)>0,AP3*100+AQ3,IF(AND(CH3=1,CI3=1),(AP3-1)*100+1,AP3*100+1)) | CK3: =IF(OR(K3="hibrido",K3="glp",K3="gnc",K3="phev"),"ECO",IF(K3="electrico","CERO",IF(K3="gasolina",IF(CJ3>=GAS_C_YM,"C",IF(CJ3>=GAS_B_YM,"B","A")),IF(K3="diesel",IF(CJ3>=DIE_C_YM,"C",IF(CJ3>=DIE_B_YM,"B","A")),"")))) | CL3: =CK3 | CM3: =IF(AU3="sí","sí",IF(AS3="regla",IF(AND(N(AQ3)=0,CH3=1),"sí","no"),"no")) | CN3: =IFERROR(VLOOKUP(F3,MOD_TBL,16,0),IFERROR(VLOOKUP(E3,OCU_TBL,2,0),NEUTRO)) | CO3: =SUMIFS(MOT_AJUSTE,MOT_MOTOR,G3,MOT_MARCA,E3,MOT_DESDE,"<="&M3,MOT_HASTA,">="&M3)+SUMIFS(MOT_AJUSTE,MOT_MOTOR,G3,MOT_MARCA,"(todas)",MOT_DESDE,"<="&M3,MOT_HASTA,">="&M3)+SUMIFS(MOT_AJUSTE,MOT_MOTOR,"(cualquiera)",MOT_MARCA,E3,MOT_DESDE,"<="&M3,MOT_HASTA,">="&M3) | CP3: =SUMIFS(COMB_AJUSTE,COMB_COMB,K3) | CQ3: =COUNTIFS(MOT_MOTOR,G3,MOT_MARCA,E3,MOT_DESDE,"<="&M3,MOT_HASTA,">="&M3)+COUNTIFS(MOT_MOTOR,G3,MOT_MARCA,"(todas)",MOT_DESDE,"<="&M3,MOT_HASTA,">="&M3)+COUNTIFS(MOT_MOTOR,"(cualquiera)",MOT_MARCA,E3,MOT_DESDE,"<="&M3,MOT_HASTA,">="&M3) | CR3: =IF(AND(K3="diesel",CQ3=0),MIN(CN3,NEUTRO),CN3) | CS3: =MAX(0,MIN(100,CR3+CO3+CP3-IF(AX3="sí",ROB_PEN,0))) | CT3: =100-MAX(0,N3-KM_TOPE_DESDE)/1000*KM_TOPE_PTS | CU3: =MAX(0,MIN(100,50+CG3*PRECIO_PEND,CT3)) | CV3: =MAX(0,100*(1-N3/KM_MAX)) | CW3: =IF(BX3<KMA_SOSP,IF(AA3="sí",100,KMA_PEN),IF(BX3<=KMA_IDEAL_MAX,100,MAX(0,100*(KMA_CERO-BX3)/(KMA_CERO-KMA_IDEAL_MAX)))) | CX3: =MAX(0,MIN(100,100*(M3-ANIO_MIN)/(ANIO_ACTUAL-ANIO_MIN))) | CY3: =W_KMT*CV3+W_KMA*CW3+W_EDAD*CX3 | CZ3: =E3&"|"&G3 | DA3: =IFERROR(VLOOKUP(CZ3,DIST_TBL,2,0),"") | DB3: =E_ITV*(V3="sí")+E_LIBRO*(W3="sí")+E_PROP*IF(Y3=1,1,IF(Y3=2,0.5,0))+E_CORREA*IF(OR(DA3="cadena",AND(X3="sí",BH3="sí")),1,IF(X3="sí",0.5,0))+E_FACT*(BI3="sí") | DC3: =MAX(0,MIN(100,IFERROR(VLOOKUP(CL3,ETQ_TBL,2,0),0)-IF(CM3="sí",ETQ_PEN_DUD,IF(AS3="regla",ETQ_PEN_REGLA,0)))) | DD3: =IF(K3<>"gasolina","",IFERROR(VLOOKUP(F3,CONS_MOD_TBL,2,0),IFERROR(VLOOKUP(L3,CONS_SEG_TBL,2,0),""))) | DE3: =IF(DD3="",NEUTRO,MAX(0,MIN(100,100*(CONS_REF_MAX-DD3)/(CONS_REF_MAX-CONS_REF_MIN)))) | DF3: =IFERROR(VLOOKUP(L3,SEGURO_TBL,3,0),"") | DG3: =IF(DF3="",NEUTRO,MAX(0,MIN(100,100*(SEG_REF_MAX-DF3)/(SEG_REF_MAX-SEG_REF_MIN)))) | DH3: =IFERROR(VLOOKUP(E3,MANT_MARCA_TBL,2,0)+0,NEUTRO) | DI3: =IF(DA3="",NEUTRO,IFERROR(VLOOKUP(DA3,DIST_PTS_TBL,2,0)+0,NEUTRO)) | DJ3: =(DH3+DI3)/2 | DK3: =W_CONS*DE3+W_SEG*DG3+W_MANT*DJ3 | DL3: =IF(N(AB3)>0,AB3,IF(AND(R3="profesional",SG_LEGAL_ON=1),GAR_LEGAL,0)) | DM3: =MAX(0,MIN(100,SG_GAR*MIN(1,DL3/SG_GAR_FULL)+SG_AMPL*(AC3="sí")+SG_KMC*(AF3="sí")+SG_REV*(N(AE3)>0)+SG_DEV*MIN(1,N(AG3)/SG_DEV_FULL)+SG_HIST*(W3="sí")-IF(AND(R3="particular",DL3=0),SG_PART_PEN,0))) | DN3: =IF(BK3="",NEUTRO,MAX(0,MIN(100,BK3/5*100))) | DO3: =IF(BL3="sí",100,IF(BL3="no",0,NEUTRO)) | DP3: =SV_W_NCAP*DN3+SV_W_ESP*DO3 | DQ3: =MAX(0,MIN(100,ATR_BASE+ATR_ACAB*(BD3<>"")+IF(BE3="16+",ATR_LL16,IF(BE3="sí",ATR_LL,0))+ATR_FAROS*(BF3="sí")+ATR_TINT*(BG3="sí")-ATR_CHAPA*(BE3="chapa"))) | DR3: =EST_W_MOD*(BB3-1)/4*100+EST_W_ATR*DQ3 | DS3: =IF(BA3="",NEUTRO,IFERROR(VLOOKUP(BA3,COLOR_TBL,2,0)+0,NEUTRO)) | DT3: =MAX(0,MIN(100,100*N(BM3)/RV_N_FULL)) | DU3: =IF(OR(BN3="",N(BO3)<RV_DIAS_MIN),NEUTRO,MAX(0,MIN(100,100*(RV_DIAS_CERO-BN3)/(RV_DIAS_CERO-RV_DIAS_FULL)))) | DV3: =RV_W_LIQ*DT3+RV_W_DIAS*DU3+RV_W_ETQ*DC3 | DW3: =IFERROR(VLOOKUP(L3,CARR_PEN_TBL,2,0),0) | DX3: =W_FIAB*CS3+W_PRECIO*CU3+W_KMEDAD*CY3+W_ESTADO*DB3+W_USO*DK3+W_SEGURIDAD*DM3+W_SEGVIAL*DP3+W_ESTETICA*DR3+W_COLOR*DS3+W_REVENTA*DV3-DW3-EG3 | DY3: =IF(N(I3)>0,I3,IFERROR(ROUND(_xlfn.NUMBERVALUE(LEFT(G3,FIND(" ",G3&" ")-1),".")*1000,0),99999)) | DZ3: =IF(R3="profesional",0,IF(O3<CUOTA_VALOR_MAX,IF(BW3>ITP_TRAMO_ALTO,SUMIFS(CF_CUOTA,CF_MAS,ITP_TRAMO_ALTO,CF_CCMIN,"<="&DY3,CF_CCMAX,">="&DY3),IF(BW3>ITP_TRAMO_BAJO,SUMIFS(CF_CUOTA,CF_MAS,ITP_TRAMO_BAJO,CF_CCMIN,"<="&DY3,CF_CCMAX,">="&DY3),O3*ITP_TIPO)),O3*ITP_TIPO)) | EA3: =IF(R3="profesional",N(AK3),0) | EB3: =IF(AND(R3="profesional",ISNUMBER(AK3),AL3="sí"),0,TASA_DGT) | EC3: =INFORME_DGT | ED3: =O3+EA3+DZ3+EB3+EC3 | EE3: =ED3+N(DF3) | EF3: =MAX(0,ED3-TOTAL_MAX) | EG3: =EF3/100*PEN_100 | EH3: =IF(R3="particular",ED3+IF(AND(DA3<>"cadena",X3<>"sí"),RES_CORREA,0)+IF(AND(BJ3<>"sí",BW3>=RES_NEUM_EDAD),RES_NEUM,0),"") | EI3: =IF(ED3<=TOTAL_MAX,"sí",IF(ED3<=TECHO,"negociar","no")) | EJ3: =ROUND(DX3,9) | EK3: =IF(EI3<>"no",SUMPRODUCT(($EI$2:$EI$209<>"no")*($EJ$2:$EJ$209>EJ3))+SUMPRODUCT(($EI$2:EI3<>"no")*($EJ$2:EJ3=EJ3)),"")
A4: autoscout24:530a78a6-41a7-4caa-9407-81ae2c44ad35 | B4: autoscout24 | C4: https://www.autoscout24.es/anuncios/opel-corsa-1-4-c-mon-139co2-gasolina-gris-cat_ma54mo1918-530a78a6-41a7-4caa-9407-81ae2c44ad35 | D4: Opel Corsa 1.4 C Mon (139CO2) | E4: Opel | F4: Opel Corsa | G4: 1.4 | H4: 1.4 C Mon (139CO2) 1.4 | I4: 1364 | J4: 90 | K4: gasolina | L4: utilitario | M4: 2009 | N4: 136000 | O4: 4500 | P4: manual | Q4: no | R4: profesional | S4: EUROREPAR AUTOS MERCHAN — MASANASSA (46470) | U4: 8 | V4: sí | Z4: sí | AB4: 12 | AM4: 6.7 | AO4: 2009-01 | AP4: 2009 | AQ4: 1 | AS4: regla | AU4: no | AV4: C | AX4: no | AY4: no | AZ4: Gris Metalizado | BA4: gris_medio | BB4: 2 | BC4: (por segmento) | BE4: sí | BJ4: sí | BK4: 5 | BM4: 456 | BN4: 0.051261574 | BO4: 11 | BP4: 3600 | BQ4: 9 | BR4: modelo+año+km | BS4: cochesnet:71842537 (https://www.coches.net/opel-corsa-cmon-14-3p-gasolina-2009-en-valencia-71842537-covo.aspx) | BT4: vendedor profesional: sin ITP (operación con IVA/REBU, confirmar en factura); gastos de gestión del vendedor no indicados: se suma la tasa DGT; preguntar el precio final; etiqueta C deducida por fecha (sin matrícula ni dato del anuncio) | BU4: Se vende Opel Corsa 1.4 Gasolina (90CV) y fecha matriculación Enero 2009. Vehiculo muy bien cuidado tanto interior como exterior y motor . Se entrega con revisión completa aceite y filtros, bujías , 4 neumáticos nuevos, 2 llaves e itv recién pasada.<br /><br /> | BV4: https://www.autoscout24.es/anuncios/opel-corsa-1-4-c-mon-139co2-gasolina-gris-cat_ma54mo1918-530a78a6-41a7-4caa-9407-81ae2c44ad35 (__NEXT_DATA__ listingDetails) /home/user/Alopecia/buscador-coches/raw/autoscout24/ea1df8b55d5dba3e.json | BW4: =MAX(ANIO_ACTUAL-M4,0) | BX4: =N4/MAX(BW4,0.5) | BY4: =F4 | BZ4: =BY4&"|"&INT(M4/SEG_ANIO)*SEG_ANIO | CA4: =BZ4&"|"&INT(N4/SEG_KM)*SEG_KM | CB4: =COUNTIF($BY$2:$BY$209,BY4) | CC4: =COUNTIF($BZ$2:$BZ$209,BZ4) | CD4: =COUNTIF($CA$2:$CA$209,CA4) | CE4: {=IF(N(BQ4)>=MIN_N,BP4,IF(CD4>=MIN_N,MEDIAN(IF($CA$2:$CA$209=CA4,$O$2:$O$209)),IF(CC4>=MIN_N,MEDIAN(IF($BZ$2:$BZ$209=BZ4,$O$2:$O$209)),MEDIAN(IF($BY$2:$BY$209=BY4,$O$2:$O$209)))))} | CF4: =IF(N(BQ4)>=MIN_N,"mercado "&BR4,IF(CD4>=MIN_N,"modelo+año+km",IF(CC4>=MIN_N,"modelo+año","modelo"))) | CG4: =(CE4-O4)/CE4 | CH4: =IF(COUNTIFS(FR_FUEL,K4,FR_YEAR,AP4)>0,1,0) | CI4: =IF(COUNTIFS(FR_FUEL,K4,FR_YEAR,AP4-1)>0,1,0) | CJ4: =IF(N(AQ4)>0,AP4*100+AQ4,IF(AND(CH4=1,CI4=1),(AP4-1)*100+1,AP4*100+1)) | CK4: =IF(OR(K4="hibrido",K4="glp",K4="gnc",K4="phev"),"ECO",IF(K4="electrico","CERO",IF(K4="gasolina",IF(CJ4>=GAS_C_YM,"C",IF(CJ4>=GAS_B_YM,"B","A")),IF(K4="diesel",IF(CJ4>=DIE_C_YM,"C",IF(CJ4>=DIE_B_YM,"B","A")),"")))) | CL4: =CK4 | CM4: =IF(AU4="sí","sí",IF(AS4="regla",IF(AND(N(AQ4)=0,CH4=1),"sí","no"),"no")) | CN4: =IFERROR(VLOOKUP(F4,MOD_TBL,16,0),IFERROR(VLOOKUP(E4,OCU_TBL,2,0),NEUTRO)) | CO4: =SUMIFS(MOT_AJUSTE,MOT_MOTOR,G4,MOT_MARCA,E4,MOT_DESDE,"<="&M4,MOT_HASTA,">="&M4)+SUMIFS(MOT_AJUSTE,MOT_MOTOR,G4,MOT_MARCA,"(todas)",MOT_DESDE,"<="&M4,MOT_HASTA,">="&M4)+SUMIFS(MOT_AJUSTE,MOT_MOTOR,"(cualquiera)",MOT_MARCA,E4,MOT_DESDE,"<="&M4,MOT_HASTA,">="&M4) | CP4: =SUMIFS(COMB_AJUSTE,COMB_COMB,K4) | CQ4: =COUNTIFS(MOT_MOTOR,G4,MOT_MARCA,E4,MOT_DESDE,"<="&M4,MOT_HASTA,">="&M4)+COUNTIFS(MOT_MOTOR,G4,MOT_MARCA,"(todas)",MOT_DESDE,"<="&M4,MOT_HASTA,">="&M4)+COUNTIFS(MOT_MOTOR,"(cualquiera)",MOT_MARCA,E4,MOT_DESDE,"<="&M4,MOT_HASTA,">="&M4) | CR4: =IF(AND(K4="diesel",CQ4=0),MIN(CN4,NEUTRO),CN4) | CS4: =MAX(0,MIN(100,CR4+CO4+CP4-IF(AX4="sí",ROB_PEN,0))) | CT4: =100-MAX(0,N4-KM_TOPE_DESDE)/1000*KM_TOPE_PTS | CU4: =MAX(0,MIN(100,50+CG4*PRECIO_PEND,CT4)) | CV4: =MAX(0,100*(1-N4/KM_MAX)) | CW4: =IF(BX4<KMA_SOSP,IF(AA4="sí",100,KMA_PEN),IF(BX4<=KMA_IDEAL_MAX,100,MAX(0,100*(KMA_CERO-BX4)/(KMA_CERO-KMA_IDEAL_MAX)))) | CX4: =MAX(0,MIN(100,100*(M4-ANIO_MIN)/(ANIO_ACTUAL-ANIO_MIN))) | CY4: =W_KMT*CV4+W_KMA*CW4+W_EDAD*CX4 | CZ4: =E4&"|"&G4 | DA4: =IFERROR(VLOOKUP(CZ4,DIST_TBL,2,0),"") | DB4: =E_ITV*(V4="sí")+E_LIBRO*(W4="sí")+E_PROP*IF(Y4=1,1,IF(Y4=2,0.5,0))+E_CORREA*IF(OR(DA4="cadena",AND(X4="sí",BH4="sí")),1,IF(X4="sí",0.5,0))+E_FACT*(BI4="sí") | DC4: =MAX(0,MIN(100,IFERROR(VLOOKUP(CL4,ETQ_TBL,2,0),0)-IF(CM4="sí",ETQ_PEN_DUD,IF(AS4="regla",ETQ_PEN_REGLA,0)))) | DD4: =IF(K4<>"gasolina","",IFERROR(VLOOKUP(F4,CONS_MOD_TBL,2,0),IFERROR(VLOOKUP(L4,CONS_SEG_TBL,2,0),""))) | DE4: =IF(DD4="",NEUTRO,MAX(0,MIN(100,100*(CONS_REF_MAX-DD4)/(CONS_REF_MAX-CONS_REF_MIN)))) | DF4: =IFERROR(VLOOKUP(L4,SEGURO_TBL,3,0),"") | DG4: =IF(DF4="",NEUTRO,MAX(0,MIN(100,100*(SEG_REF_MAX-DF4)/(SEG_REF_MAX-SEG_REF_MIN)))) | DH4: =IFERROR(VLOOKUP(E4,MANT_MARCA_TBL,2,0)+0,NEUTRO) | DI4: =IF(DA4="",NEUTRO,IFERROR(VLOOKUP(DA4,DIST_PTS_TBL,2,0)+0,NEUTRO)) | DJ4: =(DH4+DI4)/2 | DK4: =W_CONS*DE4+W_SEG*DG4+W_MANT*DJ4 | DL4: =IF(N(AB4)>0,AB4,IF(AND(R4="profesional",SG_LEGAL_ON=1),GAR_LEGAL,0)) | DM4: =MAX(0,MIN(100,SG_GAR*MIN(1,DL4/SG_GAR_FULL)+SG_AMPL*(AC4="sí")+SG_KMC*(AF4="sí")+SG_REV*(N(AE4)>0)+SG_DEV*MIN(1,N(AG4)/SG_DEV_FULL)+SG_HIST*(W4="sí")-IF(AND(R4="particular",DL4=0),SG_PART_PEN,0))) | DN4: =IF(BK4="",NEUTRO,MAX(0,MIN(100,BK4/5*100))) | DO4: =IF(BL4="sí",100,IF(BL4="no",0,NEUTRO)) | DP4: =SV_W_NCAP*DN4+SV_W_ESP*DO4 | DQ4: =MAX(0,MIN(100,ATR_BASE+ATR_ACAB*(BD4<>"")+IF(BE4="16+",ATR_LL16,IF(BE4="sí",ATR_LL,0))+ATR_FAROS*(BF4="sí")+ATR_TINT*(BG4="sí")-ATR_CHAPA*(BE4="chapa"))) | DR4: =EST_W_MOD*(BB4-1)/4*100+EST_W_ATR*DQ4 | DS4: =IF(BA4="",NEUTRO,IFERROR(VLOOKUP(BA4,COLOR_TBL,2,0)+0,NEUTRO)) | DT4: =MAX(0,MIN(100,100*N(BM4)/RV_N_FULL)) | DU4: =IF(OR(BN4="",N(BO4)<RV_DIAS_MIN),NEUTRO,MAX(0,MIN(100,100*(RV_DIAS_CERO-BN4)/(RV_DIAS_CERO-RV_DIAS_FULL)))) | DV4: =RV_W_LIQ*DT4+RV_W_DIAS*DU4+RV_W_ETQ*DC4 | DW4: =IFERROR(VLOOKUP(L4,CARR_PEN_TBL,2,0),0) | DX4: =W_FIAB*CS4+W_PRECIO*CU4+W_KMEDAD*CY4+W_ESTADO*DB4+W_USO*DK4+W_SEGURIDAD*DM4+W_SEGVIAL*DP4+W_ESTETICA*DR4+W_COLOR*DS4+W_REVENTA*DV4-DW4-EG4 | DY4: =IF(N(I4)>0,I4,IFERROR(ROUND(_xlfn.NUMBERVALUE(LEFT(G4,FIND(" ",G4&" ")-1),".")*1000,0),99999)) | DZ4: =IF(R4="profesional",0,IF(O4<CUOTA_VALOR_MAX,IF(BW4>ITP_TRAMO_ALTO,SUMIFS(CF_CUOTA,CF_MAS,ITP_TRAMO_ALTO,CF_CCMIN,"<="&DY4,CF_CCMAX,">="&DY4),IF(BW4>ITP_TRAMO_BAJO,SUMIFS(CF_CUOTA,CF_MAS,ITP_TRAMO_BAJO,CF_CCMIN,"<="&DY4,CF_CCMAX,">="&DY4),O4*ITP_TIPO)),O4*ITP_TIPO)) | EA4: =IF(R4="profesional",N(AK4),0) | EB4: =IF(AND(R4="profesional",ISNUMBER(AK4),AL4="sí"),0,TASA_DGT) | EC4: =INFORME_DGT | ED4: =O4+EA4+DZ4+EB4+EC4 | EE4: =ED4+N(DF4) | EF4: =MAX(0,ED4-TOTAL_MAX) | EG4: =EF4/100*PEN_100 | EH4: =IF(R4="particular",ED4+IF(AND(DA4<>"cadena",X4<>"sí"),RES_CORREA,0)+IF(AND(BJ4<>"sí",BW4>=RES_NEUM_EDAD),RES_NEUM,0),"") | EI4: =IF(ED4<=TOTAL_MAX,"sí",IF(ED4<=TECHO,"negociar","no")) | EJ4: =ROUND(DX4,9) | EK4: =IF(EI4<>"no",SUMPRODUCT(($EI$2:$EI$209<>"no")*($EJ$2:$EJ$209>EJ4))+SUMPRODUCT(($EI$2:EI4<>"no")*($EJ$2:EJ4=EJ4)),"")
A5: autoscout24:eff1fd1c-995f-4e05-b13f-0025ae2ba8f5 | B5: autoscout24 | C5: https://www.autoscout24.es/anuncios/opel-astra-1-7cdti-enjoy-diesel-azul-cat_ma54mo1916-eff1fd1c-995f-4e05-b13f-0025ae2ba8f5 | D5: Opel Astra 1.7CDTi Enjoy | E5: Opel | F5: Opel Astra | G5: 1.7 | H5: 1.7CDTi Enjoy 1.7 | I5: 1686 | J5: 99 | K5: diesel | L5: compacto | M5: 2008 | N5: 180065 | O5: 3599 | P5: manual | Q5: no | R5: profesional | S5: AUTOS XUQUER — SUECA (46410) | U5: 12 | V5: sí | Z5: sí | AB5: 12 | AM5: 30.8 | AO5: 2008-03 | AP5: 2008 | AQ5: 3 | AS5: regla | AU5: no | AV5: B | AX5: no | AY5: no | AZ5: Azul | BA5: azul | BB5: 3 | BC5: (por segmento) | BE5: sí | BK5: 5 | BM5: 402 | BN5: 0.062800926 | BO5: 4 | BP5: 4300 | BQ5: 18 | BR5: modelo+año+km | BT5: vendedor profesional: sin ITP (operación con IVA/REBU, confirmar en factura); gastos de gestión del vendedor no indicados: se suma la tasa DGT; preguntar el precio final; diésel: motor sin fuente de fiabilidad (fiabilidad limitada a neutra); etiqueta B deducida por fecha (sin matrícula ni dato del anuncio) | BU5: Opel Astra SW 1.7 CDTI Familiar, espacioso y muy económico<br />¿Buscas un coche espacioso, fiable y que no te haga temblar cada vez que vas a la gasolinera? Este Opel Astra SW es la combinación perfecta entre practicidad para el día a día y confort para viajar.<br />Con su motor 1.7 CDTI de 100 CV, te llevas uno de los motores diésel más duros y contrastados del mercado: consumo muy ajustado y mantenimiento económico. Además, su carrocería familiar te ofrece un maletero amplísimo con boca de carga baja, ideal para familias, viajes con equipaje o para quien necesita espacio extra sin renunciar a la agilidad de un turismo.<br />Volante con control velocidad de crucero, Radio CD, Aire Acondicionado, llantas de aleación, amplio maletero, elevalunas eléctricos. Cuenta con Baca porta equipajes.<br />Coche económico, con revisiones e ITV al dia.<br />En Autos Xúquer Albelda entregamos todos nuestros vehículos totalmente revisados y con garantía de 12 meses incluida. La financiación es 100 % flexible y sin trámites complicados, y te asesoramos en todo el proceso, antes y después de la compra. <br />Cambio de nombre no incluido (+200 €). <br />Visítanos en Sueca (Valencia) o escríbenos para concertar una prueba sin ningún compromiso.<br />Este anuncio no es vinculante y puede contener errores.<br /><br /><br /> | BV5: https://www.autoscout24.es/anuncios/opel-astra-1-7cdti-enjoy-diesel-azul-cat_ma54mo1916-eff1fd1c-995f-4e05-b13f-0025ae2ba8f5 (__NEXT_DATA__ listingDetails) /home/user/Alopecia/buscador-coches/raw/autoscout24/f2becdc4ebbeca89.json | BW5: =MAX(ANIO_ACTUAL-M5,0) | BX5: =N5/MAX(BW5,0.5) | BY5: =F5 | BZ5: =BY5&"|"&INT(M5/SEG_ANIO)*SEG_ANIO | CA5: =BZ5&"|"&INT(N5/SEG_KM)*SEG_KM | CB5: =COUNTIF($BY$2:$BY$209,BY5) | CC5: =COUNTIF($BZ$2:$BZ$209,BZ5) | CD5: =COUNTIF($CA$2:$CA$209,CA5) | CE5: {=IF(N(BQ5)>=MIN_N,BP5,IF(CD5>=MIN_N,MEDIAN(IF($CA$2:$CA$209=CA5,$O$2:$O$209)),IF(CC5>=MIN_N,MEDIAN(IF($BZ$2:$BZ$209=BZ5,$O$2:$O$209)),MEDIAN(IF($BY$2:$BY$209=BY5,$O$2:$O$209)))))} | CF5: =IF(N(BQ5)>=MIN_N,"mercado "&BR5,IF(CD5>=MIN_N,"modelo+año+km",IF(CC5>=MIN_N,"modelo+año","modelo"))) | CG5: =(CE5-O5)/CE5 | CH5: =IF(COUNTIFS(FR_FUEL,K5,FR_YEAR,AP5)>0,1,0) | CI5: =IF(COUNTIFS(FR_FUEL,K5,FR_YEAR,AP5-1)>0,1,0) | CJ5: =IF(N(AQ5)>0,AP5*100+AQ5,IF(AND(CH5=1,CI5=1),(AP5-1)*100+1,AP5*100+1)) | CK5: =IF(OR(K5="hibrido",K5="glp",K5="gnc",K5="phev"),"ECO",IF(K5="electrico","CERO",IF(K5="gasolina",IF(CJ5>=GAS_C_YM,"C",IF(CJ5>=GAS_B_YM,"B","A")),IF(K5="diesel",IF(CJ5>=DIE_C_YM,"C",IF(CJ5>=DIE_B_YM,"B","A")),"")))) | CL5: =CK5 | CM5: =IF(AU5="sí","sí",IF(AS5="regla",IF(AND(N(AQ5)=0,CH5=1),"sí","no"),"no")) | CN5: =IFERROR(VLOOKUP(F5,MOD_TBL,16,0),IFERROR(VLOOKUP(E5,OCU_TBL,2,0),NEUTRO)) | CO5: =SUMIFS(MOT_AJUSTE,MOT_MOTOR,G5,MOT_MARCA,E5,MOT_DESDE,"<="&M5,MOT_HASTA,">="&M5)+SUMIFS(MOT_AJUSTE,MOT_MOTOR,G5,MOT_MARCA,"(todas)",MOT_DESDE,"<="&M5,MOT_HASTA,">="&M5)+SUMIFS(MOT_AJUSTE,MOT_MOTOR,"(cualquiera)",MOT_MARCA,E5,MOT_DESDE,"<="&M5,MOT_HASTA,">="&M5) | CP5: =SUMIFS(COMB_AJUSTE,COMB_COMB,K5) | CQ5: =COUNTIFS(MOT_MOTOR,G5,MOT_MARCA,E5,MOT_DESDE,"<="&M5,MOT_HASTA,">="&M5)+COUNTIFS(MOT_MOTOR,G5,MOT_MARCA,"(todas)",MOT_DESDE,"<="&M5,MOT_HASTA,">="&M5)+COUNTIFS(MOT_MOTOR,"(cualquiera)",MOT_MARCA,E5,MOT_DESDE,"<="&M5,MOT_HASTA,">="&M5) | CR5: =IF(AND(K5="diesel",CQ5=0),MIN(CN5,NEUTRO),CN5) | CS5: =MAX(0,MIN(100,CR5+CO5+CP5-IF(AX5="sí",ROB_PEN,0))) | CT5: =100-MAX(0,N5-KM_TOPE_DESDE)/1000*KM_TOPE_PTS | CU5: =MAX(0,MIN(100,50+CG5*PRECIO_PEND,CT5)) | CV5: =MAX(0,100*(1-N5/KM_MAX)) | CW5: =IF(BX5<KMA_SOSP,IF(AA5="sí",100,KMA_PEN),IF(BX5<=KMA_IDEAL_MAX,100,MAX(0,100*(KMA_CERO-BX5)/(KMA_CERO-KMA_IDEAL_MAX)))) | CX5: =MAX(0,MIN(100,100*(M5-ANIO_MIN)/(ANIO_ACTUAL-ANIO_MIN))) | CY5: =W_KMT*CV5+W_KMA*CW5+W_EDAD*CX5 | CZ5: =E5&"|"&G5 | DA5: =IFERROR(VLOOKUP(CZ5,DIST_TBL,2,0),"") | DB5: =E_ITV*(V5="sí")+E_LIBRO*(W5="sí")+E_PROP*IF(Y5=1,1,IF(Y5=2,0.5,0))+E_CORREA*IF(OR(DA5="cadena",AND(X5="sí",BH5="sí")),1,IF(X5="sí",0.5,0))+E_FACT*(BI5="sí") | DC5: =MAX(0,MIN(100,IFERROR(VLOOKUP(CL5,ETQ_TBL,2,0),0)-IF(CM5="sí",ETQ_PEN_DUD,IF(AS5="regla",ETQ_PEN_REGLA,0)))) | DD5: =IF(K5<>"gasolina","",IFERROR(VLOOKUP(F5,CONS_MOD_TBL,2,0),IFERROR(VLOOKUP(L5,CONS_SEG_TBL,2,0),""))) | DE5: =IF(DD5="",NEUTRO,MAX(0,MIN(100,100*(CONS_REF_MAX-DD5)/(CONS_REF_MAX-CONS_REF_MIN)))) | DF5: =IFERROR(VLOOKUP(L5,SEGURO_TBL,3,0),"") | DG5: =IF(DF5="",NEUTRO,MAX(0,MIN(100,100*(SEG_REF_MAX-DF5)/(SEG_REF_MAX-SEG_REF_MIN)))) | DH5: =IFERROR(VLOOKUP(E5,MANT_MARCA_TBL,2,0)+0,NEUTRO) | DI5: =IF(DA5="",NEUTRO,IFERROR(VLOOKUP(DA5,DIST_PTS_TBL,2,0)+0,NEUTRO)) | DJ5: =(DH5+DI5)/2 | DK5: =W_CONS*DE5+W_SEG*DG5+W_MANT*DJ5 | DL5: =IF(N(AB5)>0,AB5,IF(AND(R5="profesional",SG_LEGAL_ON=1),GAR_LEGAL,0)) | DM5: =MAX(0,MIN(100,SG_GAR*MIN(1,DL5/SG_GAR_FULL)+SG_AMPL*(AC5="sí")+SG_KMC*(AF5="sí")+SG_REV*(N(AE5)>0)+SG_DEV*MIN(1,N(AG5)/SG_DEV_FULL)+SG_HIST*(W5="sí")-IF(AND(R5="particular",DL5=0),SG_PART_PEN,0))) | DN5: =IF(BK5="",NEUTRO,MAX(0,MIN(100,BK5/5*100))) | DO5: =IF(BL5="sí",100,IF(BL5="no",0,NEUTRO)) | DP5: =SV_W_NCAP*DN5+SV_W_ESP*DO5 | DQ5: =MAX(0,MIN(100,ATR_BASE+ATR_ACAB*(BD5<>"")+IF(BE5="16+",ATR_LL16,IF(BE5="sí",ATR_LL,0))+ATR_FAROS*(BF5="sí")+ATR_TINT*(BG5="sí")-ATR_CHAPA*(BE5="chapa"))) | DR5: =EST_W_MOD*(BB5-1)/4*100+EST_W_ATR*DQ5 | DS5: =IF(BA5="",NEUTRO,IFERROR(VLOOKUP(BA5,COLOR_TBL,2,0)+0,NEUTRO)) | DT5: =MAX(0,MIN(100,100*N(BM5)/RV_N_FULL)) | DU5: =IF(OR(BN5="",N(BO5)<RV_DIAS_MIN),NEUTRO,MAX(0,MIN(100,100*(RV_DIAS_CERO-BN5)/(RV_DIAS_CERO-RV_DIAS_FULL)))) | DV5: =RV_W_LIQ*DT5+RV_W_DIAS*DU5+RV_W_ETQ*DC5 | DW5: =IFERROR(VLOOKUP(L5,CARR_PEN_TBL,2,0),0) | DX5: =W_FIAB*CS5+W_PRECIO*CU5+W_KMEDAD*CY5+W_ESTADO*DB5+W_USO*DK5+W_SEGURIDAD*DM5+W_SEGVIAL*DP5+W_ESTETICA*DR5+W_COLOR*DS5+W_REVENTA*DV5-DW5-EG5 | DY5: =IF(N(I5)>0,I5,IFERROR(ROUND(_xlfn.NUMBERVALUE(LEFT(G5,FIND(" ",G5&" ")-1),".")*1000,0),99999)) | DZ5: =IF(R5="profesional",0,IF(O5<CUOTA_VALOR_MAX,IF(BW5>ITP_TRAMO_ALTO,SUMIFS(CF_CUOTA,CF_MAS,ITP_TRAMO_ALTO,CF_CCMIN,"<="&DY5,CF_CCMAX,">="&DY5),IF(BW5>ITP_TRAMO_BAJO,SUMIFS(CF_CUOTA,CF_MAS,ITP_TRAMO_BAJO,CF_CCMIN,"<="&DY5,CF_CCMAX,">="&DY5),O5*ITP_TIPO)),O5*ITP_TIPO)) | EA5: =IF(R5="profesional",N(AK5),0) | EB5: =IF(AND(R5="profesional",ISNUMBER(AK5),AL5="sí"),0,TASA_DGT) | EC5: =INFORME_DGT | ED5: =O5+EA5+DZ5+EB5+EC5 | EE5: =ED5+N(DF5) | EF5: =MAX(0,ED5-TOTAL_MAX) | EG5: =EF5/100*PEN_100 | EH5: =IF(R5="particular",ED5+IF(AND(DA5<>"cadena",X5<>"sí"),RES_CORREA,0)+IF(AND(BJ5<>"sí",BW5>=RES_NEUM_EDAD),RES_NEUM,0),"") | EI5: =IF(ED5<=TOTAL_MAX,"sí",IF(ED5<=TECHO,"negociar","no")) | EJ5: =ROUND(DX5,9) | EK5: =IF(EI5<>"no",SUMPRODUCT(($EI$2:$EI$209<>"no")*($EJ$2:$EJ$209>EJ5))+SUMPRODUCT(($EI$2:EI5<>"no")*($EJ$2:EJ5=EJ5)),"")
A6: autoscout24:9a094bfd-f634-4d5d-9612-b134882a2a0b | B6: autoscout24 | C6: https://www.autoscout24.es/anuncios/opel-corsa-1-3cdti-c-mon-ecoflex-diesel-cat_ma54mo1918-9a094bfd-f634-4d5d-9612-b134882a2a0b | D6: Opel Corsa 1.3CDTi C Mon ecoFlex | E6: Opel | F6: Opel Corsa | G6: 1.2 CDTi | H6: 1.3CDTi C Mon ecoFlex 1.3 CDTI | I6: 1248 | J6: 75 | K6: diesel | L6: utilitario | M6: 2009 | N6: 172000 | O6: 3990 | P6: manual | Q6: no | R6: profesional | S6: ORLANDO CARS — PATERNA (46980) | U6: 37 | V6: sí | Z6: sí | AB6: 12 | AH6: 3990 | AI6: 3990 | AM6: 9.4 | AO6: 2009-06 | AP6: 2009 | AQ6: 6 | AS6: regla | AU6: no | AV6: B | AX6: no | AY6: no | BB6: 2 | BC6: (por segmento) | BE6: sí | BK6: 5 | BM6: 456 | BN6: 0.051261574 | BO6: 11 | BP6: 3150 | BQ6: 8 | BR6: modelo+año+km | BT6: vendedor profesional: sin ITP (operación con IVA/REBU, confirmar en factura); gastos de gestión del vendedor no indicados: se suma la tasa DGT; preguntar el precio final; diésel: motor sin fuente de fiabilidad (fiabilidad limitada a neutra); etiqueta B deducida por fecha (sin matrícula ni dato del anuncio) | BU6: <strong>Precio al contado: 3990 euros</strong> <br /><br /><strong>Condiciones de la financiación</strong> <br /><br />Precio al contado: 3.990€<br />Precio financiado: 3.990€<br /><br /> <br /><br /><strong>OPEL CORSA ECOFLEX 1.3 75CV</strong><br /><strong> </strong><br /><strong>Nacional – Año 2009</strong><br /><strong>Diesel – Con 172.000Km</strong><br /><strong> </strong><br />Equipado con: -3 Puertas. -2 Llaves. -Bajo consumo. -Radio. -CD. -USB. -AUX. . -Aire acondicionado. -Cierre centralizado. -Airbag. -Elevalunas eléctricos. -Retrovisores eléctricos. -Rueda de repuesto.<br /> <br />Precio al contado: 3.990€<br />Precio financiado: 3.990€<br /> <br /> <br />Aceptamos vehículo como parte de pago. Financiación a medida. Se entrega totalmente revisado, con ITV al día, y 12 meses de garantía. Para más información, estaremos encantados de atenderle en nuestras instalaciones en c/ Ciutat de Llíria, Nº 61 en polígono industrial fuente del jarro, paterna. (cerca de Mislata, Burjasot, Llíria, Bétera, Manises).<br /> <br />Este anuncio es de carácter informativo. Las especificaciones sobre equipamiento, modelo y precio no tienen carácter vinculante, ni puede constituir base de un futuro contrato ya que pueden contener algún error. Consulte con nuestros comerciales la información detallada de este vehículo.<br /> | BV6: https://www.autoscout24.es/anuncios/opel-corsa-1-3cdti-c-mon-ecoflex-diesel-cat_ma54mo1918-9a094bfd-f634-4d5d-9612-b134882a2a0b (__NEXT_DATA__ listingDetails) /home/user/Alopecia/buscador-coches/raw/autoscout24/1927e479532d8469.json | BW6: =MAX(ANIO_ACTUAL-M6,0) | BX6: =N6/MAX(BW6,0.5) | BY6: =F6 | BZ6: =BY6&"|"&INT(M6/SEG_ANIO)*SEG_ANIO | CA6: =BZ6&"|"&INT(N6/SEG_KM)*SEG_KM | CB6: =COUNTIF($BY$2:$BY$209,BY6) | CC6: =COUNTIF($BZ$2:$BZ$209,BZ6) | CD6: =COUNTIF($CA$2:$CA$209,CA6) | CE6: {=IF(N(BQ6)>=MIN_N,BP6,IF(CD6>=MIN_N,MEDIAN(IF($CA$2:$CA$209=CA6,$O$2:$O$209)),IF(CC6>=MIN_N,MEDIAN(IF($BZ$2:$BZ$209=BZ6,$O$2:$O$209)),MEDIAN(IF($BY$2:$BY$209=BY6,$O$2:$O$209)))))} | CF6: =IF(N(BQ6)>=MIN_N,"mercado "&BR6,IF(CD6>=MIN_N,"modelo+año+km",IF(CC6>=MIN_N,"modelo+año","modelo"))) | CG6: =(CE6-O6)/CE6 | CH6: =IF(COUNTIFS(FR_FUEL,K6,FR_YEAR,AP6)>0,1,0) | CI6: =IF(COUNTIFS(FR_FUEL,K6,FR_YEAR,AP6-1)>0,1,0) | CJ6: =IF(N(AQ6)>0,AP6*100+AQ6,IF(AND(CH6=1,CI6=1),(AP6-1)*100+1,AP6*100+1)) | CK6: =IF(OR(K6="hibrido",K6="glp",K6="gnc",K6="phev"),"ECO",IF(K6="electrico","CERO",IF(K6="gasolina",IF(CJ6>=GAS_C_YM,"C",IF(CJ6>=GAS_B_YM,"B","A")),IF(K6="diesel",IF(CJ6>=DIE_C_YM,"C",IF(CJ6>=DIE_B_YM,"B","A")),"")))) | CL6: =CK6 | CM6: =IF(AU6="sí","sí",IF(AS6="regla",IF(AND(N(AQ6)=0,CH6=1),"sí","no"),"no")) | CN6: =IFERROR(VLOOKUP(F6,MOD_TBL,16,0),IFERROR(VLOOKUP(E6,OCU_TBL,2,0),NEUTRO)) | CO6: =SUMIFS(MOT_AJUSTE,MOT_MOTOR,G6,MOT_MARCA,E6,MOT_DESDE,"<="&M6,MOT_HASTA,">="&M6)+SUMIFS(MOT_AJUSTE,MOT_MOTOR,G6,MOT_MARCA,"(todas)",MOT_DESDE,"<="&M6,MOT_HASTA,">="&M6)+SUMIFS(MOT_AJUSTE,MOT_MOTOR,"(cualquiera)",MOT_MARCA,E6,MOT_DESDE,"<="&M6,MOT_HASTA,">="&M6) | CP6: =SUMIFS(COMB_AJUSTE,COMB_COMB,K6) | CQ6: =COUNTIFS(MOT_MOTOR,G6,MOT_MARCA,E6,MOT_DESDE,"<="&M6,MOT_HASTA,">="&M6)+COUNTIFS(MOT_MOTOR,G6,MOT_MARCA,"(todas)",MOT_DESDE,"<="&M6,MOT_HASTA,">="&M6)+COUNTIFS(MOT_MOTOR,"(cualquiera)",MOT_MARCA,E6,MOT_DESDE,"<="&M6,MOT_HASTA,">="&M6) | CR6: =IF(AND(K6="diesel",CQ6=0),MIN(CN6,NEUTRO),CN6) | CS6: =MAX(0,MIN(100,CR6+CO6+CP6-IF(AX6="sí",ROB_PEN,0))) | CT6: =100-MAX(0,N6-KM_TOPE_DESDE)/1000*KM_TOPE_PTS | CU6: =MAX(0,MIN(100,50+CG6*PRECIO_PEND,CT6)) | CV6: =MAX(0,100*(1-N6/KM_MAX)) | CW6: =IF(BX6<KMA_SOSP,IF(AA6="sí",100,KMA_PEN),IF(BX6<=KMA_IDEAL_MAX,100,MAX(0,100*(KMA_CERO-BX6)/(KMA_CERO-KMA_IDEAL_MAX)))) | CX6: =MAX(0,MIN(100,100*(M6-ANIO_MIN)/(ANIO_ACTUAL-ANIO_MIN))) | CY6: =W_KMT*CV6+W_KMA*CW6+W_EDAD*CX6 | CZ6: =E6&"|"&G6 | DA6: =IFERROR(VLOOKUP(CZ6,DIST_TBL,2,0),"") | DB6: =E_ITV*(V6="sí")+E_LIBRO*(W6="sí")+E_PROP*IF(Y6=1,1,IF(Y6=2,0.5,0))+E_CORREA*IF(OR(DA6="cadena",AND(X6="sí",BH6="sí")),1,IF(X6="sí",0.5,0))+E_FACT*(BI6="sí") | DC6: =MAX(0,MIN(100,IFERROR(VLOOKUP(CL6,ETQ_TBL,2,0),0)-IF(CM6="sí",ETQ_PEN_DUD,IF(AS6="regla",ETQ_PEN_REGLA,0)))) | DD6: =IF(K6<>"gasolina","",IFERROR(VLOOKUP(F6,CONS_MOD_TBL,2,0),IFERROR(VLOOKUP(L6,CONS_SEG_TBL,2,0),""))) | DE6: =IF(DD6="",NEUTRO,MAX(0,MIN(100,100*(CONS_REF_MAX-DD6)/(CONS_REF_MAX-CONS_REF_MIN)))) | DF6: =IFERROR(VLOOKUP(L6,SEGURO_TBL,3,0),"") | DG6: =IF(DF6="",NEUTRO,MAX(0,MIN(100,100*(SEG_REF_MAX-DF6)/(SEG_REF_MAX-SEG_REF_MIN)))) | DH6: =IFERROR(VLOOKUP(E6,MANT_MARCA_TBL,2,0)+0,NEUTRO) | DI6: =IF(DA6="",NEUTRO,IFERROR(VLOOKUP(DA6,DIST_PTS_TBL,2,0)+0,NEUTRO)) | DJ6: =(DH6+DI6)/2 | DK6: =W_CONS*DE6+W_SEG*DG6+W_MANT*DJ6 | DL6: =IF(N(AB6)>0,AB6,IF(AND(R6="profesional",SG_LEGAL_ON=1),GAR_LEGAL,0)) | DM6: =MAX(0,MIN(100,SG_GAR*MIN(1,DL6/SG_GAR_FULL)+SG_AMPL*(AC6="sí")+SG_KMC*(AF6="sí")+SG_REV*(N(AE6)>0)+SG_DEV*MIN(1,N(AG6)/SG_DEV_FULL)+SG_HIST*(W6="sí")-IF(AND(R6="particular",DL6=0),SG_PART_PEN,0))) | DN6: =IF(BK6="",NEUTRO,MAX(0,MIN(100,BK6/5*100))) | DO6: =IF(BL6="sí",100,IF(BL6="no",0,NEUTRO)) | DP6: =SV_W_NCAP*DN6+SV_W_ESP*DO6 | DQ6: =MAX(0,MIN(100,ATR_BASE+ATR_ACAB*(BD6<>"")+IF(BE6="16+",ATR_LL16,IF(BE6="sí",ATR_LL,0))+ATR_FAROS*(BF6="sí")+ATR_TINT*(BG6="sí")-ATR_CHAPA*(BE6="chapa"))) | DR6: =EST_W_MOD*(BB6-1)/4*100+EST_W_ATR*DQ6 | DS6: =IF(BA6="",NEUTRO,IFERROR(VLOOKUP(BA6,COLOR_TBL,2,0)+0,NEUTRO)) | DT6: =MAX(0,MIN(100,100*N(BM6)/RV_N_FULL)) | DU6: =IF(OR(BN6="",N(BO6)<RV_DIAS_MIN),NEUTRO,MAX(0,MIN(100,100*(RV_DIAS_CERO-BN6)/(RV_DIAS_CERO-RV_DIAS_FULL)))) | DV6: =RV_W_LIQ*DT6+RV_W_DIAS*DU6+RV_W_ETQ*DC6 | DW6: =IFERROR(VLOOKUP(L6,CARR_PEN_TBL,2,0),0) | DX6: =W_FIAB*CS6+W_PRECIO*CU6+W_KMEDAD*CY6+W_ESTADO*DB6+W_USO*DK6+W_SEGURIDAD*DM6+W_SEGVIAL*DP6+W_ESTETICA*DR6+W_COLOR*DS6+W_REVENTA*DV6-DW6-EG6 | DY6: =IF(N(I6)>0,I6,IFERROR(ROUND(_xlfn.NUMBERVALUE(LEFT(G6,FIND(" ",G6&" ")-1),".")*1000,0),99999)) | DZ6: =IF(R6="profesional",0,IF(O6<CUOTA_VALOR_MAX,IF(BW6>ITP_TRAMO_ALTO,SUMIFS(CF_CUOTA,CF_MAS,ITP_TRAMO_ALTO,CF_CCMIN,"<="&DY6,CF_CCMAX,">="&DY6),IF(BW6>ITP_TRAMO_BAJO,SUMIFS(CF_CUOTA,CF_MAS,ITP_TRAMO_BAJO,CF_CCMIN,"<="&DY6,CF_CCMAX,">="&DY6),O6*ITP_TIPO)),O6*ITP_TIPO)) | EA6: =IF(R6="profesional",N(AK6),0) | EB6: =IF(AND(R6="profesional",ISNUMBER(AK6),AL6="sí"),0,TASA_DGT) | EC6: =INFORME_DGT | ED6: =O6+EA6+DZ6+EB6+EC6 | EE6: =ED6+N(DF6) | EF6: =MAX(0,ED6-TOTAL_MAX) | EG6: =EF6/100*PEN_100 | EH6: =IF(R6="particular",ED6+IF(AND(DA6<>"cadena",X6<>"sí"),RES_CORREA,0)+IF(AND(BJ6<>"sí",BW6>=RES_NEUM_EDAD),RES_NEUM,0),"") | EI6: =IF(ED6<=TOTAL_MAX,"sí",IF(ED6<=TECHO,"negociar","no")) | EJ6: =ROUND(DX6,9) | EK6: =IF(EI6<>"no",SUMPRODUCT(($EI$2:$EI$209<>"no")*($EJ$2:$EJ$209>EJ6))+SUMPRODUCT(($EI$2:EI6<>"no")*($EJ$2:EJ6=EJ6)),"")
A7: wallapop:1313427276 | B7: wallapop | C7: https://es.wallapop.com/item/ford-fiesta-ford-fiesta-1-3-ambiente-1313427276 | D7: Ford Fiesta Ford Fiesta 1.3 Ambiente | E7: Ford | F7: Ford Fiesta | G7: 1.3 | H7: Ford Fiesta 1.3 Ambiente | J7: 70 | K7: gasolina | L7: utilitario | M7: 2008 | N7: 82000 | O7: 3500 | P7: manual | Q7: no | R7: profesional | S7: Manises (46940) | T7: 2026-10-30T18:10:07 | U7: 9 | AM7: 7.2 | AO7: 2008 | AP7: 2008 | AS7: regla | AU7: no | AV7: C | AX7: no | AY7: no | BB7: 2 | BC7: (por segmento) | BK7: 4 | BL7: no | BM7: 302 | BN7: 0.074340278 | BO7: 3 | BP7: 3500 | BQ7: 48 | BR7: modelo+año | BS7: autoscout24:cb47557d-00cb-449b-8153-e5de1e64bdaf (https://www.autoscout24.es/anuncios/ford-fiesta-1-3-ambiente-gasolina-gris-cat_ma29mo1758-cb47557d-00cb-449b-8153-e5de1e64bdaf) | BT7: vendedor profesional: sin ITP (operación con IVA/REBU, confirmar en factura); gastos de gestión del vendedor no indicados: se suma la tasa DGT; preguntar el precio final; etiqueta C deducida por fecha (sin matrícula ni dato del anuncio); revisar: no menciona la ITV | BU7: 🔹- con posibilidad de financiar desde 🔹79€ al mes-🤝🚗 🔹-Ford fiesta 2008 🔹-1.3 60cv gasolina( a cadena) 🔹-82.000 kilómetros 🔹-se entrega totalmente al día 🔹- 1 año de garantía 🔺-3.500€🔻 -SE ACEPTA COCHE INFERIOR COMO PARTE DE PAGO!!🤝🚗 -tiktok @eurocochesmanival -instam eloy_manival (Mini,208,Clío,micra,Ibiza,kalos,picanto,i10,i20,Mazda 2,Golf,polo,a3,Leon,Ibiza,i30,Astra,Megane,307) | BV7: https://es.wallapop.com/item/ford-fiesta-ford-fiesta-1-3-ambiente-1313427276 (__NEXT_DATA__ item) /home/user/Alopecia/buscador-coches/raw/wallapop/564731e59dcd7515.json | BW7: =MAX(ANIO_ACTUAL-M7,0) | BX7: =N7/MAX(BW7,0.5) | BY7: =F7 | BZ7: =BY7&"|"&INT(M7/SEG_ANIO)*SEG_ANIO | CA7: =BZ7&"|"&INT(N7/SEG_KM)*SEG_KM | CB7: =COUNTIF($BY$2:$BY$209,BY7) | CC7: =COUNTIF($BZ$2:$BZ$209,BZ7) | CD7: =COUNTIF($CA$2:$CA$209,CA7) | CE7: {=IF(N(BQ7)>=MIN_N,BP7,IF(CD7>=MIN_N,MEDIAN(IF($CA$2:$CA$209=CA7,$O$2:$O$209)),IF(CC7>=MIN_N,MEDIAN(IF($BZ$2:$BZ$209=BZ7,$O$2:$O$209)),MEDIAN(IF($BY$2:$BY$209=BY7,$O$2:$O$209)))))} | CF7: =IF(N(BQ7)>=MIN_N,"mercado "&BR7,IF(CD7>=MIN_N,"modelo+año+km",IF(CC7>=MIN_N,"modelo+año","modelo"))) | CG7: =(CE7-O7)/CE7 | CH7: =IF(COUNTIFS(FR_FUEL,K7,FR_YEAR,AP7)>0,1,0) | CI7: =IF(COUNTIFS(FR_FUEL,K7,FR_YEAR,AP7-1)>0,1,0) | CJ7: =IF(N(AQ7)>0,AP7*100+AQ7,IF(AND(CH7=1,CI7=1),(AP7-1)*100+1,AP7*100+1)) | CK7: =IF(OR(K7="hibrido",K7="glp",K7="gnc",K7="phev"),"ECO",IF(K7="electrico","CERO",IF(K7="gasolina",IF(CJ7>=GAS_C_YM,"C",IF(CJ7>=GAS_B_YM,"B","A")),IF(K7="diesel",IF(CJ7>=DIE_C_YM,"C",IF(CJ7>=DIE_B_YM,"B","A")),"")))) | CL7: =CK7 | CM7: =IF(AU7="sí","sí",IF(AS7="regla",IF(AND(N(AQ7)=0,CH7=1),"sí","no"),"no")) | CN7: =IFERROR(VLOOKUP(F7,MOD_TBL,16,0),IFERROR(VLOOKUP(E7,OCU_TBL,2,0),NEUTRO)) | CO7: =SUMIFS(MOT_AJUSTE,MOT_MOTOR,G7,MOT_MARCA,E7,MOT_DESDE,"<="&M7,MOT_HASTA,">="&M7)+SUMIFS(MOT_AJUSTE,MOT_MOTOR,G7,MOT_MARCA,"(todas)",MOT_DESDE,"<="&M7,MOT_HASTA,">="&M7)+SUMIFS(MOT_AJUSTE,MOT_MOTOR,"(cualquiera)",MOT_MARCA,E7,MOT_DESDE,"<="&M7,MOT_HASTA,">="&M7) | CP7: =SUMIFS(COMB_AJUSTE,COMB_COMB,K7) | CQ7: =COUNTIFS(MOT_MOTOR,G7,MOT_MARCA,E7,MOT_DESDE,"<="&M7,MOT_HASTA,">="&M7)+COUNTIFS(MOT_MOTOR,G7,MOT_MARCA,"(todas)",MOT_DESDE,"<="&M7,MOT_HASTA,">="&M7)+COUNTIFS(MOT_MOTOR,"(cualquiera)",MOT_MARCA,E7,MOT_DESDE,"<="&M7,MOT_HASTA,">="&M7) | CR7: =IF(AND(K7="diesel",CQ7=0),MIN(CN7,NEUTRO),CN7) | CS7: =MAX(0,MIN(100,CR7+CO7+CP7-IF(AX7="sí",ROB_PEN,0))) | CT7: =100-MAX(0,N7-KM_TOPE_DESDE)/1000*KM_TOPE_PTS | CU7: =MAX(0,MIN(100,50+CG7*PRECIO_PEND,CT7)) | CV7: =MAX(0,100*(1-N7/KM_MAX)) | CW7: =IF(BX7<KMA_SOSP,IF(AA7="sí",100,KMA_PEN),IF(BX7<=KMA_IDEAL_MAX,100,MAX(0,100*(KMA_CERO-BX7)/(KMA_CERO-KMA_IDEAL_MAX)))) | CX7: =MAX(0,MIN(100,100*(M7-ANIO_MIN)/(ANIO_ACTUAL-ANIO_MIN))) | CY7: =W_KMT*CV7+W_KMA*CW7+W_EDAD*CX7 | CZ7: =E7&"|"&G7 | DA7: =IFERROR(VLOOKUP(CZ7,DIST_TBL,2,0),"") | DB7: =E_ITV*(V7="sí")+E_LIBRO*(W7="sí")+E_PROP*IF(Y7=1,1,IF(Y7=2,0.5,0))+E_CORREA*IF(OR(DA7="cadena",AND(X7="sí",BH7="sí")),1,IF(X7="sí",0.5,0))+E_FACT*(BI7="sí") | DC7: =MAX(0,MIN(100,IFERROR(VLOOKUP(CL7,ETQ_TBL,2,0),0)-IF(CM7="sí",ETQ_PEN_DUD,IF(AS7="regla",ETQ_PEN_REGLA,0)))) | DD7: =IF(K7<>"gasolina","",IFERROR(VLOOKUP(F7,CONS_MOD_TBL,2,0),IFERROR(VLOOKUP(L7,CONS_SEG_TBL,2,0),""))) | DE7: =IF(DD7="",NEUTRO,MAX(0,MIN(100,100*(CONS_REF_MAX-DD7)/(CONS_REF_MAX-CONS_REF_MIN)))) | DF7: =IFERROR(VLOOKUP(L7,SEGURO_TBL,3,0),"") | DG7: =IF(DF7="",NEUTRO,MAX(0,MIN(100,100*(SEG_REF_MAX-DF7)/(SEG_REF_MAX-SEG_REF_MIN)))) | DH7: =IFERROR(VLOOKUP(E7,MANT_MARCA_TBL,2,0)+0,NEUTRO) | DI7: =IF(DA7="",NEUTRO,IFERROR(VLOOKUP(DA7,DIST_PTS_TBL,2,0)+0,NEUTRO)) | DJ7: =(DH7+DI7)/2 | DK7: =W_CONS*DE7+W_SEG*DG7+W_MANT*DJ7 | DL7: =IF(N(AB7)>0,AB7,IF(AND(R7="profesional",SG_LEGAL_ON=1),GAR_LEGAL,0)) | DM7: =MAX(0,MIN(100,SG_GAR*MIN(1,DL7/SG_GAR_FULL)+SG_AMPL*(AC7="sí")+SG_KMC*(AF7="sí")+SG_REV*(N(AE7)>0)+SG_DEV*MIN(1,N(AG7)/SG_DEV_FULL)+SG_HIST*(W7="sí")-IF(AND(R7="particular",DL7=0),SG_PART_PEN,0))) | DN7: =IF(BK7="",NEUTRO,MAX(0,MIN(100,BK7/5*100))) | DO7: =IF(BL7="sí",100,IF(BL7="no",0,NEUTRO)) | DP7: =SV_W_NCAP*DN7+SV_W_ESP*DO7 | DQ7: =MAX(0,MIN(100,ATR_BASE+ATR_ACAB*(BD7<>"")+IF(BE7="16+",ATR_LL16,IF(BE7="sí",ATR_LL,0))+ATR_FAROS*(BF7="sí")+ATR_TINT*(BG7="sí")-ATR_CHAPA*(BE7="chapa"))) | DR7: =EST_W_MOD*(BB7-1)/4*100+EST_W_ATR*DQ7 | DS7: =IF(BA7="",NEUTRO,IFERROR(VLOOKUP(BA7,COLOR_TBL,2,0)+0,NEUTRO)) | DT7: =MAX(0,MIN(100,100*N(BM7)/RV_N_FULL)) | DU7: =IF(OR(BN7="",N(BO7)<RV_DIAS_MIN),NEUTRO,MAX(0,MIN(100,100*(RV_DIAS_CERO-BN7)/(RV_DIAS_CERO-RV_DIAS_FULL)))) | DV7: =RV_W_LIQ*DT7+RV_W_DIAS*DU7+RV_W_ETQ*DC7 | DW7: =IFERROR(VLOOKUP(L7,CARR_PEN_TBL,2,0),0) | DX7: =W_FIAB*CS7+W_PRECIO*CU7+W_KMEDAD*CY7+W_ESTADO*DB7+W_USO*DK7+W_SEGURIDAD*DM7+W_SEGVIAL*DP7+W_ESTETICA*DR7+W_COLOR*DS7+W_REVENTA*DV7-DW7-EG7 | DY7: =IF(N(I7)>0,I7,IFERROR(ROUND(_xlfn.NUMBERVALUE(LEFT(G7,FIND(" ",G7&" ")-1),".")*1000,0),99999)) | DZ7: =IF(R7="profesional",0,IF(O7<CUOTA_VALOR_MAX,IF(BW7>ITP_TRAMO_ALTO,SUMIFS(CF_CUOTA,CF_MAS,ITP_TRAMO_ALTO,CF_CCMIN,"<="&DY7,CF_CCMAX,">="&DY7),IF(BW7>ITP_TRAMO_BAJO,SUMIFS(CF_CUOTA,CF_MAS,ITP_TRAMO_BAJO,CF_CCMIN,"<="&DY7,CF_CCMAX,">="&DY7),O7*ITP_TIPO)),O7*ITP_TIPO)) | EA7: =IF(R7="profesional",N(AK7),0) | EB7: =IF(AND(R7="profesional",ISNUMBER(AK7),AL7="sí"),0,TASA_DGT) | EC7: =INFORME_DGT | ED7: =O7+EA7+DZ7+EB7+EC7 | EE7: =ED7+N(DF7) | EF7: =MAX(0,ED7-TOTAL_MAX) | EG7: =EF7/100*PEN_100 | EH7: =IF(R7="particular",ED7+IF(AND(DA7<>"cadena",X7<>"sí"),RES_CORREA,0)+IF(AND(BJ7<>"sí",BW7>=RES_NEUM_EDAD),RES_NEUM,0),"") | EI7: =IF(ED7<=TOTAL_MAX,"sí",IF(ED7<=TECHO,"negociar","no")) | EJ7: =ROUND(DX7,9) | EK7: =IF(EI7<>"no",SUMPRODUCT(($EI$2:$EI$209<>"no")*($EJ$2:$EJ$209>EJ7))+SUMPRODUCT(($EI$2:EI7<>"no")*($EJ$2:EJ7=EJ7)),"")
A8: autoscout24:5df9bdd9-27ce-4647-b70f-976633b13f7a | B8: autoscout24 | C8: https://www.autoscout24.es/anuncios/chevrolet-aveo-sedan-1-4-16v-lt-gasolina-gris-cat_ma19mo18685-5df9bdd9-27ce-4647-b70f-976633b13f7a | D8: Chevrolet Aveo Sedán 1.4 16v LT | E8: Chevrolet | F8: Chevrolet Aveo | G8: 1.4 | H8: Sedán 1.4 16v LT 1.4 | I8: 1399 | J8: 94 | K8: gasolina | L8: berlina | M8: 2008 | N8: 138000 | O8: 3990 | P8: manual | Q8: no | R8: profesional | S8: SAGA VEHICULOS — MASSANASSA (46470) | U8: 26 | Z8: sí | AB8: 12 | AC8: sí | AK8: 350 | AL8: no | AM8: 7.1 | AO8: 2008-10 | AP8: 2008 | AQ8: 10 | AS8: regla | AU8: no | AV8: C | AX8: no | AY8: no | AZ8: Gris | BA8: gris_medio | BB8: 3 | BC8: (por segmento) | BK8: 2 | BL8: no | BM8: 27 | BO8: 0 | BP8: 3990 | BQ8: 4 | BR8: modelo+año+km | BS8: cochesnet:71651301 (https://www.coches.net/chevrolet-aveo-14-16v-lt-4p-gasolina-2008-en-valencia-71651301-covo.aspx) | BT8: vendedor profesional: sin ITP (operación con IVA/REBU, confirmar en factura); gastos del vendedor sin indicar si incluyen la transferencia: se suma la tasa DGT; etiqueta C deducida por fecha (sin matrícula ni dato del anuncio); revisar: no menciona la ITV; fiabilidad del modelo PENDIENTE de fuente (puntuación neutra) | BU8: Chevrolet Aveo LT 1.4 E-TEC ll, 95CV, Gasolina, vehículo muy bien cuidado.<br />Más de 100 coches en stock, Por favor llámenos para más información, atendemos SOLO CON CITA PREVIA. Gracias!!!!<br />Financiacíon de hasta el 100% del vehículo!<br />Gestión documental no incluido 350€ <br />Garantía Premium 12 Meses con cobertura a nivel nacional 399€<br />Saga Vehículos, estamos en C/ Motor Sant Agustí, 41, 46470 Massanassa, Valencia.<br />Horario: De lunes a viernes de 10:00 a 14:00 y de 16:00 a 19:00.<br />Sabado de 10:00 a 14:00.<br />- Aire acondicionado <br />- Dirección asistida<br />- Frenos ABS/EBD<br />- Airbags<br />- Ordenador abordo<br />- Android Auto / Apple CarPlay <br />- Sistema multimedia Bluetooth<br />- GPS navegación <br />- Camara trasera <br />- Llaves presencial con mandos a distancia y mucho mas....<br />Este anuncio no es vinculante, se muestra a titulo informativo y no contractual.<br /><br /><br /><br /> <strong>Extras</strong> <br /> <strong>Equipamiento destacado seleccionado por el usuario</strong> <br /> <br />- Pintura metalizada<br /> | BV8: https://www.autoscout24.es/anuncios/chevrolet-aveo-sedan-1-4-16v-lt-gasolina-gris-cat_ma19mo18685-5df9bdd9-27ce-4647-b70f-976633b13f7a (__NEXT_DATA__ listingDetails) /home/user/Alopecia/buscador-coches/raw/autoscout24/b2dc71ccfcad6c3c.json | BW8: =MAX(ANIO_ACTUAL-M8,0) | BX8: =N8/MAX(BW8,0.5) | BY8: =F8 | BZ8: =BY8&"|"&INT(M8/SEG_ANIO)*SEG_ANIO | CA8: =BZ8&"|"&INT(N8/SEG_KM)*SEG_KM | CB8: =COUNTIF($BY$2:$BY$209,BY8) | CC8: =COUNTIF($BZ$2:$BZ$209,BZ8) | CD8: =COUNTIF($CA$2:$CA$209,CA8) | CE8: {=IF(N(BQ8)>=MIN_N,BP8,IF(CD8>=MIN_N,MEDIAN(IF($CA$2:$CA$209=CA8,$O$2:$O$209)),IF(CC8>=MIN_N,MEDIAN(IF($BZ$2:$BZ$209=BZ8,$O$2:$O$209)),MEDIAN(IF($BY$2:$BY$209=BY8,$O$2:$O$209)))))} | CF8: =IF(N(BQ8)>=MIN_N,"mercado "&BR8,IF(CD8>=MIN_N,"modelo+año+km",IF(CC8>=MIN_N,"modelo+año","modelo"))) | CG8: =(CE8-O8)/CE8 | CH8: =IF(COUNTIFS(FR_FUEL,K8,FR_YEAR,AP8)>0,1,0) | CI8: =IF(COUNTIFS(FR_FUEL,K8,FR_YEAR,AP8-1)>0,1,0) | CJ8: =IF(N(AQ8)>0,AP8*100+AQ8,IF(AND(CH8=1,CI8=1),(AP8-1)*100+1,AP8*100+1)) | CK8: =IF(OR(K8="hibrido",K8="glp",K8="gnc",K8="phev"),"ECO",IF(K8="electrico","CERO",IF(K8="gasolina",IF(CJ8>=GAS_C_YM,"C",IF(CJ8>=GAS_B_YM,"B","A")),IF(K8="diesel",IF(CJ8>=DIE_C_YM,"C",IF(CJ8>=DIE_B_YM,"B","A")),"")))) | CL8: =CK8 | CM8: =IF(AU8="sí","sí",IF(AS8="regla",IF(AND(N(AQ8)=0,CH8=1),"sí","no"),"no")) | CN8: =IFERROR(VLOOKUP(F8,MOD_TBL,16,0),IFERROR(VLOOKUP(E8,OCU_TBL,2,0),NEUTRO)) | CO8: =SUMIFS(MOT_AJUSTE,MOT_MOTOR,G8,MOT_MARCA,E8,MOT_DESDE,"<="&M8,MOT_HASTA,">="&M8)+SUMIFS(MOT_AJUSTE,MOT_MOTOR,G8,MOT_MARCA,"(todas)",MOT_DESDE,"<="&M8,MOT_HASTA,">="&M8)+SUMIFS(MOT_AJUSTE,MOT_MOTOR,"(cualquiera)",MOT_MARCA,E8,MOT_DESDE,"<="&M8,MOT_HASTA,">="&M8) | CP8: =SUMIFS(COMB_AJUSTE,COMB_COMB,K8) | CQ8: =COUNTIFS(MOT_MOTOR,G8,MOT_MARCA,E8,MOT_DESDE,"<="&M8,MOT_HASTA,">="&M8)+COUNTIFS(MOT_MOTOR,G8,MOT_MARCA,"(todas)",MOT_DESDE,"<="&M8,MOT_HASTA,">="&M8)+COUNTIFS(MOT_MOTOR,"(cualquiera)",MOT_MARCA,E8,MOT_DESDE,"<="&M8,MOT_HASTA,">="&M8) | CR8: =IF(AND(K8="diesel",CQ8=0),MIN(CN8,NEUTRO),CN8) | CS8: =MAX(0,MIN(100,CR8+CO8+CP8-IF(AX8="sí",ROB_PEN,0))) | CT8: =100-MAX(0,N8-KM_TOPE_DESDE)/1000*KM_TOPE_PTS | CU8: =MAX(0,MIN(100,50+CG8*PRECIO_PEND,CT8)) | CV8: =MAX(0,100*(1-N8/KM_MAX)) | CW8: =IF(BX8<KMA_SOSP,IF(AA8="sí",100,KMA_PEN),IF(BX8<=KMA_IDEAL_MAX,100,MAX(0,100*(KMA_CERO-BX8)/(KMA_CERO-KMA_IDEAL_MAX)))) | CX8: =MAX(0,MIN(100,100*(M8-ANIO_MIN)/(ANIO_ACTUAL-ANIO_MIN))) | CY8: =W_KMT*CV8+W_KMA*CW8+W_EDAD*CX8 | CZ8: =E8&"|"&G8 | DA8: =IFERROR(VLOOKUP(CZ8,DIST_TBL,2,0),"") | DB8: =E_ITV*(V8="sí")+E_LIBRO*(W8="sí")+E_PROP*IF(Y8=1,1,IF(Y8=2,0.5,0))+E_CORREA*IF(OR(DA8="cadena",AND(X8="sí",BH8="sí")),1,IF(X8="sí",0.5,0))+E_FACT*(BI8="sí") | DC8: =MAX(0,MIN(100,IFERROR(VLOOKUP(CL8,ETQ_TBL,2,0),0)-IF(CM8="sí",ETQ_PEN_DUD,IF(AS8="regla",ETQ_PEN_REGLA,0)))) | DD8: =IF(K8<>"gasolina","",IFERROR(VLOOKUP(F8,CONS_MOD_TBL,2,0),IFERROR(VLOOKUP(L8,CONS_SEG_TBL,2,0),""))) | DE8: =IF(DD8="",NEUTRO,MAX(0,MIN(100,100*(CONS_REF_MAX-DD8)/(CONS_REF_MAX-CONS_REF_MIN)))) | DF8: =IFERROR(VLOOKUP(L8,SEGURO_TBL,3,0),"") | DG8: =IF(DF8="",NEUTRO,MAX(0,MIN(100,100*(SEG_REF_MAX-DF8)/(SEG_REF_MAX-SEG_REF_MIN)))) | DH8: =IFERROR(VLOOKUP(E8,MANT_MARCA_TBL,2,0)+0,NEUTRO) | DI8: =IF(DA8="",NEUTRO,IFERROR(VLOOKUP(DA8,DIST_PTS_TBL,2,0)+0,NEUTRO)) | DJ8: =(DH8+DI8)/2 | DK8: =W_CONS*DE8+W_SEG*DG8+W_MANT*DJ8 | DL8: =IF(N(AB8)>0,AB8,IF(AND(R8="profesional",SG_LEGAL_ON=1),GAR_LEGAL,0)) | DM8: =MAX(0,MIN(100,SG_GAR*MIN(1,DL8/SG_GAR_FULL)+SG_AMPL*(AC8="sí")+SG_KMC*(AF8="sí")+SG_REV*(N(AE8)>0)+SG_DEV*MIN(1,N(AG8)/SG_DEV_FULL)+SG_HIST*(W8="sí")-IF(AND(R8="particular",DL8=0),SG_PART_PEN,0))) | DN8: =IF(BK8="",NEUTRO,MAX(0,MIN(100,BK8/5*100))) | DO8: =IF(BL8="sí",100,IF(BL8="no",0,NEUTRO)) | DP8: =SV_W_NCAP*DN8+SV_W_ESP*DO8 | DQ8: =MAX(0,MIN(100,ATR_BASE+ATR_ACAB*(BD8<>"")+IF(BE8="16+",ATR_LL16,IF(BE8="sí",ATR_LL,0))+ATR_FAROS*(BF8="sí")+ATR_TINT*(BG8="sí")-ATR_CHAPA*(BE8="chapa"))) | DR8: =EST_W_MOD*(BB8-1)/4*100+EST_W_ATR*DQ8 | DS8: =IF(BA8="",NEUTRO,IFERROR(VLOOKUP(BA8,COLOR_TBL,2,0)+0,NEUTRO)) | DT8: =MAX(0,MIN(100,100*N(BM8)/RV_N_FULL)) | DU8: =IF(OR(BN8="",N(BO8)<RV_DIAS_MIN),NEUTRO,MAX(0,MIN(100,100*(RV_DIAS_CERO-BN8)/(RV_DIAS_CERO-RV_DIAS_FULL)))) | DV8: =RV_W_LIQ*DT8+RV_W_DIAS*DU8+RV_W_ETQ*DC8 | DW8: =IFERROR(VLOOKUP(L8,CARR_PEN_TBL,2,0),0) | DX8: =W_FIAB*CS8+W_PRECIO*CU8+W_KMEDAD*CY8+W_ESTADO*DB8+W_USO*DK8+W_SEGURIDAD*DM8+W_SEGVIAL*DP8+W_ESTETICA*DR8+W_COLOR*DS8+W_REVENTA*DV8-DW8-EG8 | DY8: =IF(N(I8)>0,I8,IFERROR(ROUND(_xlfn.NUMBERVALUE(LEFT(G8,FIND(" ",G8&" ")-1),".")*1000,0),99999)) | DZ8: =IF(R8="profesional",0,IF(O8<CUOTA_VALOR_MAX,IF(BW8>ITP_TRAMO_ALTO,SUMIFS(CF_CUOTA,CF_MAS,ITP_TRAMO_ALTO,CF_CCMIN,"<="&DY8,CF_CCMAX,">="&DY8),IF(BW8>ITP_TRAMO_BAJO,SUMIFS(CF_CUOTA,CF_MAS,ITP_TRAMO_BAJO,CF_CCMIN,"<="&DY8,CF_CCMAX,">="&DY8),O8*ITP_TIPO)),O8*ITP_TIPO)) | EA8: =IF(R8="profesional",N(AK8),0) | EB8: =IF(AND(R8="profesional",ISNUMBER(AK8),AL8="sí"),0,TASA_DGT) | EC8: =INFORME_DGT | ED8: =O8+EA8+DZ8+EB8+EC8 | EE8: =ED8+N(DF8) | EF8: =MAX(0,ED8-TOTAL_MAX) | EG8: =EF8/100*PEN_100 | EH8: =IF(R8="particular",ED8+IF(AND(DA8<>"cadena",X8<>"sí"),RES_CORREA,0)+IF(AND(BJ8<>"sí",BW8>=RES_NEUM_EDAD),RES_NEUM,0),"") | EI8: =IF(ED8<=TOTAL_MAX,"sí",IF(ED8<=TECHO,"negociar","no")) | EJ8: =ROUND(DX8,9) | EK8: =IF(EI8<>"no",SUMPRODUCT(($EI$2:$EI$209<>"no")*($EJ$2:$EJ$209>EJ8))+SUMPRODUCT(($EI$2:EI8<>"no")*($EJ$2:EJ8=EJ8)),"")
A9: cochesnet:71265682 | B9: cochesnet | C9: https://www.coches.net/mazda-mazda2-active-14-crtd-5p-diesel-2007-en-valencia-71265682-covo.aspx | D9: MAZDA Mazda2 Active 1.4 CRTD | E9: Mazda | F9: Mazda 2 | G9: 1.4 | H9: Active 1.4 CRTD | K9: diesel | L9: utilitario | M9: 2008 | N9: 145000 | O9: 4500 | P9: manual | Q9: no | R9: profesional | S9: Beniparrell | T9: 2026-08-10T16:34:09Z | U9: 13 | Z9: sí | AB9: 12 | AH9: 4500 | AM9: 10.2 | AO9: 2008 | AP9: 2008 | AR9: B | AS9: anuncio | AT9: 2007 | AU9: no | AV9: B | AX9: no | AY9: no | AZ9: COMMON.COLOR_GRAY | BA9: gris_medio | BB9: 2 | BC9: (por segmento) | BG9: sí | BK9: 5 | BL9: no | BM9: 136 | BN9: 0.029392361 | BO9: 2 | BP9: 5000 | BQ9: 11 | BR9: modelo+año | BT9: año a confirmar: la URL/título dice 2007; vendedor profesional: sin ITP (operación con IVA/REBU, confirmar en factura); gastos de gestión del vendedor no indicados: se suma la tasa DGT; preguntar el precio final; diésel: motor sin fuente de fiabilidad (fiabilidad limitada a neutra); revisar: no menciona la ITV | BU9: Este Mazda2 Active 1.4 CRTD es un compacto versátil y eficiente, diseñado para quienes buscan un vehículo manejable en ciudad sin renunciar a la practicidad. Su motor diésel de 1.4 litros ofrece un consumo moderado —4,3 l/100 km en ciclo mixto— con par disponible desde bajas revoluciones, lo que facilita la conducción en tráfico urbano y en carreteras secundarias. El interior aprovecha bien el espacio disponible con asientos delanteros individuales ajustables en altura y respaldo trasero abatible asimétrico, permitiendo ampliar la capacidad de carga hasta 787 litros con los asientos plegados. La dirección asistida con endurecimiento progresivo y la suspensión independiente delantera proporcionan una respuesta equilibrada en diferentes condiciones de circulación. En cuanto a equipamiento, este vehículo integra climatizador automático, elevalunas eléctricos en todas las puertas, cierre centralizado con mando a distancia, y un sistema de audio con radio AM/FM, lector de CD para MP3 y mandos en el volante. La seguridad se refuerza con airbags frontales inteligentes, laterales delanteros y de cortina, además de ABS en las cuatro ruedas y preparación Isofix para sistemas de retención infantil. Los cristales tintados, retrovisores exteriores eléctricos y desempañables, así como los limpiaparabrisas con intermitencia, completan el equipamiento de confort. Este ejemplar cuenta con etiqueta medioambiental B, lo que permite acceso a las ciudades con regulación de zonas de bajas emisi | BV9: https://www.coches.net/mazda-mazda2-active-14-crtd-5p-diesel-2007-en-valencia-71265682-covo.aspx (window.__INITIAL_PROPS__.ad) /home/user/Alopecia/buscador-coches/raw/cochesnet/5cd5d6b176a66f9b.json | BW9: =MAX(ANIO_ACTUAL-M9,0) | BX9: =N9/MAX(BW9,0.5) | BY9: =F9 | BZ9: =BY9&"|"&INT(M9/SEG_ANIO)*SEG_ANIO | CA9: =BZ9&"|"&INT(N9/SEG_KM)*SEG_KM | CB9: =COUNTIF($BY$2:$BY$209,BY9) | CC9: =COUNTIF($BZ$2:$BZ$209,BZ9) | CD9: =COUNTIF($CA$2:$CA$209,CA9) | CE9: {=IF(N(BQ9)>=MIN_N,BP9,IF(CD9>=MIN_N,MEDIAN(IF($CA$2:$CA$209=CA9,$O$2:$O$209)),IF(CC9>=MIN_N,MEDIAN(IF($BZ$2:$BZ$209=BZ9,$O$2:$O$209)),MEDIAN(IF($BY$2:$BY$209=BY9,$O$2:$O$209)))))} | CF9: =IF(N(BQ9)>=MIN_N,"mercado "&BR9,IF(CD9>=MIN_N,"modelo+año+km",IF(CC9>=MIN_N,"modelo+año","modelo"))) | CG9: =(CE9-O9)/CE9 | CH9: =IF(COUNTIFS(FR_FUEL,K9,FR_YEAR,AP9)>0,1,0) | CI9: =IF(COUNTIFS(FR_FUEL,K9,FR_YEAR,AP9-1)>0,1,0) | CJ9: =IF(N(AQ9)>0,AP9*100+AQ9,IF(AND(CH9=1,CI9=1),(AP9-1)*100+1,AP9*100+1)) | CK9: =IF(OR(K9="hibrido",K9="glp",K9="gnc",K9="phev"),"ECO",IF(K9="electrico","CERO",IF(K9="gasolina",IF(CJ9>=GAS_C_YM,"C",IF(CJ9>=GAS_B_YM,"B","A")),IF(K9="diesel",IF(CJ9>=DIE_C_YM,"C",IF(CJ9>=DIE_B_YM,"B","A")),"")))) | CL9: B | CM9: =IF(AU9="sí","sí",IF(AS9="regla",IF(AND(N(AQ9)=0,CH9=1),"sí","no"),"no")) | CN9: =IFERROR(VLOOKUP(F9,MOD_TBL,16,0),IFERROR(VLOOKUP(E9,OCU_TBL,2,0),NEUTRO)) | CO9: =SUMIFS(MOT_AJUSTE,MOT_MOTOR,G9,MOT_MARCA,E9,MOT_DESDE,"<="&M9,MOT_HASTA,">="&M9)+SUMIFS(MOT_AJUSTE,MOT_MOTOR,G9,MOT_MARCA,"(todas)",MOT_DESDE,"<="&M9,MOT_HASTA,">="&M9)+SUMIFS(MOT_AJUSTE,MOT_MOTOR,"(cualquiera)",MOT_MARCA,E9,MOT_DESDE,"<="&M9,MOT_HASTA,">="&M9) | CP9: =SUMIFS(COMB_AJUSTE,COMB_COMB,K9) | CQ9: =COUNTIFS(MOT_MOTOR,G9,MOT_MARCA,E9,MOT_DESDE,"<="&M9,MOT_HASTA,">="&M9)+COUNTIFS(MOT_MOTOR,G9,MOT_MARCA,"(todas)",MOT_DESDE,"<="&M9,MOT_HASTA,">="&M9)+COUNTIFS(MOT_MOTOR,"(cualquiera)",MOT_MARCA,E9,MOT_DESDE,"<="&M9,MOT_HASTA,">="&M9) | CR9: =IF(AND(K9="diesel",CQ9=0),MIN(CN9,NEUTRO),CN9) | CS9: =MAX(0,MIN(100,CR9+CO9+CP9-IF(AX9="sí",ROB_PEN,0))) | CT9: =100-MAX(0,N9-KM_TOPE_DESDE)/1000*KM_TOPE_PTS | CU9: =MAX(0,MIN(100,50+CG9*PRECIO_PEND,CT9)) | CV9: =MAX(0,100*(1-N9/KM_MAX)) | CW9: =IF(BX9<KMA_SOSP,IF(AA9="sí",100,KMA_PEN),IF(BX9<=KMA_IDEAL_MAX,100,MAX(0,100*(KMA_CERO-BX9)/(KMA_CERO-KMA_IDEAL_MAX)))) | CX9: =MAX(0,MIN(100,100*(M9-ANIO_MIN)/(ANIO_ACTUAL-ANIO_MIN))) | CY9: =W_KMT*CV9+W_KMA*CW9+W_EDAD*CX9 | CZ9: =E9&"|"&G9 | DA9: =IFERROR(VLOOKUP(CZ9,DIST_TBL,2,0),"") | DB9: =E_ITV*(V9="sí")+E_LIBRO*(W9="sí")+E_PROP*IF(Y9=1,1,IF(Y9=2,0.5,0))+E_CORREA*IF(OR(DA9="cadena",AND(X9="sí",BH9="sí")),1,IF(X9="sí",0.5,0))+E_FACT*(BI9="sí") | DC9: =MAX(0,MIN(100,IFERROR(VLOOKUP(CL9,ETQ_TBL,2,0),0)-IF(CM9="sí",ETQ_PEN_DUD,IF(AS9="regla",ETQ_PEN_REGLA,0)))) | DD9: =IF(K9<>"gasolina","",IFERROR(VLOOKUP(F9,CONS_MOD_TBL,2,0),IFERROR(VLOOKUP(L9,CONS_SEG_TBL,2,0),""))) | DE9: =IF(DD9="",NEUTRO,MAX(0,MIN(100,100*(CONS_REF_MAX-DD9)/(CONS_REF_MAX-CONS_REF_MIN)))) | DF9: =IFERROR(VLOOKUP(L9,SEGURO_TBL,3,0),"") | DG9: =IF(DF9="",NEUTRO,MAX(0,MIN(100,100*(SEG_REF_MAX-DF9)/(SEG_REF_MAX-SEG_REF_MIN)))) | DH9: =IFERROR(VLOOKUP(E9,MANT_MARCA_TBL,2,0)+0,NEUTRO) | DI9: =IF(DA9="",NEUTRO,IFERROR(VLOOKUP(DA9,DIST_PTS_TBL,2,0)+0,NEUTRO)) | DJ9: =(DH9+DI9)/2 | DK9: =W_CONS*DE9+W_SEG*DG9+W_MANT*DJ9 | DL9: =IF(N(AB9)>0,AB9,IF(AND(R9="profesional",SG_LEGAL_ON=1),GAR_LEGAL,0)) | DM9: =MAX(0,MIN(100,SG_GAR*MIN(1,DL9/SG_GAR_FULL)+SG_AMPL*(AC9="sí")+SG_KMC*(AF9="sí")+SG_REV*(N(AE9)>0)+SG_DEV*MIN(1,N(AG9)/SG_DEV_FULL)+SG_HIST*(W9="sí")-IF(AND(R9="particular",DL9=0),SG_PART_PEN,0))) | DN9: =IF(BK9="",NEUTRO,MAX(0,MIN(100,BK9/5*100))) | DO9: =IF(BL9="sí",100,IF(BL9="no",0,NEUTRO)) | DP9: =SV_W_NCAP*DN9+SV_W_ESP*DO9 | DQ9: =MAX(0,MIN(100,ATR_BASE+ATR_ACAB*(BD9<>"")+IF(BE9="16+",ATR_LL16,IF(BE9="sí",ATR_LL,0))+ATR_FAROS*(BF9="sí")+ATR_TINT*(BG9="sí")-ATR_CHAPA*(BE9="chapa"))) | DR9: =EST_W_MOD*(BB9-1)/4*100+EST_W_ATR*DQ9 | DS9: =IF(BA9="",NEUTRO,IFERROR(VLOOKUP(BA9,COLOR_TBL,2,0)+0,NEUTRO)) | DT9: =MAX(0,MIN(100,100*N(BM9)/RV_N_FULL)) | DU9: =IF(OR(BN9="",N(BO9)<RV_DIAS_MIN),NEUTRO,MAX(0,MIN(100,100*(RV_DIAS_CERO-BN9)/(RV_DIAS_CERO-RV_DIAS_FULL)))) | DV9: =RV_W_LIQ*DT9+RV_W_DIAS*DU9+RV_W_ETQ*DC9 | DW9: =IFERROR(VLOOKUP(L9,CARR_PEN_TBL,2,0),0) | DX9: =W_FIAB*CS9+W_PRECIO*CU9+W_KMEDAD*CY9+W_ESTADO*DB9+W_USO*DK9+W_SEGURIDAD*DM9+W_SEGVIAL*DP9+W_ESTETICA*DR9+W_COLOR*DS9+W_REVENTA*DV9-DW9-EG9 | DY9: =IF(N(I9)>0,I9,IFERROR(ROUND(_xlfn.NUMBERVALUE(LEFT(G9,FIND(" ",G9&" ")-1),".")*1000,0),99999)) | DZ9: =IF(R9="profesional",0,IF(O9<CUOTA_VALOR_MAX,IF(BW9>ITP_TRAMO_ALTO,SUMIFS(CF_CUOTA,CF_MAS,ITP_TRAMO_ALTO,CF_CCMIN,"<="&DY9,CF_CCMAX,">="&DY9),IF(BW9>ITP_TRAMO_BAJO,SUMIFS(CF_CUOTA,CF_MAS,ITP_TRAMO_BAJO,CF_CCMIN,"<="&DY9,CF_CCMAX,">="&DY9),O9*ITP_TIPO)),O9*ITP_TIPO)) | EA9: =IF(R9="profesional",N(AK9),0) | EB9: =IF(AND(R9="profesional",ISNUMBER(AK9),AL9="sí"),0,TASA_DGT) | EC9: =INFORME_DGT | ED9: =O9+EA9+DZ9+EB9+EC9 | EE9: =ED9+N(DF9) | EF9: =MAX(0,ED9-TOTAL_MAX) | EG9: =EF9/100*PEN_100 | EH9: =IF(R9="particular",ED9+IF(AND(DA9<>"cadena",X9<>"sí"),RES_CORREA,0)+IF(AND(BJ9<>"sí",BW9>=RES_NEUM_EDAD),RES_NEUM,0),"") | EI9: =IF(ED9<=TOTAL_MAX,"sí",IF(ED9<=TECHO,"negociar","no")) | EJ9: =ROUND(DX9,9) | EK9: =IF(EI9<>"no",SUMPRODUCT(($EI$2:$EI$209<>"no")*($EJ$2:$EJ$209>EJ9))+SUMPRODUCT(($EI$2:EI9<>"no")*($EJ$2:EJ9=EJ9)),"")
A10: cochesnet:71525978 | B10: cochesnet | C10: https://www.coches.net/mazda-mazda2-style-16-crtd-3p-diesel-2009-en-valencia-71525978-covo.aspx | D10: MAZDA Mazda2 Style 1.6 CRTD | E10: Mazda | F10: Mazda 2 | G10: 1.6 | H10: Style 1.6 CRTD | K10: diesel | L10: utilitario | M10: 2011 | N10: 214000 | O10: 3800 | P10: manual | Q10: no | R10: profesional | S10: Coches Venar Valencia | T10: 2026-09-16T11:48:49Z | U10: 8 | Z10: sí | AB10: 12 | AH10: 3800 | AM10: 0.1 | AO10: 2011 | AP10: 2011 | AS10: regla | AT10: 2009 | AU10: no | AV10: B | AX10: no | AY10: no | AZ10: COMMON.COLOR_WHITE | BA10: blanco | BB10: 2 | BC10: (por segmento) | BG10: sí | BK10: 5 | BL10: no | BM10: 136 | BN10: 0.029392361 | BO10: 2 | BP10: 5000 | BQ10: 6 | BR10: modelo+año | BT10: año a confirmar: la URL/título dice 2009; vendedor profesional: sin ITP (operación con IVA/REBU, confirmar en factura); gastos de gestión del vendedor no indicados: se suma la tasa DGT; preguntar el precio final; diésel: motor sin fuente de fiabilidad (fiabilidad limitada a neutra); etiqueta B deducida por fecha (sin matrícula ni dato del anuncio); revisar: no menciona la ITV | BU10: Este Mazda2 Style 1.6 CRTD combina practicidad urbana con equipamiento de confort pensado para el uso diario. Destaca por su aire acondicionado automático, dirección asistida eléctrica con endurecimiento progresivo, y volante multifunción ajustable que facilitan la conducción. Dispone de cierre centralizado con mando a distancia, elevalunas eléctricos delanteros con función de un solo toque, y retrovisores exteriores eléctricos desempañables. El interior ofrece asientos ajustables en altura, reposacabezas regulables en todas las plazas, y sistema de ventilación con filtro de polen. Incluye ordenador de viaje con datos de consumo y autonomía, equipo de audio con radio AM/FM/LW, reproductor de CD y lector MP3 con control remoto en volante. Cristales tintados y climatización automática completan un habitáculo versátil para desplazamientos cotidianos. | BV10: https://www.coches.net/mazda-mazda2-style-16-crtd-3p-diesel-2009-en-valencia-71525978-covo.aspx (window.__INITIAL_PROPS__.ad) /home/user/Alopecia/buscador-coches/raw/cochesnet/680bda08a6c8bde6.json | BW10: =MAX(ANIO_ACTUAL-M10,0) | BX10: =N10/MAX(BW10,0.5) | BY10: =F10 | BZ10: =BY10&"|"&INT(M10/SEG_ANIO)*SEG_ANIO | CA10: =BZ10&"|"&INT(N10/SEG_KM)*SEG_KM | CB10: =COUNTIF($BY$2:$BY$209,BY10) | CC10: =COUNTIF($BZ$2:$BZ$209,BZ10) | CD10: =COUNTIF($CA$2:$CA$209,CA10) | CE10: {=IF(N(BQ10)>=MIN_N,BP10,IF(CD10>=MIN_N,MEDIAN(IF($CA$2:$CA$209=CA10,$O$2:$O$209)),IF(CC10>=MIN_N,MEDIAN(IF($BZ$2:$BZ$209=BZ10,$O$2:$O$209)),MEDIAN(IF($BY$2:$BY$209=BY10,$O$2:$O$209)))))} | CF10: =IF(N(BQ10)>=MIN_N,"mercado "&BR10,IF(CD10>=MIN_N,"modelo+año+km",IF(CC10>=MIN_N,"modelo+año","modelo"))) | CG10: =(CE10-O10)/CE10 | CH10: =IF(COUNTIFS(FR_FUEL,K10,FR_YEAR,AP10)>0,1,0) | CI10: =IF(COUNTIFS(FR_FUEL,K10,FR_YEAR,AP10-1)>0,1,0) | CJ10: =IF(N(AQ10)>0,AP10*100+AQ10,IF(AND(CH10=1,CI10=1),(AP10-1)*100+1,AP10*100+1)) | CK10: =IF(OR(K10="hibrido",K10="glp",K10="gnc",K10="phev"),"ECO",IF(K10="electrico","CERO",IF(K10="gasolina",IF(CJ10>=GAS_C_YM,"C",IF(CJ10>=GAS_B_YM,"B","A")),IF(K10="diesel",IF(CJ10>=DIE_C_YM,"C",IF(CJ10>=DIE_B_YM,"B","A")),"")))) | CL10: =CK10 | CM10: =IF(AU10="sí","sí",IF(AS10="regla",IF(AND(N(AQ10)=0,CH10=1),"sí","no"),"no")) | CN10: =IFERROR(VLOOKUP(F10,MOD_TBL,16,0),IFERROR(VLOOKUP(E10,OCU_TBL,2,0),NEUTRO)) | CO10: =SUMIFS(MOT_AJUSTE,MOT_MOTOR,G10,MOT_MARCA,E10,MOT_DESDE,"<="&M10,MOT_HASTA,">="&M10)+SUMIFS(MOT_AJUSTE,MOT_MOTOR,G10,MOT_MARCA,"(todas)",MOT_DESDE,"<="&M10,MOT_HASTA,">="&M10)+SUMIFS(MOT_AJUSTE,MOT_MOTOR,"(cualquiera)",MOT_MARCA,E10,MOT_DESDE,"<="&M10,MOT_HASTA,">="&M10) | CP10: =SUMIFS(COMB_AJUSTE,COMB_COMB,K10) | CQ10: =COUNTIFS(MOT_MOTOR,G10,MOT_MARCA,E10,MOT_DESDE,"<="&M10,MOT_HASTA,">="&M10)+COUNTIFS(MOT_MOTOR,G10,MOT_MARCA,"(todas)",MOT_DESDE,"<="&M10,MOT_HASTA,">="&M10)+COUNTIFS(MOT_MOTOR,"(cualquiera)",MOT_MARCA,E10,MOT_DESDE,"<="&M10,MOT_HASTA,">="&M10) | CR10: =IF(AND(K10="diesel",CQ10=0),MIN(CN10,NEUTRO),CN10) | CS10: =MAX(0,MIN(100,CR10+CO10+CP10-IF(AX10="sí",ROB_PEN,0))) | CT10: =100-MAX(0,N10-KM_TOPE_DESDE)/1000*KM_TOPE_PTS | CU10: =MAX(0,MIN(100,50+CG10*PRECIO_PEND,CT10)) | CV10: =MAX(0,100*(1-N10/KM_MAX)) | CW10: =IF(BX10<KMA_SOSP,IF(AA10="sí",100,KMA_PEN),IF(BX10<=KMA_IDEAL_MAX,100,MAX(0,100*(KMA_CERO-BX10)/(KMA_CERO-KMA_IDEAL_MAX)))) | CX10: =MAX(0,MIN(100,100*(M10-ANIO_MIN)/(ANIO_ACTUAL-ANIO_MIN))) | CY10: =W_KMT*CV10+W_KMA*CW10+W_EDAD*CX10 | CZ10: =E10&"|"&G10 | DA10: =IFERROR(VLOOKUP(CZ10,DIST_TBL,2,0),"") | DB10: =E_ITV*(V10="sí")+E_LIBRO*(W10="sí")+E_PROP*IF(Y10=1,1,IF(Y10=2,0.5,0))+E_CORREA*IF(OR(DA10="cadena",AND(X10="sí",BH10="sí")),1,IF(X10="sí",0.5,0))+E_FACT*(BI10="sí") | DC10: =MAX(0,MIN(100,IFERROR(VLOOKUP(CL10,ETQ_TBL,2,0),0)-IF(CM10="sí",ETQ_PEN_DUD,IF(AS10="regla",ETQ_PEN_REGLA,0)))) | DD10: =IF(K10<>"gasolina","",IFERROR(VLOOKUP(F10,CONS_MOD_TBL,2,0),IFERROR(VLOOKUP(L10,CONS_SEG_TBL,2,0),""))) | DE10: =IF(DD10="",NEUTRO,MAX(0,MIN(100,100*(CONS_REF_MAX-DD10)/(CONS_REF_MAX-CONS_REF_MIN)))) | DF10: =IFERROR(VLOOKUP(L10,SEGURO_TBL,3,0),"") | DG10: =IF(DF10="",NEUTRO,MAX(0,MIN(100,100*(SEG_REF_MAX-DF10)/(SEG_REF_MAX-SEG_REF_MIN)))) | DH10: =IFERROR(VLOOKUP(E10,MANT_MARCA_TBL,2,0)+0,NEUTRO) | DI10: =IF(DA10="",NEUTRO,IFERROR(VLOOKUP(DA10,DIST_PTS_TBL,2,0)+0,NEUTRO)) | DJ10: =(DH10+DI10)/2 | DK10: =W_CONS*DE10+W_SEG*DG10+W_MANT*DJ10 | DL10: =IF(N(AB10)>0,AB10,IF(AND(R10="profesional",SG_LEGAL_ON=1),GAR_LEGAL,0)) | DM10: =MAX(0,MIN(100,SG_GAR*MIN(1,DL10/SG_GAR_FULL)+SG_AMPL*(AC10="sí")+SG_KMC*(AF10="sí")+SG_REV*(N(AE10)>0)+SG_DEV*MIN(1,N(AG10)/SG_DEV_FULL)+SG_HIST*(W10="sí")-IF(AND(R10="particular",DL10=0),SG_PART_PEN,0))) | DN10: =IF(BK10="",NEUTRO,MAX(0,MIN(100,BK10/5*100))) | DO10: =IF(BL10="sí",100,IF(BL10="no",0,NEUTRO)) | DP10: =SV_W_NCAP*DN10+SV_W_ESP*DO10 | DQ10: =MAX(0,MIN(100,ATR_BASE+ATR_ACAB*(BD10<>"")+IF(BE10="16+",ATR_LL16,IF(BE10="sí",ATR_LL,0))+ATR_FAROS*(BF10="sí")+ATR_TINT*(BG10="sí")-ATR_CHAPA*(BE10="chapa"))) | DR10: =EST_W_MOD*(BB10-1)/4*100+EST_W_ATR*DQ10 | DS10: =IF(BA10="",NEUTRO,IFERROR(VLOOKUP(BA10,COLOR_TBL,2,0)+0,NEUTRO)) | DT10: =MAX(0,MIN(100,100*N(BM10)/RV_N_FULL)) | DU10: =IF(OR(BN10="",N(BO10)<RV_DIAS_MIN),NEUTRO,MAX(0,MIN(100,100*(RV_DIAS_CERO-BN10)/(RV_DIAS_CERO-RV_DIAS_FULL)))) | DV10: =RV_W_LIQ*DT10+RV_W_DIAS*DU10+RV_W_ETQ*DC10 | DW10: =IFERROR(VLOOKUP(L10,CARR_PEN_TBL,2,0),0) | DX10: =W_FIAB*CS10+W_PRECIO*CU10+W_KMEDAD*CY10+W_ESTADO*DB10+W_USO*DK10+W_SEGURIDAD*DM10+W_SEGVIAL*DP10+W_ESTETICA*DR10+W_COLOR*DS10+W_REVENTA*DV10-DW10-EG10 | DY10: =IF(N(I10)>0,I10,IFERROR(ROUND(_xlfn.NUMBERVALUE(LEFT(G10,FIND(" ",G10&" ")-1),".")*1000,0),99999)) | DZ10: =IF(R10="profesional",0,IF(O10<CUOTA_VALOR_MAX,IF(BW10>ITP_TRAMO_ALTO,SUMIFS(CF_CUOTA,CF_MAS,ITP_TRAMO_ALTO,CF_CCMIN,"<="&DY10,CF_CCMAX,">="&DY10),IF(BW10>ITP_TRAMO_BAJO,SUMIFS(CF_CUOTA,CF_MAS,ITP_TRAMO_BAJO,CF_CCMIN,"<="&DY10,CF_CCMAX,">="&DY10),O10*ITP_TIPO)),O10*ITP_TIPO)) | EA10: =IF(R10="profesional",N(AK10),0) | EB10: =IF(AND(R10="profesional",ISNUMBER(AK10),AL10="sí"),0,TASA_DGT) | EC10: =INFORME_DGT | ED10: =O10+EA10+DZ10+EB10+EC10 | EE10: =ED10+N(DF10) | EF10: =MAX(0,ED10-TOTAL_MAX) | EG10: =EF10/100*PEN_100 | EH10: =IF(R10="particular",ED10+IF(AND(DA10<>"cadena",X10<>"sí"),RES_CORREA,0)+IF(AND(BJ10<>"sí",BW10>=RES_NEUM_EDAD),RES_NEUM,0),"") | EI10: =IF(ED10<=TOTAL_MAX,"sí",IF(ED10<=TECHO,"negociar","no")) | EJ10: =ROUND(DX10,9) | EK10: =IF(EI10<>"no",SUMPRODUCT(($EI$2:$EI$209<>"no")*($EJ$2:$EJ$209>EJ10))+SUMPRODUCT(($EI$2:EI10<>"no")*($EJ$2:EJ10=EJ10)),"")
A11: cochesnet:71817386 | B11: cochesnet | C11: https://www.coches.net/kia-picanto-10-sohc-concept-5p-gasolina-2010-en-valencia-71817386-covo.aspx | D11: KIA Picanto 1.0 SOHC Concept | E11: Kia | F11: Kia Picanto | G11: 1.0 | H11: 1.0 SOHC Concept | K11: gasolina | L11: utilitario | M11: 2010 | N11: 99500 | O11: 4490 | P11: manual | Q11: no | R11: profesional | S11: JM Automóviles Alboraya | T11: 2026-10-23T14:17:23Z | U11: 17 | Z11: sí | AB11: 12 | AH11: 4490 | AI11: 4490 | AM11: 4 | AO11: 2010 | AP11: 2010 | AR11: C | AS11: anuncio | AU11: no | AV11: C | AX11: no | AY11: no | AZ11: COMMON.COLOR_BLUE | BA11: azul | BB11: 2 | BC11: (por segmento) | BK11: 3 | BL11: no | BM11: 130 | BO11: 0 | BT11: vendedor profesional: sin ITP (operación con IVA/REBU, confirmar en factura); gastos de gestión del vendedor no indicados: se suma la tasa DGT; preguntar el precio final; revisar: no menciona la ITV | BU11: KIA PICANTO GASOLINA – 2010 – 99.500 KM Kia Picanto del año 2010, con motor de gasolina y 99.500 km. Un vehículo urbano, práctico y económico, ideal para el día a día, con un tamaño perfecto para moverse por ciudad y aparcar fácilmente. DATOS PRINCIPALES Año: 2010 Combustible: Gasolina Kilómetros: 99.500 km Motor: Gasolina Cambio: Manual (por confirmar) EQUIPAMIENTO DESTACADO Aire acondicionado Radio Elevalunas eléctricos Cierre centralizado Dirección asistida ABS Interior práctico y funcional LO MEJOR Solo 99.500 km Motor de gasolina Tamaño compacto, ideal para ciudad Fácil de aparcar Mantenimiento económico Vehículo en buen estado, cuidado y preparado para su entrega. | BV11: https://www.coches.net/kia-picanto-10-sohc-concept-5p-gasolina-2010-en-valencia-71817386-covo.aspx (window.__INITIAL_PROPS__.ad) /home/user/Alopecia/buscador-coches/raw/cochesnet/7d779d6ecf209f81.json | BW11: =MAX(ANIO_ACTUAL-M11,0) | BX11: =N11/MAX(BW11,0.5) | BY11: =F11 | BZ11: =BY11&"|"&INT(M11/SEG_ANIO)*SEG_ANIO | CA11: =BZ11&"|"&INT(N11/SEG_KM)*SEG_KM | CB11: =COUNTIF($BY$2:$BY$209,BY11) | CC11: =COUNTIF($BZ$2:$BZ$209,BZ11) | CD11: =COUNTIF($CA$2:$CA$209,CA11) | CE11: {=IF(N(BQ11)>=MIN_N,BP11,IF(CD11>=MIN_N,MEDIAN(IF($CA$2:$CA$209=CA11,$O$2:$O$209)),IF(CC11>=MIN_N,MEDIAN(IF($BZ$2:$BZ$209=BZ11,$O$2:$O$209)),MEDIAN(IF($BY$2:$BY$209=BY11,$O$2:$O$209)))))} | CF11: =IF(N(BQ11)>=MIN_N,"mercado "&BR11,IF(CD11>=MIN_N,"modelo+año+km",IF(CC11>=MIN_N,"modelo+año","modelo"))) | CG11: =(CE11-O11)/CE11 | CH11: =IF(COUNTIFS(FR_FUEL,K11,FR_YEAR,AP11)>0,1,0) | CI11: =IF(COUNTIFS(FR_FUEL,K11,FR_YEAR,AP11-1)>0,1,0) | CJ11: =IF(N(AQ11)>0,AP11*100+AQ11,IF(AND(CH11=1,CI11=1),(AP11-1)*100+1,AP11*100+1)) | CK11: =IF(OR(K11="hibrido",K11="glp",K11="gnc",K11="phev"),"ECO",IF(K11="electrico","CERO",IF(K11="gasolina",IF(CJ11>=GAS_C_YM,"C",IF(CJ11>=GAS_B_YM,"B","A")),IF(K11="diesel",IF(CJ11>=DIE_C_YM,"C",IF(CJ11>=DIE_B_YM,"B","A")),"")))) | CL11: C | CM11: =IF(AU11="sí","sí",IF(AS11="regla",IF(AND(N(AQ11)=0,CH11=1),"sí","no"),"no")) | CN11: =IFERROR(VLOOKUP(F11,MOD_TBL,16,0),IFERROR(VLOOKUP(E11,OCU_TBL,2,0),NEUTRO)) | CO11: =SUMIFS(MOT_AJUSTE,MOT_MOTOR,G11,MOT_MARCA,E11,MOT_DESDE,"<="&M11,MOT_HASTA,">="&M11)+SUMIFS(MOT_AJUSTE,MOT_MOTOR,G11,MOT_MARCA,"(todas)",MOT_DESDE,"<="&M11,MOT_HASTA,">="&M11)+SUMIFS(MOT_AJUSTE,MOT_MOTOR,"(cualquiera)",MOT_MARCA,E11,MOT_DESDE,"<="&M11,MOT_HASTA,">="&M11) | CP11: =SUMIFS(COMB_AJUSTE,COMB_COMB,K11) | CQ11: =COUNTIFS(MOT_MOTOR,G11,MOT_MARCA,E11,MOT_DESDE,"<="&M11,MOT_HASTA,">="&M11)+COUNTIFS(MOT_MOTOR,G11,MOT_MARCA,"(todas)",MOT_DESDE,"<="&M11,MOT_HASTA,">="&M11)+COUNTIFS(MOT_MOTOR,"(cualquiera)",MOT_MARCA,E11,MOT_DESDE,"<="&M11,MOT_HASTA,">="&M11) | CR11: =IF(AND(K11="diesel",CQ11=0),MIN(CN11,NEUTRO),CN11) | CS11: =MAX(0,MIN(100,CR11+CO11+CP11-IF(AX11="sí",ROB_PEN,0))) | CT11: =100-MAX(0,N11-KM_TOPE_DESDE)/1000*KM_TOPE_PTS | CU11: =MAX(0,MIN(100,50+CG11*PRECIO_PEND,CT11)) | CV11: =MAX(0,100*(1-N11/KM_MAX)) | CW11: =IF(BX11<KMA_SOSP,IF(AA11="sí",100,KMA_PEN),IF(BX11<=KMA_IDEAL_MAX,100,MAX(0,100*(KMA_CERO-BX11)/(KMA_CERO-KMA_IDEAL_MAX)))) | CX11: =MAX(0,MIN(100,100*(M11-ANIO_MIN)/(ANIO_ACTUAL-ANIO_MIN))) | CY11: =W_KMT*CV11+W_KMA*CW11+W_EDAD*CX11 | CZ11: =E11&"|"&G11 | DA11: =IFERROR(VLOOKUP(CZ11,DIST_TBL,2,0),"") | DB11: =E_ITV*(V11="sí")+E_LIBRO*(W11="sí")+E_PROP*IF(Y11=1,1,IF(Y11=2,0.5,0))+E_CORREA*IF(OR(DA11="cadena",AND(X11="sí",BH11="sí")),1,IF(X11="sí",0.5,0))+E_FACT*(BI11="sí") | DC11: =MAX(0,MIN(100,IFERROR(VLOOKUP(CL11,ETQ_TBL,2,0),0)-IF(CM11="sí",ETQ_PEN_DUD,IF(AS11="regla",ETQ_PEN_REGLA,0)))) | DD11: =IF(K11<>"gasolina","",IFERROR(VLOOKUP(F11,CONS_MOD_TBL,2,0),IFERROR(VLOOKUP(L11,CONS_SEG_TBL,2,0),""))) | DE11: =IF(DD11="",NEUTRO,MAX(0,MIN(100,100*(CONS_REF_MAX-DD11)/(CONS_REF_MAX-CONS_REF_MIN)))) | DF11: =IFERROR(VLOOKUP(L11,SEGURO_TBL,3,0),"") | DG11: =IF(DF11="",NEUTRO,MAX(0,MIN(100,100*(SEG_REF_MAX-DF11)/(SEG_REF_MAX-SEG_REF_MIN)))) | DH11: =IFERROR(VLOOKUP(E11,MANT_MARCA_TBL,2,0)+0,NEUTRO) | DI11: =IF(DA11="",NEUTRO,IFERROR(VLOOKUP(DA11,DIST_PTS_TBL,2,0)+0,NEUTRO)) | DJ11: =(DH11+DI11)/2 | DK11: =W_CONS*DE11+W_SEG*DG11+W_MANT*DJ11 | DL11: =IF(N(AB11)>0,AB11,IF(AND(R11="profesional",SG_LEGAL_ON=1),GAR_LEGAL,0)) | DM11: =MAX(0,MIN(100,SG_GAR*MIN(1,DL11/SG_GAR_FULL)+SG_AMPL*(AC11="sí")+SG_KMC*(AF11="sí")+SG_REV*(N(AE11)>0)+SG_DEV*MIN(1,N(AG11)/SG_DEV_FULL)+SG_HIST*(W11="sí")-IF(AND(R11="particular",DL11=0),SG_PART_PEN,0))) | DN11: =IF(BK11="",NEUTRO,MAX(0,MIN(100,BK11/5*100))) | DO11: =IF(BL11="sí",100,IF(BL11="no",0,NEUTRO)) | DP11: =SV_W_NCAP*DN11+SV_W_ESP*DO11 | DQ11: =MAX(0,MIN(100,ATR_BASE+ATR_ACAB*(BD11<>"")+IF(BE11="16+",ATR_LL16,IF(BE11="sí",ATR_LL,0))+ATR_FAROS*(BF11="sí")+ATR_TINT*(BG11="sí")-ATR_CHAPA*(BE11="chapa"))) | DR11: =EST_W_MOD*(BB11-1)/4*100+EST_W_ATR*DQ11 | DS11: =IF(BA11="",NEUTRO,IFERROR(VLOOKUP(BA11,COLOR_TBL,2,0)+0,NEUTRO)) | DT11: =MAX(0,MIN(100,100*N(BM11)/RV_N_FULL)) | DU11: =IF(OR(BN11="",N(BO11)<RV_DIAS_MIN),NEUTRO,MAX(0,MIN(100,100*(RV_DIAS_CERO-BN11)/(RV_DIAS_CERO-RV_DIAS_FULL)))) | DV11: =RV_W_LIQ*DT11+RV_W_DIAS*DU11+RV_W_ETQ*DC11 | DW11: =IFERROR(VLOOKUP(L11,CARR_PEN_TBL,2,0),0) | DX11: =W_FIAB*CS11+W_PRECIO*CU11+W_KMEDAD*CY11+W_ESTADO*DB11+W_USO*DK11+W_SEGURIDAD*DM11+W_SEGVIAL*DP11+W_ESTETICA*DR11+W_COLOR*DS11+W_REVENTA*DV11-DW11-EG11 | DY11: =IF(N(I11)>0,I11,IFERROR(ROUND(_xlfn.NUMBERVALUE(LEFT(G11,FIND(" ",G11&" ")-1),".")*1000,0),99999)) | DZ11: =IF(R11="profesional",0,IF(O11<CUOTA_VALOR_MAX,IF(BW11>ITP_TRAMO_ALTO,SUMIFS(CF_CUOTA,CF_MAS,ITP_TRAMO_ALTO,CF_CCMIN,"<="&DY11,CF_CCMAX,">="&DY11),IF(BW11>ITP_TRAMO_BAJO,SUMIFS(CF_CUOTA,CF_MAS,ITP_TRAMO_BAJO,CF_CCMIN,"<="&DY11,CF_CCMAX,">="&DY11),O11*ITP_TIPO)),O11*ITP_TIPO)) | EA11: =IF(R11="profesional",N(AK11),0) | EB11: =IF(AND(R11="profesional",ISNUMBER(AK11),AL11="sí"),0,TASA_DGT) | EC11: =INFORME_DGT | ED11: =O11+EA11+DZ11+EB11+EC11 | EE11: =ED11+N(DF11) | EF11: =MAX(0,ED11-TOTAL_MAX) | EG11: =EF11/100*PEN_100 | EH11: =IF(R11="particular",ED11+IF(AND(DA11<>"cadena",X11<>"sí"),RES_CORREA,0)+IF(AND(BJ11<>"sí",BW11>=RES_NEUM_EDAD),RES_NEUM,0),"") | EI11: =IF(ED11<=TOTAL_MAX,"sí",IF(ED11<=TECHO,"negociar","no")) | EJ11: =ROUND(DX11,9) | EK11: =IF(EI11<>"no",SUMPRODUCT(($EI$2:$EI$209<>"no")*($EJ$2:$EJ$209>EJ11))+SUMPRODUCT(($EI$2:EI11<>"no")*($EJ$2:EJ11=EJ11)),"")
A12: cochesnet:70216779 | B12: cochesnet | C12: https://www.coches.net/opel-corsa-13-ecoflex-75-cv-essentia-5p-diesel-2012-en-valencia-70216779-covo.aspx | D12: OPEL Corsa 1.3 ecoFLEX 75 CV Essentia | E12: Opel | F12: Opel Corsa | G12: 1.3 | H12: 1.3 ecoFLEX 75 CV Essentia | J12: 75 | K12: diesel | L12: utilitario | M12: 2011 | N12: 193600 | O12: 4300 | P12: manual | Q12: no | R12: profesional | S12: Motor Valencia Alaquàs | T12: 2026-09-11T18:55:45Z | U12: 16 | V12: sí | Z12: sí | AB12: 12 | AH12: 4300 | AI12: 4300 | AM12: 7.4 | AO12: 2011 | AP12: 2011 | AS12: regla | AT12: 2012 | AU12: no | AV12: B | AX12: no | AY12: no | AZ12: COMMON.COLOR_BLUE | BA12: azul | BB12: 2 | BC12: (por segmento) | BK12: 5 | BM12: 456 | BN12: 0.051261574 | BO12: 11 | BP12: 3500 | BQ12: 7 | BR12: modelo+año+km | BT12: año a confirmar: la URL/título dice 2012; vendedor profesional: sin ITP (operación con IVA/REBU, confirmar en factura); gastos de gestión del vendedor no indicados: se suma la tasa DGT; preguntar el precio final; diésel: motor sin fuente de fiabilidad (fiabilidad limitada a neutra); etiqueta B deducida por fecha (sin matrícula ni dato del anuncio) | BU12: MOTOR MUY DURADERO Y MINIMO CONSUMO, SE ENTREGA CON MANTENIMIENTO COMPLETO Y KIT CADENA DISTRIBUCION REALIZADO, ITV RECIEN PASADA, CON GARANTIA, LIMPIO Y DESINFECTADO DE TAPICERIA, SE ACEPTA PRUEBAS VEHICULO DONDE DESIGNE COMPRADOR, VISITE STOCK VEHICULOS DISPONIBLES EN NUESTRA PAGINA WEB | BV12: https://www.coches.net/opel-corsa-13-ecoflex-75-cv-essentia-5p-diesel-2012-en-valencia-70216779-covo.aspx (window.__INITIAL_PROPS__.ad) /home/user/Alopecia/buscador-coches/raw/cochesnet/ee37a0c149e995e6.json | BW12: =MAX(ANIO_ACTUAL-M12,0) | BX12: =N12/MAX(BW12,0.5) | BY12: =F12 | BZ12: =BY12&"|"&INT(M12/SEG_ANIO)*SEG_ANIO | CA12: =BZ12&"|"&INT(N12/SEG_KM)*SEG_KM | CB12: =COUNTIF($BY$2:$BY$209,BY12) | CC12: =COUNTIF($BZ$2:$BZ$209,BZ12) | CD12: =COUNTIF($CA$2:$CA$209,CA12) | CE12: {=IF(N(BQ12)>=MIN_N,BP12,IF(CD12>=MIN_N,MEDIAN(IF($CA$2:$CA$209=CA12,$O$2:$O$209)),IF(CC12>=MIN_N,MEDIAN(IF($BZ$2:$BZ$209=BZ12,$O$2:$O$209)),MEDIAN(IF($BY$2:$BY$209=BY12,$O$2:$O$209)))))} | CF12: =IF(N(BQ12)>=MIN_N,"mercado "&BR12,IF(CD12>=MIN_N,"modelo+año+km",IF(CC12>=MIN_N,"modelo+año","modelo"))) | CG12: =(CE12-O12)/CE12 | CH12: =IF(COUNTIFS(FR_FUEL,K12,FR_YEAR,AP12)>0,1,0) | CI12: =IF(COUNTIFS(FR_FUEL,K12,FR_YEAR,AP12-1)>0,1,0) | CJ12: =IF(N(AQ12)>0,AP12*100+AQ12,IF(AND(CH12=1,CI12=1),(AP12-1)*100+1,AP12*100+1)) | CK12: =IF(OR(K12="hibrido",K12="glp",K12="gnc",K12="phev"),"ECO",IF(K12="electrico","CERO",IF(K12="gasolina",IF(CJ12>=GAS_C_YM,"C",IF(CJ12>=GAS_B_YM,"B","A")),IF(K12="diesel",IF(CJ12>=DIE_C_YM,"C",IF(CJ12>=DIE_B_YM,"B","A")),"")))) | CL12: =CK12 | CM12: =IF(AU12="sí","sí",IF(AS12="regla",IF(AND(N(AQ12)=0,CH12=1),"sí","no"),"no")) | CN12: =IFERROR(VLOOKUP(F12,MOD_TBL,16,0),IFERROR(VLOOKUP(E12,OCU_TBL,2,0),NEUTRO)) | CO12: =SUMIFS(MOT_AJUSTE,MOT_MOTOR,G12,MOT_MARCA,E12,MOT_DESDE,"<="&M12,MOT_HASTA,">="&M12)+SUMIFS(MOT_AJUSTE,MOT_MOTOR,G12,MOT_MARCA,"(todas)",MOT_DESDE,"<="&M12,MOT_HASTA,">="&M12)+SUMIFS(MOT_AJUSTE,MOT_MOTOR,"(cualquiera)",MOT_MARCA,E12,MOT_DESDE,"<="&M12,MOT_HASTA,">="&M12) | CP12: =SUMIFS(COMB_AJUSTE,COMB_COMB,K12) | CQ12: =COUNTIFS(MOT_MOTOR,G12,MOT_MARCA,E12,MOT_DESDE,"<="&M12,MOT_HASTA,">="&M12)+COUNTIFS(MOT_MOTOR,G12,MOT_MARCA,"(todas)",MOT_DESDE,"<="&M12,MOT_HASTA,">="&M12)+COUNTIFS(MOT_MOTOR,"(cualquiera)",MOT_MARCA,E12,MOT_DESDE,"<="&M12,MOT_HASTA,">="&M12) | CR12: =IF(AND(K12="diesel",CQ12=0),MIN(CN12,NEUTRO),CN12) | CS12: =MAX(0,MIN(100,CR12+CO12+CP12-IF(AX12="sí",ROB_PEN,0))) | CT12: =100-MAX(0,N12-KM_TOPE_DESDE)/1000*KM_TOPE_PTS | CU12: =MAX(0,MIN(100,50+CG12*PRECIO_PEND,CT12)) | CV12: =MAX(0,100*(1-N12/KM_MAX)) | CW12: =IF(BX12<KMA_SOSP,IF(AA12="sí",100,KMA_PEN),IF(BX12<=KMA_IDEAL_MAX,100,MAX(0,100*(KMA_CERO-BX12)/(KMA_CERO-KMA_IDEAL_MAX)))) | CX12: =MAX(0,MIN(100,100*(M12-ANIO_MIN)/(ANIO_ACTUAL-ANIO_MIN))) | CY12: =W_KMT*CV12+W_KMA*CW12+W_EDAD*CX12 | CZ12: =E12&"|"&G12 | DA12: =IFERROR(VLOOKUP(CZ12,DIST_TBL,2,0),"") | DB12: =E_ITV*(V12="sí")+E_LIBRO*(W12="sí")+E_PROP*IF(Y12=1,1,IF(Y12=2,0.5,0))+E_CORREA*IF(OR(DA12="cadena",AND(X12="sí",BH12="sí")),1,IF(X12="sí",0.5,0))+E_FACT*(BI12="sí") | DC12: =MAX(0,MIN(100,IFERROR(VLOOKUP(CL12,ETQ_TBL,2,0),0)-IF(CM12="sí",ETQ_PEN_DUD,IF(AS12="regla",ETQ_PEN_REGLA,0)))) | DD12: =IF(K12<>"gasolina","",IFERROR(VLOOKUP(F12,CONS_MOD_TBL,2,0),IFERROR(VLOOKUP(L12,CONS_SEG_TBL,2,0),""))) | DE12: =IF(DD12="",NEUTRO,MAX(0,MIN(100,100*(CONS_REF_MAX-DD12)/(CONS_REF_MAX-CONS_REF_MIN)))) | DF12: =IFERROR(VLOOKUP(L12,SEGURO_TBL,3,0),"") | DG12: =IF(DF12="",NEUTRO,MAX(0,MIN(100,100*(SEG_REF_MAX-DF12)/(SEG_REF_MAX-SEG_REF_MIN)))) | DH12: =IFERROR(VLOOKUP(E12,MANT_MARCA_TBL,2,0)+0,NEUTRO) | DI12: =IF(DA12="",NEUTRO,IFERROR(VLOOKUP(DA12,DIST_PTS_TBL,2,0)+0,NEUTRO)) | DJ12: =(DH12+DI12)/2 | DK12: =W_CONS*DE12+W_SEG*DG12+W_MANT*DJ12 | DL12: =IF(N(AB12)>0,AB12,IF(AND(R12="profesional",SG_LEGAL_ON=1),GAR_LEGAL,0)) | DM12: =MAX(0,MIN(100,SG_GAR*MIN(1,DL12/SG_GAR_FULL)+SG_AMPL*(AC12="sí")+SG_KMC*(AF12="sí")+SG_REV*(N(AE12)>0)+SG_DEV*MIN(1,N(AG12)/SG_DEV_FULL)+SG_HIST*(W12="sí")-IF(AND(R12="particular",DL12=0),SG_PART_PEN,0))) | DN12: =IF(BK12="",NEUTRO,MAX(0,MIN(100,BK12/5*100))) | DO12: =IF(BL12="sí",100,IF(BL12="no",0,NEUTRO)) | DP12: =SV_W_NCAP*DN12+SV_W_ESP*DO12 | DQ12: =MAX(0,MIN(100,ATR_BASE+ATR_ACAB*(BD12<>"")+IF(BE12="16+",ATR_LL16,IF(BE12="sí",ATR_LL,0))+ATR_FAROS*(BF12="sí")+ATR_TINT*(BG12="sí")-ATR_CHAPA*(BE12="chapa"))) | DR12: =EST_W_MOD*(BB12-1)/4*100+EST_W_ATR*DQ12 | DS12: =IF(BA12="",NEUTRO,IFERROR(VLOOKUP(BA12,COLOR_TBL,2,0)+0,NEUTRO)) | DT12: =MAX(0,MIN(100,100*N(BM12)/RV_N_FULL)) | DU12: =IF(OR(BN12="",N(BO12)<RV_DIAS_MIN),NEUTRO,MAX(0,MIN(100,100*(RV_DIAS_CERO-BN12)/(RV_DIAS_CERO-RV_DIAS_FULL)))) | DV12: =RV_W_LIQ*DT12+RV_W_DIAS*DU12+RV_W_ETQ*DC12 | DW12: =IFERROR(VLOOKUP(L12,CARR_PEN_TBL,2,0),0) | DX12: =W_FIAB*CS12+W_PRECIO*CU12+W_KMEDAD*CY12+W_ESTADO*DB12+W_USO*DK12+W_SEGURIDAD*DM12+W_SEGVIAL*DP12+W_ESTETICA*DR12+W_COLOR*DS12+W_REVENTA*DV12-DW12-EG12 | DY12: =IF(N(I12)>0,I12,IFERROR(ROUND(_xlfn.NUMBERVALUE(LEFT(G12,FIND(" ",G12&" ")-1),".")*1000,0),99999)) | DZ12: =IF(R12="profesional",0,IF(O12<CUOTA_VALOR_MAX,IF(BW12>ITP_TRAMO_ALTO,SUMIFS(CF_CUOTA,CF_MAS,ITP_TRAMO_ALTO,CF_CCMIN,"<="&DY12,CF_CCMAX,">="&DY12),IF(BW12>ITP_TRAMO_BAJO,SUMIFS(CF_CUOTA,CF_MAS,ITP_TRAMO_BAJO,CF_CCMIN,"<="&DY12,CF_CCMAX,">="&DY12),O12*ITP_TIPO)),O12*ITP_TIPO)) | EA12: =IF(R12="profesional",N(AK12),0) | EB12: =IF(AND(R12="profesional",ISNUMBER(AK12),AL12="sí"),0,TASA_DGT) | EC12: =INFORME_DGT | ED12: =O12+EA12+DZ12+EB12+EC12 | EE12: =ED12+N(DF12) | EF12: =MAX(0,ED12-TOTAL_MAX) | EG12: =EF12/100*PEN_100 | EH12: =IF(R12="particular",ED12+IF(AND(DA12<>"cadena",X12<>"sí"),RES_CORREA,0)+IF(AND(BJ12<>"sí",BW12>=RES_NEUM_EDAD),RES_NEUM,0),"") | EI12: =IF(ED12<=TOTAL_MAX,"sí",IF(ED12<=TECHO,"negociar","no")) | EJ12: =ROUND(DX12,9) | EK12: =IF(EI12<>"no",SUMPRODUCT(($EI$2:$EI$209<>"no")*($EJ$2:$EJ$209>EJ12))+SUMPRODUCT(($EI$2:EI12<>"no")*($EJ$2:EJ12=EJ12)),"")
A13: cochesnet:71625576 | B13: cochesnet | C13: https://www.coches.net/opel-corsa-10-essentia-3p-gasolina-2011-en-valencia-71625576-covo.aspx | D13: OPEL Corsa 1.0 Essentia | E13: Opel | F13: Opel Corsa | G13: 1.0 | H13: 1.0 Essentia | K13: gasolina | L13: utilitario | M13: 2010 | N13: 205000 | O13: 3990 | P13: manual | Q13: no | R13: profesional | S13: Fos Motor Valencia | T13: 2026-09-29T16:17:21Z | U13: 11 | Z13: sí | AB13: 12 | AF13: sí | AH13: 3990 | AI13: 3990 | AM13: 0.1 | AO13: 2010 | AP13: 2010 | AR13: C | AS13: anuncio | AT13: 2011 | AU13: no | AV13: C | AX13: no | AY13: no | AZ13: COMMON.COLOR_WHITE | BA13: blanco | BB13: 2 | BC13: (por segmento) | BK13: 5 | BM13: 456 | BN13: 0.051261574 | BO13: 11 | BP13: 2990 | BQ13: 4 | BR13: modelo+año+km | BT13: año a confirmar: la URL/título dice 2011; vendedor profesional: sin ITP (operación con IVA/REBU, confirmar en factura); gastos de gestión del vendedor no indicados: se suma la tasa DGT; preguntar el precio final; revisar: no menciona la ITV | BU13: Opel Corsa en la Motorización 1.0i de 60Cv. Visitas solo con cita previa. -Kilómetros certificados. -Nacional. Equipamiento destacado: -Volante Multifunción. -Elevalunas eléctricos -Aire Acondicionado -Cierre Centralizado -Espejos con regulación -Y mucho más… Mantenimieto destacado: -Aceite y filtro. -Filtro de Habitáculo. -Filtro de Aire. En definitiva, una unidad de reestreno lista para disfrutar. Servicios adicionales: -Envío a toda España (consultar condiciones) -Garantía europea adicional y/o ampliada (consultar precios) -Cambio de titularidad: 150 € ¡Contacta para más información o reservar tu visita! | BV13: https://www.coches.net/opel-corsa-10-essentia-3p-gasolina-2011-en-valencia-71625576-covo.aspx (window.__INITIAL_PROPS__.ad) /home/user/Alopecia/buscador-coches/raw/cochesnet/25f38d7266968fd1.json | BW13: =MAX(ANIO_ACTUAL-M13,0) | BX13: =N13/MAX(BW13,0.5) | BY13: =F13 | BZ13: =BY13&"|"&INT(M13/SEG_ANIO)*SEG_ANIO | CA13: =BZ13&"|"&INT(N13/SEG_KM)*SEG_KM | CB13: =COUNTIF($BY$2:$BY$209,BY13) | CC13: =COUNTIF($BZ$2:$BZ$209,BZ13) | CD13: =COUNTIF($CA$2:$CA$209,CA13) | CE13: {=IF(N(BQ13)>=MIN_N,BP13,IF(CD13>=MIN_N,MEDIAN(IF($CA$2:$CA$209=CA13,$O$2:$O$209)),IF(CC13>=MIN_N,MEDIAN(IF($BZ$2:$BZ$209=BZ13,$O$2:$O$209)),MEDIAN(IF($BY$2:$BY$209=BY13,$O$2:$O$209)))))} | CF13: =IF(N(BQ13)>=MIN_N,"mercado "&BR13,IF(CD13>=MIN_N,"modelo+año+km",IF(CC13>=MIN_N,"modelo+año","modelo"))) | CG13: =(CE13-O13)/CE13 | CH13: =IF(COUNTIFS(FR_FUEL,K13,FR_YEAR,AP13)>0,1,0) | CI13: =IF(COUNTIFS(FR_FUEL,K13,FR_YEAR,AP13-1)>0,1,0) | CJ13: =IF(N(AQ13)>0,AP13*100+AQ13,IF(AND(CH13=1,CI13=1),(AP13-1)*100+1,AP13*100+1)) | CK13: =IF(OR(K13="hibrido",K13="glp",K13="gnc",K13="phev"),"ECO",IF(K13="electrico","CERO",IF(K13="gasolina",IF(CJ13>=GAS_C_YM,"C",IF(CJ13>=GAS_B_YM,"B","A")),IF(K13="diesel",IF(CJ13>=DIE_C_YM,"C",IF(CJ13>=DIE_B_YM,"B","A")),"")))) | CL13: C | CM13: =IF(AU13="sí","sí",IF(AS13="regla",IF(AND(N(AQ13)=0,CH13=1),"sí","no"),"no")) | CN13: =IFERROR(VLOOKUP(F13,MOD_TBL,16,0),IFERROR(VLOOKUP(E13,OCU_TBL,2,0),NEUTRO)) | CO13: =SUMIFS(MOT_AJUSTE,MOT_MOTOR,G13,MOT_MARCA,E13,MOT_DESDE,"<="&M13,MOT_HASTA,">="&M13)+SUMIFS(MOT_AJUSTE,MOT_MOTOR,G13,MOT_MARCA,"(todas)",MOT_DESDE,"<="&M13,MOT_HASTA,">="&M13)+SUMIFS(MOT_AJUSTE,MOT_MOTOR,"(cualquiera)",MOT_MARCA,E13,MOT_DESDE,"<="&M13,MOT_HASTA,">="&M13) | CP13: =SUMIFS(COMB_AJUSTE,COMB_COMB,K13) | CQ13: =COUNTIFS(MOT_MOTOR,G13,MOT_MARCA,E13,MOT_DESDE,"<="&M13,MOT_HASTA,">="&M13)+COUNTIFS(MOT_MOTOR,G13,MOT_MARCA,"(todas)",MOT_DESDE,"<="&M13,MOT_HASTA,">="&M13)+COUNTIFS(MOT_MOTOR,"(cualquiera)",MOT_MARCA,E13,MOT_DESDE,"<="&M13,MOT_HASTA,">="&M13) | CR13: =IF(AND(K13="diesel",CQ13=0),MIN(CN13,NEUTRO),CN13) | CS13: =MAX(0,MIN(100,CR13+CO13+CP13-IF(AX13="sí",ROB_PEN,0))) | CT13: =100-MAX(0,N13-KM_TOPE_DESDE)/1000*KM_TOPE_PTS | CU13: =MAX(0,MIN(100,50+CG13*PRECIO_PEND,CT13)) | CV13: =MAX(0,100*(1-N13/KM_MAX)) | CW13: =IF(BX13<KMA_SOSP,IF(AA13="sí",100,KMA_PEN),IF(BX13<=KMA_IDEAL_MAX,100,MAX(0,100*(KMA_CERO-BX13)/(KMA_CERO-KMA_IDEAL_MAX)))) | CX13: =MAX(0,MIN(100,100*(M13-ANIO_MIN)/(ANIO_ACTUAL-ANIO_MIN))) | CY13: =W_KMT*CV13+W_KMA*CW13+W_EDAD*CX13 | CZ13: =E13&"|"&G13 | DA13: =IFERROR(VLOOKUP(CZ13,DIST_TBL,2,0),"") | DB13: =E_ITV*(V13="sí")+E_LIBRO*(W13="sí")+E_PROP*IF(Y13=1,1,IF(Y13=2,0.5,0))+E_CORREA*IF(OR(DA13="cadena",AND(X13="sí",BH13="sí")),1,IF(X13="sí",0.5,0))+E_FACT*(BI13="sí") | DC13: =MAX(0,MIN(100,IFERROR(VLOOKUP(CL13,ETQ_TBL,2,0),0)-IF(CM13="sí",ETQ_PEN_DUD,IF(AS13="regla",ETQ_PEN_REGLA,0)))) | DD13: =IF(K13<>"gasolina","",IFERROR(VLOOKUP(F13,CONS_MOD_TBL,2,0),IFERROR(VLOOKUP(L13,CONS_SEG_TBL,2,0),""))) | DE13: =IF(DD13="",NEUTRO,MAX(0,MIN(100,100*(CONS_REF_MAX-DD13)/(CONS_REF_MAX-CONS_REF_MIN)))) | DF13: =IFERROR(VLOOKUP(L13,SEGURO_TBL,3,0),"") | DG13: =IF(DF13="",NEUTRO,MAX(0,MIN(100,100*(SEG_REF_MAX-DF13)/(SEG_REF_MAX-SEG_REF_MIN)))) | DH13: =IFERROR(VLOOKUP(E13,MANT_MARCA_TBL,2,0)+0,NEUTRO) | DI13: =IF(DA13="",NEUTRO,IFERROR(VLOOKUP(DA13,DIST_PTS_TBL,2,0)+0,NEUTRO)) | DJ13: =(DH13+DI13)/2 | DK13: =W_CONS*DE13+W_SEG*DG13+W_MANT*DJ13 | DL13: =IF(N(AB13)>0,AB13,IF(AND(R13="profesional",SG_LEGAL_ON=1),GAR_LEGAL,0)) | DM13: =MAX(0,MIN(100,SG_GAR*MIN(1,DL13/SG_GAR_FULL)+SG_AMPL*(AC13="sí")+SG_KMC*(AF13="sí")+SG_REV*(N(AE13)>0)+SG_DEV*MIN(1,N(AG13)/SG_DEV_FULL)+SG_HIST*(W13="sí")-IF(AND(R13="particular",DL13=0),SG_PART_PEN,0))) | DN13: =IF(BK13="",NEUTRO,MAX(0,MIN(100,BK13/5*100))) | DO13: =IF(BL13="sí",100,IF(BL13="no",0,NEUTRO)) | DP13: =SV_W_NCAP*DN13+SV_W_ESP*DO13 | DQ13: =MAX(0,MIN(100,ATR_BASE+ATR_ACAB*(BD13<>"")+IF(BE13="16+",ATR_LL16,IF(BE13="sí",ATR_LL,0))+ATR_FAROS*(BF13="sí")+ATR_TINT*(BG13="sí")-ATR_CHAPA*(BE13="chapa"))) | DR13: =EST_W_MOD*(BB13-1)/4*100+EST_W_ATR*DQ13 | DS13: =IF(BA13="",NEUTRO,IFERROR(VLOOKUP(BA13,COLOR_TBL,2,0)+0,NEUTRO)) | DT13: =MAX(0,MIN(100,100*N(BM13)/RV_N_FULL)) | DU13: =IF(OR(BN13="",N(BO13)<RV_DIAS_MIN),NEUTRO,MAX(0,MIN(100,100*(RV_DIAS_CERO-BN13)/(RV_DIAS_CERO-RV_DIAS_FULL)))) | DV13: =RV_W_LIQ*DT13+RV_W_DIAS*DU13+RV_W_ETQ*DC13 | DW13: =IFERROR(VLOOKUP(L13,CARR_PEN_TBL,2,0),0) | DX13: =W_FIAB*CS13+W_PRECIO*CU13+W_KMEDAD*CY13+W_ESTADO*DB13+W_USO*DK13+W_SEGURIDAD*DM13+W_SEGVIAL*DP13+W_ESTETICA*DR13+W_COLOR*DS13+W_REVENTA*DV13-DW13-EG13 | DY13: =IF(N(I13)>0,I13,IFERROR(ROUND(_xlfn.NUMBERVALUE(LEFT(G13,FIND(" ",G13&" ")-1),".")*1000,0),99999)) | DZ13: =IF(R13="profesional",0,IF(O13<CUOTA_VALOR_MAX,IF(BW13>ITP_TRAMO_ALTO,SUMIFS(CF_CUOTA,CF_MAS,ITP_TRAMO_ALTO,CF_CCMIN,"<="&DY13,CF_CCMAX,">="&DY13),IF(BW13>ITP_TRAMO_BAJO,SUMIFS(CF_CUOTA,CF_MAS,ITP_TRAMO_BAJO,CF_CCMIN,"<="&DY13,CF_CCMAX,">="&DY13),O13*ITP_TIPO)),O13*ITP_TIPO)) | EA13: =IF(R13="profesional",N(AK13),0) | EB13: =IF(AND(R13="profesional",ISNUMBER(AK13),AL13="sí"),0,TASA_DGT) | EC13: =INFORME_DGT | ED13: =O13+EA13+DZ13+EB13+EC13 | EE13: =ED13+N(DF13) | EF13: =MAX(0,ED13-TOTAL_MAX) | EG13: =EF13/100*PEN_100 | EH13: =IF(R13="particular",ED13+IF(AND(DA13<>"cadena",X13<>"sí"),RES_CORREA,0)+IF(AND(BJ13<>"sí",BW13>=RES_NEUM_EDAD),RES_NEUM,0),"") | EI13: =IF(ED13<=TOTAL_MAX,"sí",IF(ED13<=TECHO,"negociar","no")) | EJ13: =ROUND(DX13,9) | EK13: =IF(EI13<>"no",SUMPRODUCT(($EI$2:$EI$209<>"no")*($EJ$2:$EJ$209>EJ13))+SUMPRODUCT(($EI$2:EI13<>"no")*($EJ$2:EJ13=EJ13)),"")
A14: cochesnet:71339047 | B14: cochesnet | C14: https://www.coches.net/opel-astra-13-ecoflex-ss-selective-5p-diesel-2013-en-valencia-71339047-covo.aspx | D14: OPEL Astra 1.3 ecoFlex SS Selective | E14: Opel | F14: Opel Astra | G14: 1.3 | H14: 1.3 ecoFlex SS Selective | K14: diesel | L14: compacto | M14: 2012 | N14: 215000 | O14: 4490 | P14: manual | Q14: no | R14: profesional | S14: V.O. Eliana San Antonio de Benagéber | T14: 2026-08-21T14:26:39Z | U14: 16 | Z14: sí | AB14: 12 | AH14: 4490 | AM14: 19.1 | AO14: 2012 | AP14: 2012 | AR14: B | AS14: anuncio | AT14: 2013 | AU14: no | AV14: B | AX14: no | AY14: no | AZ14: COMMON.COLOR_GRAY | BA14: gris_medio | BB14: 3 | BC14: (por segmento) | BG14: sí | BM14: 402 | BN14: 0.062800926 | BO14: 4 | BP14: 4490 | BQ14: 7 | BR14: modelo+año+km | BT14: año a confirmar: la URL/título dice 2013; vendedor profesional: sin ITP (operación con IVA/REBU, confirmar en factura); gastos de gestión del vendedor no indicados: se suma la tasa DGT; preguntar el precio final; Euro NCAP de la generación PENDIENTE (seguridad neutra); diésel: motor sin fuente de fiabilidad (fiabilidad limitada a neutra); revisar: no menciona la ITV | BU14: Este Opel Astra Selective combina equipamiento multimedia completo con control de crucero y ordenador de viaje para optimizar cada trayecto. Dirección asistida eléctrica con endurecimiento progresivo, aire acondicionado, asientos delanteros ajustables manualmente y volante multifunción regulable ofrecen confort y practicidad diaria. Cristales tintados, retrovisores eléctricos desempañables y elevalunas con un solo toque completan la experiencia de conducción. Sistema de ventilación con filtros de polen y carbón activo, junto con limpiaparabrisas delantero, garantizan habitabilidad. Etiqueta medioambiental B facilita acceso a zonas de tráfico limitado. | BV14: https://www.coches.net/opel-astra-13-ecoflex-ss-selective-5p-diesel-2013-en-valencia-71339047-covo.aspx (window.__INITIAL_PROPS__.ad) /home/user/Alopecia/buscador-coches/raw/cochesnet/127119c37c17981d.json | BW14: =MAX(ANIO_ACTUAL-M14,0) | BX14: =N14/MAX(BW14,0.5) | BY14: =F14 | BZ14: =BY14&"|"&INT(M14/SEG_ANIO)*SEG_ANIO | CA14: =BZ14&"|"&INT(N14/SEG_KM)*SEG_KM | CB14: =COUNTIF($BY$2:$BY$209,BY14) | CC14: =COUNTIF($BZ$2:$BZ$209,BZ14) | CD14: =COUNTIF($CA$2:$CA$209,CA14) | CE14: {=IF(N(BQ14)>=MIN_N,BP14,IF(CD14>=MIN_N,MEDIAN(IF($CA$2:$CA$209=CA14,$O$2:$O$209)),IF(CC14>=MIN_N,MEDIAN(IF($BZ$2:$BZ$209=BZ14,$O$2:$O$209)),MEDIAN(IF($BY$2:$BY$209=BY14,$O$2:$O$209)))))} | CF14: =IF(N(BQ14)>=MIN_N,"mercado "&BR14,IF(CD14>=MIN_N,"modelo+año+km",IF(CC14>=MIN_N,"modelo+año","modelo"))) | CG14: =(CE14-O14)/CE14 | CH14: =IF(COUNTIFS(FR_FUEL,K14,FR_YEAR,AP14)>0,1,0) | CI14: =IF(COUNTIFS(FR_FUEL,K14,FR_YEAR,AP14-1)>0,1,0) | CJ14: =IF(N(AQ14)>0,AP14*100+AQ14,IF(AND(CH14=1,CI14=1),(AP14-1)*100+1,AP14*100+1)) | CK14: =IF(OR(K14="hibrido",K14="glp",K14="gnc",K14="phev"),"ECO",IF(K14="electrico","CERO",IF(K14="gasolina",IF(CJ14>=GAS_C_YM,"C",IF(CJ14>=GAS_B_YM,"B","A")),IF(K14="diesel",IF(CJ14>=DIE_C_YM,"C",IF(CJ14>=DIE_B_YM,"B","A")),"")))) | CL14: B | CM14: =IF(AU14="sí","sí",IF(AS14="regla",IF(AND(N(AQ14)=0,CH14=1),"sí","no"),"no")) | CN14: =IFERROR(VLOOKUP(F14,MOD_TBL,16,0),IFERROR(VLOOKUP(E14,OCU_TBL,2,0),NEUTRO)) | CO14: =SUMIFS(MOT_AJUSTE,MOT_MOTOR,G14,MOT_MARCA,E14,MOT_DESDE,"<="&M14,MOT_HASTA,">="&M14)+SUMIFS(MOT_AJUSTE,MOT_MOTOR,G14,MOT_MARCA,"(todas)",MOT_DESDE,"<="&M14,MOT_HASTA,">="&M14)+SUMIFS(MOT_AJUSTE,MOT_MOTOR,"(cualquiera)",MOT_MARCA,E14,MOT_DESDE,"<="&M14,MOT_HASTA,">="&M14) | CP14: =SUMIFS(COMB_AJUSTE,COMB_COMB,K14) | CQ14: =COUNTIFS(MOT_MOTOR,G14,MOT_MARCA,E14,MOT_DESDE,"<="&M14,MOT_HASTA,">="&M14)+COUNTIFS(MOT_MOTOR,G14,MOT_MARCA,"(todas)",MOT_DESDE,"<="&M14,MOT_HASTA,">="&M14)+COUNTIFS(MOT_MOTOR,"(cualquiera)",MOT_MARCA,E14,MOT_DESDE,"<="&M14,MOT_HASTA,">="&M14) | CR14: =IF(AND(K14="diesel",CQ14=0),MIN(CN14,NEUTRO),CN14) | CS14: =MAX(0,MIN(100,CR14+CO14+CP14-IF(AX14="sí",ROB_PEN,0))) | CT14: =100-MAX(0,N14-KM_TOPE_DESDE)/1000*KM_TOPE_PTS | CU14: =MAX(0,MIN(100,50+CG14*PRECIO_PEND,CT14)) | CV14: =MAX(0,100*(1-N14/KM_MAX)) | CW14: =IF(BX14<KMA_SOSP,IF(AA14="sí",100,KMA_PEN),IF(BX14<=KMA_IDEAL_MAX,100,MAX(0,100*(KMA_CERO-BX14)/(KMA_CERO-KMA_IDEAL_MAX)))) | CX14: =MAX(0,MIN(100,100*(M14-ANIO_MIN)/(ANIO_ACTUAL-ANIO_MIN))) | CY14: =W_KMT*CV14+W_KMA*CW14+W_EDAD*CX14 | CZ14: =E14&"|"&G14 | DA14: =IFERROR(VLOOKUP(CZ14,DIST_TBL,2,0),"") | DB14: =E_ITV*(V14="sí")+E_LIBRO*(W14="sí")+E_PROP*IF(Y14=1,1,IF(Y14=2,0.5,0))+E_CORREA*IF(OR(DA14="cadena",AND(X14="sí",BH14="sí")),1,IF(X14="sí",0.5,0))+E_FACT*(BI14="sí") | DC14: =MAX(0,MIN(100,IFERROR(VLOOKUP(CL14,ETQ_TBL,2,0),0)-IF(CM14="sí",ETQ_PEN_DUD,IF(AS14="regla",ETQ_PEN_REGLA,0)))) | DD14: =IF(K14<>"gasolina","",IFERROR(VLOOKUP(F14,CONS_MOD_TBL,2,0),IFERROR(VLOOKUP(L14,CONS_SEG_TBL,2,0),""))) | DE14: =IF(DD14="",NEUTRO,MAX(0,MIN(100,100*(CONS_REF_MAX-DD14)/(CONS_REF_MAX-CONS_REF_MIN)))) | DF14: =IFERROR(VLOOKUP(L14,SEGURO_TBL,3,0),"") | DG14: =IF(DF14="",NEUTRO,MAX(0,MIN(100,100*(SEG_REF_MAX-DF14)/(SEG_REF_MAX-SEG_REF_MIN)))) | DH14: =IFERROR(VLOOKUP(E14,MANT_MARCA_TBL,2,0)+0,NEUTRO) | DI14: =IF(DA14="",NEUTRO,IFERROR(VLOOKUP(DA14,DIST_PTS_TBL,2,0)+0,NEUTRO)) | DJ14: =(DH14+DI14)/2 | DK14: =W_CONS*DE14+W_SEG*DG14+W_MANT*DJ14 | DL14: =IF(N(AB14)>0,AB14,IF(AND(R14="profesional",SG_LEGAL_ON=1),GAR_LEGAL,0)) | DM14: =MAX(0,MIN(100,SG_GAR*MIN(1,DL14/SG_GAR_FULL)+SG_AMPL*(AC14="sí")+SG_KMC*(AF14="sí")+SG_REV*(N(AE14)>0)+SG_DEV*MIN(1,N(AG14)/SG_DEV_FULL)+SG_HIST*(W14="sí")-IF(AND(R14="particular",DL14=0),SG_PART_PEN,0))) | DN14: =IF(BK14="",NEUTRO,MAX(0,MIN(100,BK14/5*100))) | DO14: =IF(BL14="sí",100,IF(BL14="no",0,NEUTRO)) | DP14: =SV_W_NCAP*DN14+SV_W_ESP*DO14 | DQ14: =MAX(0,MIN(100,ATR_BASE+ATR_ACAB*(BD14<>"")+IF(BE14="16+",ATR_LL16,IF(BE14="sí",ATR_LL,0))+ATR_FAROS*(BF14="sí")+ATR_TINT*(BG14="sí")-ATR_CHAPA*(BE14="chapa"))) | DR14: =EST_W_MOD*(BB14-1)/4*100+EST_W_ATR*DQ14 | DS14: =IF(BA14="",NEUTRO,IFERROR(VLOOKUP(BA14,COLOR_TBL,2,0)+0,NEUTRO)) | DT14: =MAX(0,MIN(100,100*N(BM14)/RV_N_FULL)) | DU14: =IF(OR(BN14="",N(BO14)<RV_DIAS_MIN),NEUTRO,MAX(0,MIN(100,100*(RV_DIAS_CERO-BN14)/(RV_DIAS_CERO-RV_DIAS_FULL)))) | DV14: =RV_W_LIQ*DT14+RV_W_DIAS*DU14+RV_W_ETQ*DC14 | DW14: =IFERROR(VLOOKUP(L14,CARR_PEN_TBL,2,0),0) | DX14: =W_FIAB*CS14+W_PRECIO*CU14+W_KMEDAD*CY14+W_ESTADO*DB14+W_USO*DK14+W_SEGURIDAD*DM14+W_SEGVIAL*DP14+W_ESTETICA*DR14+W_COLOR*DS14+W_REVENTA*DV14-DW14-EG14 | DY14: =IF(N(I14)>0,I14,IFERROR(ROUND(_xlfn.NUMBERVALUE(LEFT(G14,FIND(" ",G14&" ")-1),".")*1000,0),99999)) | DZ14: =IF(R14="profesional",0,IF(O14<CUOTA_VALOR_MAX,IF(BW14>ITP_TRAMO_ALTO,SUMIFS(CF_CUOTA,CF_MAS,ITP_TRAMO_ALTO,CF_CCMIN,"<="&DY14,CF_CCMAX,">="&DY14),IF(BW14>ITP_TRAMO_BAJO,SUMIFS(CF_CUOTA,CF_MAS,ITP_TRAMO_BAJO,CF_CCMIN,"<="&DY14,CF_CCMAX,">="&DY14),O14*ITP_TIPO)),O14*ITP_TIPO)) | EA14: =IF(R14="profesional",N(AK14),0) | EB14: =IF(AND(R14="profesional",ISNUMBER(AK14),AL14="sí"),0,TASA_DGT) | EC14: =INFORME_DGT | ED14: =O14+EA14+DZ14+EB14+EC14 | EE14: =ED14+N(DF14) | EF14: =MAX(0,ED14-TOTAL_MAX) | EG14: =EF14/100*PEN_100 | EH14: =IF(R14="particular",ED14+IF(AND(DA14<>"cadena",X14<>"sí"),RES_CORREA,0)+IF(AND(BJ14<>"sí",BW14>=RES_NEUM_EDAD),RES_NEUM,0),"") | EI14: =IF(ED14<=TOTAL_MAX,"sí",IF(ED14<=TECHO,"negociar","no")) | EJ14: =ROUND(DX14,9) | EK14: =IF(EI14<>"no",SUMPRODUCT(($EI$2:$EI$209<>"no")*($EJ$2:$EJ$209>EJ14))+SUMPRODUCT(($EI$2:EI14<>"no")*($EJ$2:EJ14=EJ14)),"")
A15: cochesnet:71725639 | B15: cochesnet | C15: https://www.coches.net/renault-clio-business-15dci85-eco2-5p-diesel-2008-en-valencia-71725639-covo.aspx | D15: RENAULT Clio Business 1.5DCI85 eco2 | E15: Renault | F15: Renault Clio | G15: 1.5 | H15: Business 1.5DCI85 eco2 | K15: diesel | L15: utilitario | M15: 2009 | N15: 160000 | O15: 3990 | P15: manual | Q15: no | R15: profesional | S15: Foios | T15: 2026-10-12T10:42:16Z | U15: 10 | Z15: sí | AB15: 12 | AH15: 3990 | AI15: 3990 | AM15: 7.7 | AO15: 2009 | AP15: 2009 | AS15: regla | AT15: 2008 | AU15: no | AV15: B | AW15: C | AX15: no | AY15: no | AZ15: COMMON.COLOR_GRAY | BA15: gris_medio | BB15: 2 | BC15: (por segmento) | BG15: sí | BK15: 5 | BM15: 332 | BN15: 0.051261574 | BO15: 9 | BP15: 3470 | BQ15: 4 | BR15: modelo+año+km | BT15: año a confirmar: la URL/título dice 2008; anuncio incoherente: dice etiqueta C y por fecha corresponde B; se usa la regla; vendedor profesional: sin ITP (operación con IVA/REBU, confirmar en factura); gastos de gestión del vendedor no indicados: se suma la tasa DGT; preguntar el precio final; diésel: motor sin fuente de fiabilidad (fiabilidad limitada a neutra); etiqueta B deducida por fecha (sin matrícula ni dato del anuncio); revisar: no menciona la ITV | BU15: Este Renault Clio Exception 1.5dCi destaca por su equipamiento multimedia completo con radio AM/FM, reproductor de CD y mandos en el volante, combinado con climatizador automático y dirección asistida progresiva. Incorpora control de crucero, sensor de lluvia en limpiaparabrisas, retrovisores eléctricos desempañables y cristales tintados. Dispone de asientos ajustables en altura con reposacabezas regulables, volante multifuncional de cuero, elevalunas eléctricos en las cuatro puertas y cierre centralizado con mando a distancia. Este modelo ofrece confort y conectividad en un compacto versátil con etiqueta medioambiental C. Este anuncio puede contener errores de valor no contractual | BV15: https://www.coches.net/renault-clio-business-15dci85-eco2-5p-diesel-2008-en-valencia-71725639-covo.aspx (window.__INITIAL_PROPS__.ad) /home/user/Alopecia/buscador-coches/raw/cochesnet/56093e2c37b0b096.json | BW15: =MAX(ANIO_ACTUAL-M15,0) | BX15: =N15/MAX(BW15,0.5) | BY15: =F15 | BZ15: =BY15&"|"&INT(M15/SEG_ANIO)*SEG_ANIO | CA15: =BZ15&"|"&INT(N15/SEG_KM)*SEG_KM | CB15: =COUNTIF($BY$2:$BY$209,BY15) | CC15: =COUNTIF($BZ$2:$BZ$209,BZ15) | CD15: =COUNTIF($CA$2:$CA$209,CA15) | CE15: {=IF(N(BQ15)>=MIN_N,BP15,IF(CD15>=MIN_N,MEDIAN(IF($CA$2:$CA$209=CA15,$O$2:$O$209)),IF(CC15>=MIN_N,MEDIAN(IF($BZ$2:$BZ$209=BZ15,$O$2:$O$209)),MEDIAN(IF($BY$2:$BY$209=BY15,$O$2:$O$209)))))} | CF15: =IF(N(BQ15)>=MIN_N,"mercado "&BR15,IF(CD15>=MIN_N,"modelo+año+km",IF(CC15>=MIN_N,"modelo+año","modelo"))) | CG15: =(CE15-O15)/CE15 | CH15: =IF(COUNTIFS(FR_FUEL,K15,FR_YEAR,AP15)>0,1,0) | CI15: =IF(COUNTIFS(FR_FUEL,K15,FR_YEAR,AP15-1)>0,1,0) | CJ15: =IF(N(AQ15)>0,AP15*100+AQ15,IF(AND(CH15=1,CI15=1),(AP15-1)*100+1,AP15*100+1)) | CK15: =IF(OR(K15="hibrido",K15="glp",K15="gnc",K15="phev"),"ECO",IF(K15="electrico","CERO",IF(K15="gasolina",IF(CJ15>=GAS_C_YM,"C",IF(CJ15>=GAS_B_YM,"B","A")),IF(K15="diesel",IF(CJ15>=DIE_C_YM,"C",IF(CJ15>=DIE_B_YM,"B","A")),"")))) | CL15: =CK15 | CM15: =IF(AU15="sí","sí",IF(AS15="regla",IF(AND(N(AQ15)=0,CH15=1),"sí","no"),"no")) | CN15: =IFERROR(VLOOKUP(F15,MOD_TBL,16,0),IFERROR(VLOOKUP(E15,OCU_TBL,2,0),NEUTRO)) | CO15: =SUMIFS(MOT_AJUSTE,MOT_MOTOR,G15,MOT_MARCA,E15,MOT_DESDE,"<="&M15,MOT_HASTA,">="&M15)+SUMIFS(MOT_AJUSTE,MOT_MOTOR,G15,MOT_MARCA,"(todas)",MOT_DESDE,"<="&M15,MOT_HASTA,">="&M15)+SUMIFS(MOT_AJUSTE,MOT_MOTOR,"(cualquiera)",MOT_MARCA,E15,MOT_DESDE,"<="&M15,MOT_HASTA,">="&M15) | CP15: =SUMIFS(COMB_AJUSTE,COMB_COMB,K15) | CQ15: =COUNTIFS(MOT_MOTOR,G15,MOT_MARCA,E15,MOT_DESDE,"<="&M15,MOT_HASTA,">="&M15)+COUNTIFS(MOT_MOTOR,G15,MOT_MARCA,"(todas)",MOT_DESDE,"<="&M15,MOT_HASTA,">="&M15)+COUNTIFS(MOT_MOTOR,"(cualquiera)",MOT_MARCA,E15,MOT_DESDE,"<="&M15,MOT_HASTA,">="&M15) | CR15: =IF(AND(K15="diesel",CQ15=0),MIN(CN15,NEUTRO),CN15) | CS15: =MAX(0,MIN(100,CR15+CO15+CP15-IF(AX15="sí",ROB_PEN,0))) | CT15: =100-MAX(0,N15-KM_TOPE_DESDE)/1000*KM_TOPE_PTS | CU15: =MAX(0,MIN(100,50+CG15*PRECIO_PEND,CT15)) | CV15: =MAX(0,100*(1-N15/KM_MAX)) | CW15: =IF(BX15<KMA_SOSP,IF(AA15="sí",100,KMA_PEN),IF(BX15<=KMA_IDEAL_MAX,100,MAX(0,100*(KMA_CERO-BX15)/(KMA_CERO-KMA_IDEAL_MAX)))) | CX15: =MAX(0,MIN(100,100*(M15-ANIO_MIN)/(ANIO_ACTUAL-ANIO_MIN))) | CY15: =W_KMT*CV15+W_KMA*CW15+W_EDAD*CX15 | CZ15: =E15&"|"&G15 | DA15: =IFERROR(VLOOKUP(CZ15,DIST_TBL,2,0),"") | DB15: =E_ITV*(V15="sí")+E_LIBRO*(W15="sí")+E_PROP*IF(Y15=1,1,IF(Y15=2,0.5,0))+E_CORREA*IF(OR(DA15="cadena",AND(X15="sí",BH15="sí")),1,IF(X15="sí",0.5,0))+E_FACT*(BI15="sí") | DC15: =MAX(0,MIN(100,IFERROR(VLOOKUP(CL15,ETQ_TBL,2,0),0)-IF(CM15="sí",ETQ_PEN_DUD,IF(AS15="regla",ETQ_PEN_REGLA,0)))) | DD15: =IF(K15<>"gasolina","",IFERROR(VLOOKUP(F15,CONS_MOD_TBL,2,0),IFERROR(VLOOKUP(L15,CONS_SEG_TBL,2,0),""))) | DE15: =IF(DD15="",NEUTRO,MAX(0,MIN(100,100*(CONS_REF_MAX-DD15)/(CONS_REF_MAX-CONS_REF_MIN)))) | DF15: =IFERROR(VLOOKUP(L15,SEGURO_TBL,3,0),"") | DG15: =IF(DF15="",NEUTRO,MAX(0,MIN(100,100*(SEG_REF_MAX-DF15)/(SEG_REF_MAX-SEG_REF_MIN)))) | DH15: =IFERROR(VLOOKUP(E15,MANT_MARCA_TBL,2,0)+0,NEUTRO) | DI15: =IF(DA15="",NEUTRO,IFERROR(VLOOKUP(DA15,DIST_PTS_TBL,2,0)+0,NEUTRO)) | DJ15: =(DH15+DI15)/2 | DK15: =W_CONS*DE15+W_SEG*DG15+W_MANT*DJ15 | DL15: =IF(N(AB15)>0,AB15,IF(AND(R15="profesional",SG_LEGAL_ON=1),GAR_LEGAL,0)) | DM15: =MAX(0,MIN(100,SG_GAR*MIN(1,DL15/SG_GAR_FULL)+SG_AMPL*(AC15="sí")+SG_KMC*(AF15="sí")+SG_REV*(N(AE15)>0)+SG_DEV*MIN(1,N(AG15)/SG_DEV_FULL)+SG_HIST*(W15="sí")-IF(AND(R15="particular",DL15=0),SG_PART_PEN,0))) | DN15: =IF(BK15="",NEUTRO,MAX(0,MIN(100,BK15/5*100))) | DO15: =IF(BL15="sí",100,IF(BL15="no",0,NEUTRO)) | DP15: =SV_W_NCAP*DN15+SV_W_ESP*DO15 | DQ15: =MAX(0,MIN(100,ATR_BASE+ATR_ACAB*(BD15<>"")+IF(BE15="16+",ATR_LL16,IF(BE15="sí",ATR_LL,0))+ATR_FAROS*(BF15="sí")+ATR_TINT*(BG15="sí")-ATR_CHAPA*(BE15="chapa"))) | DR15: =EST_W_MOD*(BB15-1)/4*100+EST_W_ATR*DQ15 | DS15: =IF(BA15="",NEUTRO,IFERROR(VLOOKUP(BA15,COLOR_TBL,2,0)+0,NEUTRO)) | DT15: =MAX(0,MIN(100,100*N(BM15)/RV_N_FULL)) | DU15: =IF(OR(BN15="",N(BO15)<RV_DIAS_MIN),NEUTRO,MAX(0,MIN(100,100*(RV_DIAS_CERO-BN15)/(RV_DIAS_CERO-RV_DIAS_FULL)))) | DV15: =RV_W_LIQ*DT15+RV_W_DIAS*DU15+RV_W_ETQ*DC15 | DW15: =IFERROR(VLOOKUP(L15,CARR_PEN_TBL,2,0),0) | DX15: =W_FIAB*CS15+W_PRECIO*CU15+W_KMEDAD*CY15+W_ESTADO*DB15+W_USO*DK15+W_SEGURIDAD*DM15+W_SEGVIAL*DP15+W_ESTETICA*DR15+W_COLOR*DS15+W_REVENTA*DV15-DW15-EG15 | DY15: =IF(N(I15)>0,I15,IFERROR(ROUND(_xlfn.NUMBERVALUE(LEFT(G15,FIND(" ",G15&" ")-1),".")*1000,0),99999)) | DZ15: =IF(R15="profesional",0,IF(O15<CUOTA_VALOR_MAX,IF(BW15>ITP_TRAMO_ALTO,SUMIFS(CF_CUOTA,CF_MAS,ITP_TRAMO_ALTO,CF_CCMIN,"<="&DY15,CF_CCMAX,">="&DY15),IF(BW15>ITP_TRAMO_BAJO,SUMIFS(CF_CUOTA,CF_MAS,ITP_TRAMO_BAJO,CF_CCMIN,"<="&DY15,CF_CCMAX,">="&DY15),O15*ITP_TIPO)),O15*ITP_TIPO)) | EA15: =IF(R15="profesional",N(AK15),0) | EB15: =IF(AND(R15="profesional",ISNUMBER(AK15),AL15="sí"),0,TASA_DGT) | EC15: =INFORME_DGT | ED15: =O15+EA15+DZ15+EB15+EC15 | EE15: =ED15+N(DF15) | EF15: =MAX(0,ED15-TOTAL_MAX) | EG15: =EF15/100*PEN_100 | EH15: =IF(R15="particular",ED15+IF(AND(DA15<>"cadena",X15<>"sí"),RES_CORREA,0)+IF(AND(BJ15<>"sí",BW15>=RES_NEUM_EDAD),RES_NEUM,0),"") | EI15: =IF(ED15<=TOTAL_MAX,"sí",IF(ED15<=TECHO,"negociar","no")) | EJ15: =ROUND(DX15,9) | EK15: =IF(EI15<>"no",SUMPRODUCT(($EI$2:$EI$209<>"no")*($EJ$2:$EJ$209>EJ15))+SUMPRODUCT(($EI$2:EI15<>"no")*($EJ$2:EJ15=EJ15)),"")
A16: cochesnet:71399209 | B16: cochesnet | C16: https://www.coches.net/renault-megane-emotion-2008-14-16v-5p-gasolina-2008-en-valencia-71399209-covo.aspx | D16: RENAULT Mégane Emotion 2008 1.4 16V | E16: Renault | F16: Renault Mégane | G16: 1.4 | H16: Emotion 2008 1.4 16V | K16: gasolina | L16: compacto | M16: 2008 | N16: 134000 | O16: 4590 | P16: manual | Q16: no | R16: profesional | S16: Only Cars Valencia Aldaia | T16: 2026-08-31T12:15:05Z | U16: 11 | Y16: 1 | Z16: sí | AB16: 12 | AH16: 4590 | AM16: 7.5 | AO16: 2008 | AP16: 2008 | AR16: C | AS16: anuncio | AU16: no | AV16: C | AX16: no | AY16: no | AZ16: COMMON.COLOR_BLUE | BA16: azul | BB16: 3 | BC16: (por segmento) | BK16: 5 | BM16: 387 | BN16: 0.074340278 | BO16: 7 | BP16: 4500 | BQ16: 5 | BR16: modelo+año+km | BT16: vendedor profesional: sin ITP (operación con IVA/REBU, confirmar en factura); gastos de gestión del vendedor no indicados: se suma la tasa DGT; preguntar el precio final; revisar: no menciona la ITV | BU16: Renault Megane 1.4 Emotion año 2008 con 134.000Kms 98CV. ÚNICO PROPIETARIO. Equipamiento: - elevalunas eléctricos - Espejos eléctricos - Aire acondicionado - Dirección asistida - Mando a distancia - Ordenador de abordo - Control de velocidad - Velocidad crucero Mantenimiento: - cambio de filtro de aire - cambio de filtro de aceite - cambio de aceite - Dos juegos de llave - Alfombrillas | BV16: https://www.coches.net/renault-megane-emotion-2008-14-16v-5p-gasolina-2008-en-valencia-71399209-covo.aspx (window.__INITIAL_PROPS__.ad) /home/user/Alopecia/buscador-coches/raw/cochesnet/893afa53c262edfe.json | BW16: =MAX(ANIO_ACTUAL-M16,0) | BX16: =N16/MAX(BW16,0.5) | BY16: =F16 | BZ16: =BY16&"|"&INT(M16/SEG_ANIO)*SEG_ANIO | CA16: =BZ16&"|"&INT(N16/SEG_KM)*SEG_KM | CB16: =COUNTIF($BY$2:$BY$209,BY16) | CC16: =COUNTIF($BZ$2:$BZ$209,BZ16) | CD16: =COUNTIF($CA$2:$CA$209,CA16) | CE16: {=IF(N(BQ16)>=MIN_N,BP16,IF(CD16>=MIN_N,MEDIAN(IF($CA$2:$CA$209=CA16,$O$2:$O$209)),IF(CC16>=MIN_N,MEDIAN(IF($BZ$2:$BZ$209=BZ16,$O$2:$O$209)),MEDIAN(IF($BY$2:$BY$209=BY16,$O$2:$O$209)))))} | CF16: =IF(N(BQ16)>=MIN_N,"mercado "&BR16,IF(CD16>=MIN_N,"modelo+año+km",IF(CC16>=MIN_N,"modelo+año","modelo"))) | CG16: =(CE16-O16)/CE16 | CH16: =IF(COUNTIFS(FR_FUEL,K16,FR_YEAR,AP16)>0,1,0) | CI16: =IF(COUNTIFS(FR_FUEL,K16,FR_YEAR,AP16-1)>0,1,0) | CJ16: =IF(N(AQ16)>0,AP16*100+AQ16,IF(AND(CH16=1,CI16=1),(AP16-1)*100+1,AP16*100+1)) | CK16: =IF(OR(K16="hibrido",K16="glp",K16="gnc",K16="phev"),"ECO",IF(K16="electrico","CERO",IF(K16="gasolina",IF(CJ16>=GAS_C_YM,"C",IF(CJ16>=GAS_B_YM,"B","A")),IF(K16="diesel",IF(CJ16>=DIE_C_YM,"C",IF(CJ16>=DIE_B_YM,"B","A")),"")))) | CL16: C | CM16: =IF(AU16="sí","sí",IF(AS16="regla",IF(AND(N(AQ16)=0,CH16=1),"sí","no"),"no")) | CN16: =IFERROR(VLOOKUP(F16,MOD_TBL,16,0),IFERROR(VLOOKUP(E16,OCU_TBL,2,0),NEUTRO)) | CO16: =SUMIFS(MOT_AJUSTE,MOT_MOTOR,G16,MOT_MARCA,E16,MOT_DESDE,"<="&M16,MOT_HASTA,">="&M16)+SUMIFS(MOT_AJUSTE,MOT_MOTOR,G16,MOT_MARCA,"(todas)",MOT_DESDE,"<="&M16,MOT_HASTA,">="&M16)+SUMIFS(MOT_AJUSTE,MOT_MOTOR,"(cualquiera)",MOT_MARCA,E16,MOT_DESDE,"<="&M16,MOT_HASTA,">="&M16) | CP16: =SUMIFS(COMB_AJUSTE,COMB_COMB,K16) | CQ16: =COUNTIFS(MOT_MOTOR,G16,MOT_MARCA,E16,MOT_DESDE,"<="&M16,MOT_HASTA,">="&M16)+COUNTIFS(MOT_MOTOR,G16,MOT_MARCA,"(todas)",MOT_DESDE,"<="&M16,MOT_HASTA,">="&M16)+COUNTIFS(MOT_MOTOR,"(cualquiera)",MOT_MARCA,E16,MOT_DESDE,"<="&M16,MOT_HASTA,">="&M16) | CR16: =IF(AND(K16="diesel",CQ16=0),MIN(CN16,NEUTRO),CN16) | CS16: =MAX(0,MIN(100,CR16+CO16+CP16-IF(AX16="sí",ROB_PEN,0))) | CT16: =100-MAX(0,N16-KM_TOPE_DESDE)/1000*KM_TOPE_PTS | CU16: =MAX(0,MIN(100,50+CG16*PRECIO_PEND,CT16)) | CV16: =MAX(0,100*(1-N16/KM_MAX)) | CW16: =IF(BX16<KMA_SOSP,IF(AA16="sí",100,KMA_PEN),IF(BX16<=KMA_IDEAL_MAX,100,MAX(0,100*(KMA_CERO-BX16)/(KMA_CERO-KMA_IDEAL_MAX)))) | CX16: =MAX(0,MIN(100,100*(M16-ANIO_MIN)/(ANIO_ACTUAL-ANIO_MIN))) | CY16: =W_KMT*CV16+W_KMA*CW16+W_EDAD*CX16 | CZ16: =E16&"|"&G16 | DA16: =IFERROR(VLOOKUP(CZ16,DIST_TBL,2,0),"") | DB16: =E_ITV*(V16="sí")+E_LIBRO*(W16="sí")+E_PROP*IF(Y16=1,1,IF(Y16=2,0.5,0))+E_CORREA*IF(OR(DA16="cadena",AND(X16="sí",BH16="sí")),1,IF(X16="sí",0.5,0))+E_FACT*(BI16="sí") | DC16: =MAX(0,MIN(100,IFERROR(VLOOKUP(CL16,ETQ_TBL,2,0),0)-IF(CM16="sí",ETQ_PEN_DUD,IF(AS16="regla",ETQ_PEN_REGLA,0)))) | DD16: =IF(K16<>"gasolina","",IFERROR(VLOOKUP(F16,CONS_MOD_TBL,2,0),IFERROR(VLOOKUP(L16,CONS_SEG_TBL,2,0),""))) | DE16: =IF(DD16="",NEUTRO,MAX(0,MIN(100,100*(CONS_REF_MAX-DD16)/(CONS_REF_MAX-CONS_REF_MIN)))) | DF16: =IFERROR(VLOOKUP(L16,SEGURO_TBL,3,0),"") | DG16: =IF(DF16="",NEUTRO,MAX(0,MIN(100,100*(SEG_REF_MAX-DF16)/(SEG_REF_MAX-SEG_REF_MIN)))) | DH16: =IFERROR(VLOOKUP(E16,MANT_MARCA_TBL,2,0)+0,NEUTRO) | DI16: =IF(DA16="",NEUTRO,IFERROR(VLOOKUP(DA16,DIST_PTS_TBL,2,0)+0,NEUTRO)) | DJ16: =(DH16+DI16)/2 | DK16: =W_CONS*DE16+W_SEG*DG16+W_MANT*DJ16 | DL16: =IF(N(AB16)>0,AB16,IF(AND(R16="profesional",SG_LEGAL_ON=1),GAR_LEGAL,0)) | DM16: =MAX(0,MIN(100,SG_GAR*MIN(1,DL16/SG_GAR_FULL)+SG_AMPL*(AC16="sí")+SG_KMC*(AF16="sí")+SG_REV*(N(AE16)>0)+SG_DEV*MIN(1,N(AG16)/SG_DEV_FULL)+SG_HIST*(W16="sí")-IF(AND(R16="particular",DL16=0),SG_PART_PEN,0))) | DN16: =IF(BK16="",NEUTRO,MAX(0,MIN(100,BK16/5*100))) | DO16: =IF(BL16="sí",100,IF(BL16="no",0,NEUTRO)) | DP16: =SV_W_NCAP*DN16+SV_W_ESP*DO16 | DQ16: =MAX(0,MIN(100,ATR_BASE+ATR_ACAB*(BD16<>"")+IF(BE16="16+",ATR_LL16,IF(BE16="sí",ATR_LL,0))+ATR_FAROS*(BF16="sí")+ATR_TINT*(BG16="sí")-ATR_CHAPA*(BE16="chapa"))) | DR16: =EST_W_MOD*(BB16-1)/4*100+EST_W_ATR*DQ16 | DS16: =IF(BA16="",NEUTRO,IFERROR(VLOOKUP(BA16,COLOR_TBL,2,0)+0,NEUTRO)) | DT16: =MAX(0,MIN(100,100*N(BM16)/RV_N_FULL)) | DU16: =IF(OR(BN16="",N(BO16)<RV_DIAS_MIN),NEUTRO,MAX(0,MIN(100,100*(RV_DIAS_CERO-BN16)/(RV_DIAS_CERO-RV_DIAS_FULL)))) | DV16: =RV_W_LIQ*DT16+RV_W_DIAS*DU16+RV_W_ETQ*DC16 | DW16: =IFERROR(VLOOKUP(L16,CARR_PEN_TBL,2,0),0) | DX16: =W_FIAB*CS16+W_PRECIO*CU16+W_KMEDAD*CY16+W_ESTADO*DB16+W_USO*DK16+W_SEGURIDAD*DM16+W_SEGVIAL*DP16+W_ESTETICA*DR16+W_COLOR*DS16+W_REVENTA*DV16-DW16-EG16 | DY16: =IF(N(I16)>0,I16,IFERROR(ROUND(_xlfn.NUMBERVALUE(LEFT(G16,FIND(" ",G16&" ")-1),".")*1000,0),99999)) | DZ16: =IF(R16="profesional",0,IF(O16<CUOTA_VALOR_MAX,IF(BW16>ITP_TRAMO_ALTO,SUMIFS(CF_CUOTA,CF_MAS,ITP_TRAMO_ALTO,CF_CCMIN,"<="&DY16,CF_CCMAX,">="&DY16),IF(BW16>ITP_TRAMO_BAJO,SUMIFS(CF_CUOTA,CF_MAS,ITP_TRAMO_BAJO,CF_CCMIN,"<="&DY16,CF_CCMAX,">="&DY16),O16*ITP_TIPO)),O16*ITP_TIPO)) | EA16: =IF(R16="profesional",N(AK16),0) | EB16: =IF(AND(R16="profesional",ISNUMBER(AK16),AL16="sí"),0,TASA_DGT) | EC16: =INFORME_DGT | ED16: =O16+EA16+DZ16+EB16+EC16 | EE16: =ED16+N(DF16) | EF16: =MAX(0,ED16-TOTAL_MAX) | EG16: =EF16/100*PEN_100 | EH16: =IF(R16="particular",ED16+IF(AND(DA16<>"cadena",X16<>"sí"),RES_CORREA,0)+IF(AND(BJ16<>"sí",BW16>=RES_NEUM_EDAD),RES_NEUM,0),"") | EI16: =IF(ED16<=TOTAL_MAX,"sí",IF(ED16<=TECHO,"negociar","no")) | EJ16: =ROUND(DX16,9) | EK16: =IF(EI16<>"no",SUMPRODUCT(($EI$2:$EI$209<>"no")*($EJ$2:$EJ$209>EJ16))+SUMPRODUCT(($EI$2:EI16<>"no")*($EJ$2:EJ16=EJ16)),"")
A17: cochesnet:71622320 | B17: cochesnet | C17: https://www.coches.net/renault-megane-dynamique-15dci85-eco2-5p-diesel-2008-en-valencia-71622320-covo.aspx | D17: RENAULT Mégane Dynamique 1.5dCi85 eco2 | E17: Renault | F17: Renault Mégane | G17: 1.5 | H17: Dynamique 1.5dCi85 eco2 | K17: diesel | L17: compacto | M17: 2008 | N17: 145000 | O17: 3990 | P17: manual | Q17: no | R17: profesional | S17: Only Cars Valencia Aldaia | T17: 2026-09-29T10:48:11Z | U17: 11 | Y17: 1 | Z17: sí | AB17: 12 | AH17: 3990 | AM17: 7.5 | AO17: 2008 | AP17: 2008 | AR17: B | AS17: anuncio | AU17: no | AV17: B | AX17: no | AY17: no | AZ17: COMMON.COLOR_BEIGE | BA17: beige | BB17: 3 | BC17: (por segmento) | BK17: 5 | BM17: 387 | BN17: 0.074340278 | BO17: 7 | BP17: 4500 | BQ17: 5 | BR17: modelo+año+km | BT17: vendedor profesional: sin ITP (operación con IVA/REBU, confirmar en factura); gastos de gestión del vendedor no indicados: se suma la tasa DGT; preguntar el precio final; diésel: motor sin fuente de fiabilidad (fiabilidad limitada a neutra); revisar: no menciona la ITV | BU17: Renault Megane 1.5 dCi Dynamique año 2008 con 145.000Kms 85CV. UNICO PROPIETARIO. Equipamiento: - elevalunas eléctricos - Espejos eléctricos - Aire acondicionado - Dirección asistida - Mando a distancia - Ordenador de abordo - Control de velocidad - Velocidad crucero Mantenimiento: - cambio de filtro de aire - cambio de filtro de aceite - cambio de aceite - Dos juegos de llave - Alfombrillas | BV17: https://www.coches.net/renault-megane-dynamique-15dci85-eco2-5p-diesel-2008-en-valencia-71622320-covo.aspx (window.__INITIAL_PROPS__.ad) /home/user/Alopecia/buscador-coches/raw/cochesnet/b27e6845a5e23e51.json | BW17: =MAX(ANIO_ACTUAL-M17,0) | BX17: =N17/MAX(BW17,0.5) | BY17: =F17 | BZ17: =BY17&"|"&INT(M17/SEG_ANIO)*SEG_ANIO | CA17: =BZ17&"|"&INT(N17/SEG_KM)*SEG_KM | CB17: =COUNTIF($BY$2:$BY$209,BY17) | CC17: =COUNTIF($BZ$2:$BZ$209,BZ17) | CD17: =COUNTIF($CA$2:$CA$209,CA17) | CE17: {=IF(N(BQ17)>=MIN_N,BP17,IF(CD17>=MIN_N,MEDIAN(IF($CA$2:$CA$209=CA17,$O$2:$O$209)),IF(CC17>=MIN_N,MEDIAN(IF($BZ$2:$BZ$209=BZ17,$O$2:$O$209)),MEDIAN(IF($BY$2:$BY$209=BY17,$O$2:$O$209)))))} | CF17: =IF(N(BQ17)>=MIN_N,"mercado "&BR17,IF(CD17>=MIN_N,"modelo+año+km",IF(CC17>=MIN_N,"modelo+año","modelo"))) | CG17: =(CE17-O17)/CE17 | CH17: =IF(COUNTIFS(FR_FUEL,K17,FR_YEAR,AP17)>0,1,0) | CI17: =IF(COUNTIFS(FR_FUEL,K17,FR_YEAR,AP17-1)>0,1,0) | CJ17: =IF(N(AQ17)>0,AP17*100+AQ17,IF(AND(CH17=1,CI17=1),(AP17-1)*100+1,AP17*100+1)) | CK17: =IF(OR(K17="hibrido",K17="glp",K17="gnc",K17="phev"),"ECO",IF(K17="electrico","CERO",IF(K17="gasolina",IF(CJ17>=GAS_C_YM,"C",IF(CJ17>=GAS_B_YM,"B","A")),IF(K17="diesel",IF(CJ17>=DIE_C_YM,"C",IF(CJ17>=DIE_B_YM,"B","A")),"")))) | CL17: B | CM17: =IF(AU17="sí","sí",IF(AS17="regla",IF(AND(N(AQ17)=0,CH17=1),"sí","no"),"no")) | CN17: =IFERROR(VLOOKUP(F17,MOD_TBL,16,0),IFERROR(VLOOKUP(E17,OCU_TBL,2,0),NEUTRO)) | CO17: =SUMIFS(MOT_AJUSTE,MOT_MOTOR,G17,MOT_MARCA,E17,MOT_DESDE,"<="&M17,MOT_HASTA,">="&M17)+SUMIFS(MOT_AJUSTE,MOT_MOTOR,G17,MOT_MARCA,"(todas)",MOT_DESDE,"<="&M17,MOT_HASTA,">="&M17)+SUMIFS(MOT_AJUSTE,MOT_MOTOR,"(cualquiera)",MOT_MARCA,E17,MOT_DESDE,"<="&M17,MOT_HASTA,">="&M17) | CP17: =SUMIFS(COMB_AJUSTE,COMB_COMB,K17) | CQ17: =COUNTIFS(MOT_MOTOR,G17,MOT_MARCA,E17,MOT_DESDE,"<="&M17,MOT_HASTA,">="&M17)+COUNTIFS(MOT_MOTOR,G17,MOT_MARCA,"(todas)",MOT_DESDE,"<="&M17,MOT_HASTA,">="&M17)+COUNTIFS(MOT_MOTOR,"(cualquiera)",MOT_MARCA,E17,MOT_DESDE,"<="&M17,MOT_HASTA,">="&M17) | CR17: =IF(AND(K17="diesel",CQ17=0),MIN(CN17,NEUTRO),CN17) | CS17: =MAX(0,MIN(100,CR17+CO17+CP17-IF(AX17="sí",ROB_PEN,0))) | CT17: =100-MAX(0,N17-KM_TOPE_DESDE)/1000*KM_TOPE_PTS | CU17: =MAX(0,MIN(100,50+CG17*PRECIO_PEND,CT17)) | CV17: =MAX(0,100*(1-N17/KM_MAX)) | CW17: =IF(BX17<KMA_SOSP,IF(AA17="sí",100,KMA_PEN),IF(BX17<=KMA_IDEAL_MAX,100,MAX(0,100*(KMA_CERO-BX17)/(KMA_CERO-KMA_IDEAL_MAX)))) | CX17: =MAX(0,MIN(100,100*(M17-ANIO_MIN)/(ANIO_ACTUAL-ANIO_MIN))) | CY17: =W_KMT*CV17+W_KMA*CW17+W_EDAD*CX17 | CZ17: =E17&"|"&G17 | DA17: =IFERROR(VLOOKUP(CZ17,DIST_TBL,2,0),"") | DB17: =E_ITV*(V17="sí")+E_LIBRO*(W17="sí")+E_PROP*IF(Y17=1,1,IF(Y17=2,0.5,0))+E_CORREA*IF(OR(DA17="cadena",AND(X17="sí",BH17="sí")),1,IF(X17="sí",0.5,0))+E_FACT*(BI17="sí") | DC17: =MAX(0,MIN(100,IFERROR(VLOOKUP(CL17,ETQ_TBL,2,0),0)-IF(CM17="sí",ETQ_PEN_DUD,IF(AS17="regla",ETQ_PEN_REGLA,0)))) | DD17: =IF(K17<>"gasolina","",IFERROR(VLOOKUP(F17,CONS_MOD_TBL,2,0),IFERROR(VLOOKUP(L17,CONS_SEG_TBL,2,0),""))) | DE17: =IF(DD17="",NEUTRO,MAX(0,MIN(100,100*(CONS_REF_MAX-DD17)/(CONS_REF_MAX-CONS_REF_MIN)))) | DF17: =IFERROR(VLOOKUP(L17,SEGURO_TBL,3,0),"") | DG17: =IF(DF17="",NEUTRO,MAX(0,MIN(100,100*(SEG_REF_MAX-DF17)/(SEG_REF_MAX-SEG_REF_MIN)))) | DH17: =IFERROR(VLOOKUP(E17,MANT_MARCA_TBL,2,0)+0,NEUTRO) | DI17: =IF(DA17="",NEUTRO,IFERROR(VLOOKUP(DA17,DIST_PTS_TBL,2,0)+0,NEUTRO)) | DJ17: =(DH17+DI17)/2 | DK17: =W_CONS*DE17+W_SEG*DG17+W_MANT*DJ17 | DL17: =IF(N(AB17)>0,AB17,IF(AND(R17="profesional",SG_LEGAL_ON=1),GAR_LEGAL,0)) | DM17: =MAX(0,MIN(100,SG_GAR*MIN(1,DL17/SG_GAR_FULL)+SG_AMPL*(AC17="sí")+SG_KMC*(AF17="sí")+SG_REV*(N(AE17)>0)+SG_DEV*MIN(1,N(AG17)/SG_DEV_FULL)+SG_HIST*(W17="sí")-IF(AND(R17="particular",DL17=0),SG_PART_PEN,0))) | DN17: =IF(BK17="",NEUTRO,MAX(0,MIN(100,BK17/5*100))) | DO17: =IF(BL17="sí",100,IF(BL17="no",0,NEUTRO)) | DP17: =SV_W_NCAP*DN17+SV_W_ESP*DO17 | DQ17: =MAX(0,MIN(100,ATR_BASE+ATR_ACAB*(BD17<>"")+IF(BE17="16+",ATR_LL16,IF(BE17="sí",ATR_LL,0))+ATR_FAROS*(BF17="sí")+ATR_TINT*(BG17="sí")-ATR_CHAPA*(BE17="chapa"))) | DR17: =EST_W_MOD*(BB17-1)/4*100+EST_W_ATR*DQ17 | DS17: =IF(BA17="",NEUTRO,IFERROR(VLOOKUP(BA17,COLOR_TBL,2,0)+0,NEUTRO)) | DT17: =MAX(0,MIN(100,100*N(BM17)/RV_N_FULL)) | DU17: =IF(OR(BN17="",N(BO17)<RV_DIAS_MIN),NEUTRO,MAX(0,MIN(100,100*(RV_DIAS_CERO-BN17)/(RV_DIAS_CERO-RV_DIAS_FULL)))) | DV17: =RV_W_LIQ*DT17+RV_W_DIAS*DU17+RV_W_ETQ*DC17 | DW17: =IFERROR(VLOOKUP(L17,CARR_PEN_TBL,2,0),0) | DX17: =W_FIAB*CS17+W_PRECIO*CU17+W_KMEDAD*CY17+W_ESTADO*DB17+W_USO*DK17+W_SEGURIDAD*DM17+W_SEGVIAL*DP17+W_ESTETICA*DR17+W_COLOR*DS17+W_REVENTA*DV17-DW17-EG17 | DY17: =IF(N(I17)>0,I17,IFERROR(ROUND(_xlfn.NUMBERVALUE(LEFT(G17,FIND(" ",G17&" ")-1),".")*1000,0),99999)) | DZ17: =IF(R17="profesional",0,IF(O17<CUOTA_VALOR_MAX,IF(BW17>ITP_TRAMO_ALTO,SUMIFS(CF_CUOTA,CF_MAS,ITP_TRAMO_ALTO,CF_CCMIN,"<="&DY17,CF_CCMAX,">="&DY17),IF(BW17>ITP_TRAMO_BAJO,SUMIFS(CF_CUOTA,CF_MAS,ITP_TRAMO_BAJO,CF_CCMIN,"<="&DY17,CF_CCMAX,">="&DY17),O17*ITP_TIPO)),O17*ITP_TIPO)) | EA17: =IF(R17="profesional",N(AK17),0) | EB17: =IF(AND(R17="profesional",ISNUMBER(AK17),AL17="sí"),0,TASA_DGT) | EC17: =INFORME_DGT | ED17: =O17+EA17+DZ17+EB17+EC17 | EE17: =ED17+N(DF17) | EF17: =MAX(0,ED17-TOTAL_MAX) | EG17: =EF17/100*PEN_100 | EH17: =IF(R17="particular",ED17+IF(AND(DA17<>"cadena",X17<>"sí"),RES_CORREA,0)+IF(AND(BJ17<>"sí",BW17>=RES_NEUM_EDAD),RES_NEUM,0),"") | EI17: =IF(ED17<=TOTAL_MAX,"sí",IF(ED17<=TECHO,"negociar","no")) | EJ17: =ROUND(DX17,9) | EK17: =IF(EI17<>"no",SUMPRODUCT(($EI$2:$EI$209<>"no")*($EJ$2:$EJ$209>EJ17))+SUMPRODUCT(($EI$2:EI17<>"no")*($EJ$2:EJ17=EJ17)),"")
A18: cochesnet:71224992 | B18: cochesnet | C18: https://www.coches.net/renault-megane-dynamique-16-16v-110-e5-5p-gasolina-2010-en-valencia-71224992-covo.aspx | D18: RENAULT Mégane Dynamique 1.6 16v 110 E5 | E18: Renault | F18: Renault Mégane | G18: 1.6 | H18: Dynamique 1.6 16v 110 E5 | K18: gasolina | L18: compacto | M18: 2011 | N18: 170000 | O18: 4490 | P18: manual | Q18: no | R18: profesional | S18: Cullera | T18: 2026-08-04T11:55:07Z | U18: 16 | Z18: sí | AB18: 12 | AH18: 4490 | AM18: 35.4 | AO18: 2011 | AP18: 2011 | AR18: C | AS18: anuncio | AT18: 2010 | AU18: no | AV18: C | AX18: no | AY18: no | AZ18: COMMON.COLOR_WHITE | BA18: blanco | BB18: 3 | BC18: (por segmento) | BM18: 387 | BN18: 0.074340278 | BO18: 7 | BP18: 5295 | BQ18: 14 | BR18: modelo+año+km | BT18: año a confirmar: la URL/título dice 2010; vendedor profesional: sin ITP (operación con IVA/REBU, confirmar en factura); gastos de gestión del vendedor no indicados: se suma la tasa DGT; preguntar el precio final; Euro NCAP de la generación PENDIENTE (seguridad neutra); revisar: no menciona la ITV | BU18: ?VEHÍCULO NACIONAL, 170.000KMS CERTIFICADOS, LIBRE DE ACCIDENTES ESTRUCTURALES ?1 AÑO DE GARANTÍA INCLUIDO EN EL PRECIO, POSIBILIDAD DE AMPLIAR A 2 AÑOS -ENVÍO A TODA ESPAÑA DESDE 150€, POSIBILIDAD DE COMPRA ONLINE O EN NUESTRA TIENDA EN CORBERA, VALENCIA -ETIQUETA MEDIOAMBIENTAL C VERDE -MOTOR MUY FIABLE Y DE BAJO CONSUMO AIRE ACONDICIONADO, ELEVALUNAS ELECTRICOS, DIRECCIÓN ASISITIDA ETC | BV18: https://www.coches.net/renault-megane-dynamique-16-16v-110-e5-5p-gasolina-2010-en-valencia-71224992-covo.aspx (window.__INITIAL_PROPS__.ad) /home/user/Alopecia/buscador-coches/raw/cochesnet/b60848ab8e8cf1e1.json | BW18: =MAX(ANIO_ACTUAL-M18,0) | BX18: =N18/MAX(BW18,0.5) | BY18: =F18 | BZ18: =BY18&"|"&INT(M18/SEG_ANIO)*SEG_ANIO | CA18: =BZ18&"|"&INT(N18/SEG_KM)*SEG_KM | CB18: =COUNTIF($BY$2:$BY$209,BY18) | CC18: =COUNTIF($BZ$2:$BZ$209,BZ18) | CD18: =COUNTIF($CA$2:$CA$209,CA18) | CE18: {=IF(N(BQ18)>=MIN_N,BP18,IF(CD18>=MIN_N,MEDIAN(IF($CA$2:$CA$209=CA18,$O$2:$O$209)),IF(CC18>=MIN_N,MEDIAN(IF($BZ$2:$BZ$209=BZ18,$O$2:$O$209)),MEDIAN(IF($BY$2:$BY$209=BY18,$O$2:$O$209)))))} | CF18: =IF(N(BQ18)>=MIN_N,"mercado "&BR18,IF(CD18>=MIN_N,"modelo+año+km",IF(CC18>=MIN_N,"modelo+año","modelo"))) | CG18: =(CE18-O18)/CE18 | CH18: =IF(COUNTIFS(FR_FUEL,K18,FR_YEAR,AP18)>0,1,0) | CI18: =IF(COUNTIFS(FR_FUEL,K18,FR_YEAR,AP18-1)>0,1,0) | CJ18: =IF(N(AQ18)>0,AP18*100+AQ18,IF(AND(CH18=1,CI18=1),(AP18-1)*100+1,AP18*100+1)) | CK18: =IF(OR(K18="hibrido",K18="glp",K18="gnc",K18="phev"),"ECO",IF(K18="electrico","CERO",IF(K18="gasolina",IF(CJ18>=GAS_C_YM,"C",IF(CJ18>=GAS_B_YM,"B","A")),IF(K18="diesel",IF(CJ18>=DIE_C_YM,"C",IF(CJ18>=DIE_B_YM,"B","A")),"")))) | CL18: C | CM18: =IF(AU18="sí","sí",IF(AS18="regla",IF(AND(N(AQ18)=0,CH18=1),"sí","no"),"no")) | CN18: =IFERROR(VLOOKUP(F18,MOD_TBL,16,0),IFERROR(VLOOKUP(E18,OCU_TBL,2,0),NEUTRO)) | CO18: =SUMIFS(MOT_AJUSTE,MOT_MOTOR,G18,MOT_MARCA,E18,MOT_DESDE,"<="&M18,MOT_HASTA,">="&M18)+SUMIFS(MOT_AJUSTE,MOT_MOTOR,G18,MOT_MARCA,"(todas)",MOT_DESDE,"<="&M18,MOT_HASTA,">="&M18)+SUMIFS(MOT_AJUSTE,MOT_MOTOR,"(cualquiera)",MOT_MARCA,E18,MOT_DESDE,"<="&M18,MOT_HASTA,">="&M18) | CP18: =SUMIFS(COMB_AJUSTE,COMB_COMB,K18) | CQ18: =COUNTIFS(MOT_MOTOR,G18,MOT_MARCA,E18,MOT_DESDE,"<="&M18,MOT_HASTA,">="&M18)+COUNTIFS(MOT_MOTOR,G18,MOT_MARCA,"(todas)",MOT_DESDE,"<="&M18,MOT_HASTA,">="&M18)+COUNTIFS(MOT_MOTOR,"(cualquiera)",MOT_MARCA,E18,MOT_DESDE,"<="&M18,MOT_HASTA,">="&M18) | CR18: =IF(AND(K18="diesel",CQ18=0),MIN(CN18,NEUTRO),CN18) | CS18: =MAX(0,MIN(100,CR18+CO18+CP18-IF(AX18="sí",ROB_PEN,0))) | CT18: =100-MAX(0,N18-KM_TOPE_DESDE)/1000*KM_TOPE_PTS | CU18: =MAX(0,MIN(100,50+CG18*PRECIO_PEND,CT18)) | CV18: =MAX(0,100*(1-N18/KM_MAX)) | CW18: =IF(BX18<KMA_SOSP,IF(AA18="sí",100,KMA_PEN),IF(BX18<=KMA_IDEAL_MAX,100,MAX(0,100*(KMA_CERO-BX18)/(KMA_CERO-KMA_IDEAL_MAX)))) | CX18: =MAX(0,MIN(100,100*(M18-ANIO_MIN)/(ANIO_ACTUAL-ANIO_MIN))) | CY18: =W_KMT*CV18+W_KMA*CW18+W_EDAD*CX18 | CZ18: =E18&"|"&G18 | DA18: =IFERROR(VLOOKUP(CZ18,DIST_TBL,2,0),"") | DB18: =E_ITV*(V18="sí")+E_LIBRO*(W18="sí")+E_PROP*IF(Y18=1,1,IF(Y18=2,0.5,0))+E_CORREA*IF(OR(DA18="cadena",AND(X18="sí",BH18="sí")),1,IF(X18="sí",0.5,0))+E_FACT*(BI18="sí") | DC18: =MAX(0,MIN(100,IFERROR(VLOOKUP(CL18,ETQ_TBL,2,0),0)-IF(CM18="sí",ETQ_PEN_DUD,IF(AS18="regla",ETQ_PEN_REGLA,0)))) | DD18: =IF(K18<>"gasolina","",IFERROR(VLOOKUP(F18,CONS_MOD_TBL,2,0),IFERROR(VLOOKUP(L18,CONS_SEG_TBL,2,0),""))) | DE18: =IF(DD18="",NEUTRO,MAX(0,MIN(100,100*(CONS_REF_MAX-DD18)/(CONS_REF_MAX-CONS_REF_MIN)))) | DF18: =IFERROR(VLOOKUP(L18,SEGURO_TBL,3,0),"") | DG18: =IF(DF18="",NEUTRO,MAX(0,MIN(100,100*(SEG_REF_MAX-DF18)/(SEG_REF_MAX-SEG_REF_MIN)))) | DH18: =IFERROR(VLOOKUP(E18,MANT_MARCA_TBL,2,0)+0,NEUTRO) | DI18: =IF(DA18="",NEUTRO,IFERROR(VLOOKUP(DA18,DIST_PTS_TBL,2,0)+0,NEUTRO)) | DJ18: =(DH18+DI18)/2 | DK18: =W_CONS*DE18+W_SEG*DG18+W_MANT*DJ18 | DL18: =IF(N(AB18)>0,AB18,IF(AND(R18="profesional",SG_LEGAL_ON=1),GAR_LEGAL,0)) | DM18: =MAX(0,MIN(100,SG_GAR*MIN(1,DL18/SG_GAR_FULL)+SG_AMPL*(AC18="sí")+SG_KMC*(AF18="sí")+SG_REV*(N(AE18)>0)+SG_DEV*MIN(1,N(AG18)/SG_DEV_FULL)+SG_HIST*(W18="sí")-IF(AND(R18="particular",DL18=0),SG_PART_PEN,0))) | DN18: =IF(BK18="",NEUTRO,MAX(0,MIN(100,BK18/5*100))) | DO18: =IF(BL18="sí",100,IF(BL18="no",0,NEUTRO)) | DP18: =SV_W_NCAP*DN18+SV_W_ESP*DO18 | DQ18: =MAX(0,MIN(100,ATR_BASE+ATR_ACAB*(BD18<>"")+IF(BE18="16+",ATR_LL16,IF(BE18="sí",ATR_LL,0))+ATR_FAROS*(BF18="sí")+ATR_TINT*(BG18="sí")-ATR_CHAPA*(BE18="chapa"))) | DR18: =EST_W_MOD*(BB18-1)/4*100+EST_W_ATR*DQ18 | DS18: =IF(BA18="",NEUTRO,IFERROR(VLOOKUP(BA18,COLOR_TBL,2,0)+0,NEUTRO)) | DT18: =MAX(0,MIN(100,100*N(BM18)/RV_N_FULL)) | DU18: =IF(OR(BN18="",N(BO18)<RV_DIAS_MIN),NEUTRO,MAX(0,MIN(100,100*(RV_DIAS_CERO-BN18)/(RV_DIAS_CERO-RV_DIAS_FULL)))) | DV18: =RV_W_LIQ*DT18+RV_W_DIAS*DU18+RV_W_ETQ*DC18 | DW18: =IFERROR(VLOOKUP(L18,CARR_PEN_TBL,2,0),0) | DX18: =W_FIAB*CS18+W_PRECIO*CU18+W_KMEDAD*CY18+W_ESTADO*DB18+W_USO*DK18+W_SEGURIDAD*DM18+W_SEGVIAL*DP18+W_ESTETICA*DR18+W_COLOR*DS18+W_REVENTA*DV18-DW18-EG18 | DY18: =IF(N(I18)>0,I18,IFERROR(ROUND(_xlfn.NUMBERVALUE(LEFT(G18,FIND(" ",G18&" ")-1),".")*1000,0),99999)) | DZ18: =IF(R18="profesional",0,IF(O18<CUOTA_VALOR_MAX,IF(BW18>ITP_TRAMO_ALTO,SUMIFS(CF_CUOTA,CF_MAS,ITP_TRAMO_ALTO,CF_CCMIN,"<="&DY18,CF_CCMAX,">="&DY18),IF(BW18>ITP_TRAMO_BAJO,SUMIFS(CF_CUOTA,CF_MAS,ITP_TRAMO_BAJO,CF_CCMIN,"<="&DY18,CF_CCMAX,">="&DY18),O18*ITP_TIPO)),O18*ITP_TIPO)) | EA18: =IF(R18="profesional",N(AK18),0) | EB18: =IF(AND(R18="profesional",ISNUMBER(AK18),AL18="sí"),0,TASA_DGT) | EC18: =INFORME_DGT | ED18: =O18+EA18+DZ18+EB18+EC18 | EE18: =ED18+N(DF18) | EF18: =MAX(0,ED18-TOTAL_MAX) | EG18: =EF18/100*PEN_100 | EH18: =IF(R18="particular",ED18+IF(AND(DA18<>"cadena",X18<>"sí"),RES_CORREA,0)+IF(AND(BJ18<>"sí",BW18>=RES_NEUM_EDAD),RES_NEUM,0),"") | EI18: =IF(ED18<=TOTAL_MAX,"sí",IF(ED18<=TECHO,"negociar","no")) | EJ18: =ROUND(DX18,9) | EK18: =IF(EI18<>"no",SUMPRODUCT(($EI$2:$EI$209<>"no")*($EJ$2:$EJ$209>EJ18))+SUMPRODUCT(($EI$2:EI18<>"no")*($EJ$2:EJ18=EJ18)),"")
A19: cochesnet:70507667 | B19: cochesnet | C19: https://www.coches.net/dacia-sandero-ambiance-12-75cv-5p-gasolina-2012-en-valencia-70507667-covo.aspx | D19: DACIA Sandero Ambiance 1.2 | E19: Dacia | F19: Dacia Sandero | G19: 1.2 | H19: Ambiance 1.2 75cv | J19: 75 | K19: gasolina | L19: utilitario | M19: 2013 | N19: 175000 | O19: 3490 | P19: manual | Q19: no | R19: profesional | S19: AutoEco Valencia | T19: 2026-10-23T09:34:08Z | U19: 14 | W19: sí | Z19: sí | AB19: 12 | AH19: 3490 | AI19: 3490 | AM19: 0.1 | AO19: 2013 | AP19: 2013 | AR19: C | AS19: anuncio | AT19: 2012 | AU19: no | AV19: C | AX19: no | AY19: no | AZ19: COMMON.COLOR_BLUE | BA19: azul | BB19: 2 | BC19: (por segmento) | BM19: 211 | BN19: 0.021909722 | BO19: 4 | BP19: 5300 | BQ19: 4 | BR19: modelo+año+km | BT19: año a confirmar: la URL/título dice 2012; vendedor profesional: sin ITP (operación con IVA/REBU, confirmar en factura); gastos de gestión del vendedor no indicados: se suma la tasa DGT; preguntar el precio final; Euro NCAP de la generación PENDIENTE (seguridad neutra) | BU19: -AUTOECO- *Concesionario Vehículos Ocasión multimarca. *C/ Cases de Bárcena N4 Bonrepos/Valencia 46131 Junto a Gasolinera Repsol* *Lunes a Viernes 9h a 14h y 16h a 20h* *Sábados 10h a 14h tarde y domingos atendemos con cita previa* FINANCIACIÓN A SU MEDIDA sin necesidad de entrada, consulte sin compromiso. DESTACADO: -Con algunos desperfectos de chapa, de ahí su precio. -Vehículo nacional. -Vehículo sin mucha electrónica, fiable. -Sin aire acondicionado. -Muy buen estado interior con desperfectos exteriores de chapa. -Distintivo medioambiental C. -Gran espacio de maletero y amplitud interior. -Radio CD/USB. -1 año de Garantía incluido en precio con opción de ampliación a Premium. *Se entrega con ITV y mantenimiento al día, listo para circular.* Este anuncio puede contener algún error tipográfico o de transcripción. Para más información contacten sin compromiso. | BV19: https://www.coches.net/dacia-sandero-ambiance-12-75cv-5p-gasolina-2012-en-valencia-70507667-covo.aspx (window.__INITIAL_PROPS__.ad) /home/user/Alopecia/buscador-coches/raw/cochesnet/0b381e23cb5ab3e1.json | BW19: =MAX(ANIO_ACTUAL-M19,0) | BX19: =N19/MAX(BW19,0.5) | BY19: =F19 | BZ19: =BY19&"|"&INT(M19/SEG_ANIO)*SEG_ANIO | CA19: =BZ19&"|"&INT(N19/SEG_KM)*SEG_KM | CB19: =COUNTIF($BY$2:$BY$209,BY19) | CC19: =COUNTIF($BZ$2:$BZ$209,BZ19) | CD19: =COUNTIF($CA$2:$CA$209,CA19) | CE19: {=IF(N(BQ19)>=MIN_N,BP19,IF(CD19>=MIN_N,MEDIAN(IF($CA$2:$CA$209=CA19,$O$2:$O$209)),IF(CC19>=MIN_N,MEDIAN(IF($BZ$2:$BZ$209=BZ19,$O$2:$O$209)),MEDIAN(IF($BY$2:$BY$209=BY19,$O$2:$O$209)))))} | CF19: =IF(N(BQ19)>=MIN_N,"mercado "&BR19,IF(CD19>=MIN_N,"modelo+año+km",IF(CC19>=MIN_N,"modelo+año","modelo"))) | CG19: =(CE19-O19)/CE19 | CH19: =IF(COUNTIFS(FR_FUEL,K19,FR_YEAR,AP19)>0,1,0) | CI19: =IF(COUNTIFS(FR_FUEL,K19,FR_YEAR,AP19-1)>0,1,0) | CJ19: =IF(N(AQ19)>0,AP19*100+AQ19,IF(AND(CH19=1,CI19=1),(AP19-1)*100+1,AP19*100+1)) | CK19: =IF(OR(K19="hibrido",K19="glp",K19="gnc",K19="phev"),"ECO",IF(K19="electrico","CERO",IF(K19="gasolina",IF(CJ19>=GAS_C_YM,"C",IF(CJ19>=GAS_B_YM,"B","A")),IF(K19="diesel",IF(CJ19>=DIE_C_YM,"C",IF(CJ19>=DIE_B_YM,"B","A")),"")))) | CL19: C | CM19: =IF(AU19="sí","sí",IF(AS19="regla",IF(AND(N(AQ19)=0,CH19=1),"sí","no"),"no")) | CN19: =IFERROR(VLOOKUP(F19,MOD_TBL,16,0),IFERROR(VLOOKUP(E19,OCU_TBL,2,0),NEUTRO)) | CO19: =SUMIFS(MOT_AJUSTE,MOT_MOTOR,G19,MOT_MARCA,E19,MOT_DESDE,"<="&M19,MOT_HASTA,">="&M19)+SUMIFS(MOT_AJUSTE,MOT_MOTOR,G19,MOT_MARCA,"(todas)",MOT_DESDE,"<="&M19,MOT_HASTA,">="&M19)+SUMIFS(MOT_AJUSTE,MOT_MOTOR,"(cualquiera)",MOT_MARCA,E19,MOT_DESDE,"<="&M19,MOT_HASTA,">="&M19) | CP19: =SUMIFS(COMB_AJUSTE,COMB_COMB,K19) | CQ19: =COUNTIFS(MOT_MOTOR,G19,MOT_MARCA,E19,MOT_DESDE,"<="&M19,MOT_HASTA,">="&M19)+COUNTIFS(MOT_MOTOR,G19,MOT_MARCA,"(todas)",MOT_DESDE,"<="&M19,MOT_HASTA,">="&M19)+COUNTIFS(MOT_MOTOR,"(cualquiera)",MOT_MARCA,E19,MOT_DESDE,"<="&M19,MOT_HASTA,">="&M19) | CR19: =IF(AND(K19="diesel",CQ19=0),MIN(CN19,NEUTRO),CN19) | CS19: =MAX(0,MIN(100,CR19+CO19+CP19-IF(AX19="sí",ROB_PEN,0))) | CT19: =100-MAX(0,N19-KM_TOPE_DESDE)/1000*KM_TOPE_PTS | CU19: =MAX(0,MIN(100,50+CG19*PRECIO_PEND,CT19)) | CV19: =MAX(0,100*(1-N19/KM_MAX)) | CW19: =IF(BX19<KMA_SOSP,IF(AA19="sí",100,KMA_PEN),IF(BX19<=KMA_IDEAL_MAX,100,MAX(0,100*(KMA_CERO-BX19)/(KMA_CERO-KMA_IDEAL_MAX)))) | CX19: =MAX(0,MIN(100,100*(M19-ANIO_MIN)/(ANIO_ACTUAL-ANIO_MIN))) | CY19: =W_KMT*CV19+W_KMA*CW19+W_EDAD*CX19 | CZ19: =E19&"|"&G19 | DA19: =IFERROR(VLOOKUP(CZ19,DIST_TBL,2,0),"") | DB19: =E_ITV*(V19="sí")+E_LIBRO*(W19="sí")+E_PROP*IF(Y19=1,1,IF(Y19=2,0.5,0))+E_CORREA*IF(OR(DA19="cadena",AND(X19="sí",BH19="sí")),1,IF(X19="sí",0.5,0))+E_FACT*(BI19="sí") | DC19: =MAX(0,MIN(100,IFERROR(VLOOKUP(CL19,ETQ_TBL,2,0),0)-IF(CM19="sí",ETQ_PEN_DUD,IF(AS19="regla",ETQ_PEN_REGLA,0)))) | DD19: =IF(K19<>"gasolina","",IFERROR(VLOOKUP(F19,CONS_MOD_TBL,2,0),IFERROR(VLOOKUP(L19,CONS_SEG_TBL,2,0),""))) | DE19: =IF(DD19="",NEUTRO,MAX(0,MIN(100,100*(CONS_REF_MAX-DD19)/(CONS_REF_MAX-CONS_REF_MIN)))) | DF19: =IFERROR(VLOOKUP(L19,SEGURO_TBL,3,0),"") | DG19: =IF(DF19="",NEUTRO,MAX(0,MIN(100,100*(SEG_REF_MAX-DF19)/(SEG_REF_MAX-SEG_REF_MIN)))) | DH19: =IFERROR(VLOOKUP(E19,MANT_MARCA_TBL,2,0)+0,NEUTRO) | DI19: =IF(DA19="",NEUTRO,IFERROR(VLOOKUP(DA19,DIST_PTS_TBL,2,0)+0,NEUTRO)) | DJ19: =(DH19+DI19)/2 | DK19: =W_CONS*DE19+W_SEG*DG19+W_MANT*DJ19 | DL19: =IF(N(AB19)>0,AB19,IF(AND(R19="profesional",SG_LEGAL_ON=1),GAR_LEGAL,0)) | DM19: =MAX(0,MIN(100,SG_GAR*MIN(1,DL19/SG_GAR_FULL)+SG_AMPL*(AC19="sí")+SG_KMC*(AF19="sí")+SG_REV*(N(AE19)>0)+SG_DEV*MIN(1,N(AG19)/SG_DEV_FULL)+SG_HIST*(W19="sí")-IF(AND(R19="particular",DL19=0),SG_PART_PEN,0))) | DN19: =IF(BK19="",NEUTRO,MAX(0,MIN(100,BK19/5*100))) | DO19: =IF(BL19="sí",100,IF(BL19="no",0,NEUTRO)) | DP19: =SV_W_NCAP*DN19+SV_W_ESP*DO19 | DQ19: =MAX(0,MIN(100,ATR_BASE+ATR_ACAB*(BD19<>"")+IF(BE19="16+",ATR_LL16,IF(BE19="sí",ATR_LL,0))+ATR_FAROS*(BF19="sí")+ATR_TINT*(BG19="sí")-ATR_CHAPA*(BE19="chapa"))) | DR19: =EST_W_MOD*(BB19-1)/4*100+EST_W_ATR*DQ19 | DS19: =IF(BA19="",NEUTRO,IFERROR(VLOOKUP(BA19,COLOR_TBL,2,0)+0,NEUTRO)) | DT19: =MAX(0,MIN(100,100*N(BM19)/RV_N_FULL)) | DU19: =IF(OR(BN19="",N(BO19)<RV_DIAS_MIN),NEUTRO,MAX(0,MIN(100,100*(RV_DIAS_CERO-BN19)/(RV_DIAS_CERO-RV_DIAS_FULL)))) | DV19: =RV_W_LIQ*DT19+RV_W_DIAS*DU19+RV_W_ETQ*DC19 | DW19: =IFERROR(VLOOKUP(L19,CARR_PEN_TBL,2,0),0) | DX19: =W_FIAB*CS19+W_PRECIO*CU19+W_KMEDAD*CY19+W_ESTADO*DB19+W_USO*DK19+W_SEGURIDAD*DM19+W_SEGVIAL*DP19+W_ESTETICA*DR19+W_COLOR*DS19+W_REVENTA*DV19-DW19-EG19 | DY19: =IF(N(I19)>0,I19,IFERROR(ROUND(_xlfn.NUMBERVALUE(LEFT(G19,FIND(" ",G19&" ")-1),".")*1000,0),99999)) | DZ19: =IF(R19="profesional",0,IF(O19<CUOTA_VALOR_MAX,IF(BW19>ITP_TRAMO_ALTO,SUMIFS(CF_CUOTA,CF_MAS,ITP_TRAMO_ALTO,CF_CCMIN,"<="&DY19,CF_CCMAX,">="&DY19),IF(BW19>ITP_TRAMO_BAJO,SUMIFS(CF_CUOTA,CF_MAS,ITP_TRAMO_BAJO,CF_CCMIN,"<="&DY19,CF_CCMAX,">="&DY19),O19*ITP_TIPO)),O19*ITP_TIPO)) | EA19: =IF(R19="profesional",N(AK19),0) | EB19: =IF(AND(R19="profesional",ISNUMBER(AK19),AL19="sí"),0,TASA_DGT) | EC19: =INFORME_DGT | ED19: =O19+EA19+DZ19+EB19+EC19 | EE19: =ED19+N(DF19) | EF19: =MAX(0,ED19-TOTAL_MAX) | EG19: =EF19/100*PEN_100 | EH19: =IF(R19="particular",ED19+IF(AND(DA19<>"cadena",X19<>"sí"),RES_CORREA,0)+IF(AND(BJ19<>"sí",BW19>=RES_NEUM_EDAD),RES_NEUM,0),"") | EI19: =IF(ED19<=TOTAL_MAX,"sí",IF(ED19<=TECHO,"negociar","no")) | EJ19: =ROUND(DX19,9) | EK19: =IF(EI19<>"no",SUMPRODUCT(($EI$2:$EI$209<>"no")*($EJ$2:$EJ$209>EJ19))+SUMPRODUCT(($EI$2:EI19<>"no")*($EJ$2:EJ19=EJ19)),"")
A20: cochesnet:71571620 | B20: cochesnet | C20: https://www.coches.net/dacia-logan-laureate-14-4p-gasolina-2007-en-valencia-71571620-covo.aspx | D20: DACIA Logan Laureate 1.4 | E20: Dacia | F20: Dacia Logan | G20: 1.4 | H20: Laureate 1.4 | K20: gasolina | L20: berlina | M20: 2008 | N20: 128293 | O20: 3490 | P20: manual | Q20: no | R20: profesional | S20: AUTOSCOL Torrent | T20: 2026-09-22T15:40:22Z | U20: 18 | Z20: sí | AB20: 12 | AH20: 3490 | AK20: 180 | AL20: sí | AM20: 8.8 | AO20: 2008 | AP20: 2008 | AR20: C | AS20: anuncio | AT20: 2007 | AU20: no | AV20: C | AX20: no | AY20: no | AZ20: COMMON.COLOR_BLUE | BA20: azul | BB20: 3 | BC20: (por segmento) | BM20: 24 | BN20: 0.051261574 | BO20: 2 | BT20: año a confirmar: la URL/título dice 2007; vendedor profesional: sin ITP (operación con IVA/REBU, confirmar en factura); Euro NCAP de la generación PENDIENTE (seguridad neutra); revisar: no menciona la ITV; mediana con solo 1 anuncio(s) | BU20: DACIA LOGAN 1.4 LAUREATE 75 CV – AÑO 2008 ? 128.293 km reales ? Gasolina | Cambio manual | 5 puertas ? Color azul ? Distintivo ambiental: Etiqueta C Coche revisado y preparado en nuestras instalaciones antes de la venta. Motor 1.4 de mecánica Renault, sencilla y resistente, con recambios muy económicos y barato de mantener. Maletero muy amplio y mucho espacio interior. Ideal como primer coche, para trabajar o para uso diario. ?? PRECIO: 3.490 € ??? Garantía de 12 meses ?? Transferencia aparte: 180 € Somos profesionales del sector, compraventa de vehículos de ocasión en Valencia. Facturamos y entregamos toda la documentación en regla. ?? Escríbenos para más fotos o para venir a verlo y probarlo sin compromiso. ?? También compramos y tasamos tu coche. Dacia Logan Sedan en Torrent | BV20: https://www.coches.net/dacia-logan-laureate-14-4p-gasolina-2007-en-valencia-71571620-covo.aspx (window.__INITIAL_PROPS__.ad) /home/user/Alopecia/buscador-coches/raw/cochesnet/419db24ec45a6b74.json | BW20: =MAX(ANIO_ACTUAL-M20,0) | BX20: =N20/MAX(BW20,0.5) | BY20: =F20 | BZ20: =BY20&"|"&INT(M20/SEG_ANIO)*SEG_ANIO | CA20: =BZ20&"|"&INT(N20/SEG_KM)*SEG_KM | CB20: =COUNTIF($BY$2:$BY$209,BY20) | CC20: =COUNTIF($BZ$2:$BZ$209,BZ20) | CD20: =COUNTIF($CA$2:$CA$209,CA20) | CE20: {=IF(N(BQ20)>=MIN_N,BP20,IF(CD20>=MIN_N,MEDIAN(IF($CA$2:$CA$209=CA20,$O$2:$O$209)),IF(CC20>=MIN_N,MEDIAN(IF($BZ$2:$BZ$209=BZ20,$O$2:$O$209)),MEDIAN(IF($BY$2:$BY$209=BY20,$O$2:$O$209)))))} | CF20: =IF(N(BQ20)>=MIN_N,"mercado "&BR20,IF(CD20>=MIN_N,"modelo+año+km",IF(CC20>=MIN_N,"modelo+año","modelo"))) | CG20: =(CE20-O20)/CE20 | CH20: =IF(COUNTIFS(FR_FUEL,K20,FR_YEAR,AP20)>0,1,0) | CI20: =IF(COUNTIFS(FR_FUEL,K20,FR_YEAR,AP20-1)>0,1,0) | CJ20: =IF(N(AQ20)>0,AP20*100+AQ20,IF(AND(CH20=1,CI20=1),(AP20-1)*100+1,AP20*100+1)) | CK20: =IF(OR(K20="hibrido",K20="glp",K20="gnc",K20="phev"),"ECO",IF(K20="electrico","CERO",IF(K20="gasolina",IF(CJ20>=GAS_C_YM,"C",IF(CJ20>=GAS_B_YM,"B","A")),IF(K20="diesel",IF(CJ20>=DIE_C_YM,"C",IF(CJ20>=DIE_B_YM,"B","A")),"")))) | CL20: C | CM20: =IF(AU20="sí","sí",IF(AS20="regla",IF(AND(N(AQ20)=0,CH20=1),"sí","no"),"no")) | CN20: =IFERROR(VLOOKUP(F20,MOD_TBL,16,0),IFERROR(VLOOKUP(E20,OCU_TBL,2,0),NEUTRO)) | CO20: =SUMIFS(MOT_AJUSTE,MOT_MOTOR,G20,MOT_MARCA,E20,MOT_DESDE,"<="&M20,MOT_HASTA,">="&M20)+SUMIFS(MOT_AJUSTE,MOT_MOTOR,G20,MOT_MARCA,"(todas)",MOT_DESDE,"<="&M20,MOT_HASTA,">="&M20)+SUMIFS(MOT_AJUSTE,MOT_MOTOR,"(cualquiera)",MOT_MARCA,E20,MOT_DESDE,"<="&M20,MOT_HASTA,">="&M20) | CP20: =SUMIFS(COMB_AJUSTE,COMB_COMB,K20) | CQ20: =COUNTIFS(MOT_MOTOR,G20,MOT_MARCA,E20,MOT_DESDE,"<="&M20,MOT_HASTA,">="&M20)+COUNTIFS(MOT_MOTOR,G20,MOT_MARCA,"(todas)",MOT_DESDE,"<="&M20,MOT_HASTA,">="&M20)+COUNTIFS(MOT_MOTOR,"(cualquiera)",MOT_MARCA,E20,MOT_DESDE,"<="&M20,MOT_HASTA,">="&M20) | CR20: =IF(AND(K20="diesel",CQ20=0),MIN(CN20,NEUTRO),CN20) | CS20: =MAX(0,MIN(100,CR20+CO20+CP20-IF(AX20="sí",ROB_PEN,0))) | CT20: =100-MAX(0,N20-KM_TOPE_DESDE)/1000*KM_TOPE_PTS | CU20: =MAX(0,MIN(100,50+CG20*PRECIO_PEND,CT20)) | CV20: =MAX(0,100*(1-N20/KM_MAX)) | CW20: =IF(BX20<KMA_SOSP,IF(AA20="sí",100,KMA_PEN),IF(BX20<=KMA_IDEAL_MAX,100,MAX(0,100*(KMA_CERO-BX20)/(KMA_CERO-KMA_IDEAL_MAX)))) | CX20: =MAX(0,MIN(100,100*(M20-ANIO_MIN)/(ANIO_ACTUAL-ANIO_MIN))) | CY20: =W_KMT*CV20+W_KMA*CW20+W_EDAD*CX20 | CZ20: =E20&"|"&G20 | DA20: =IFERROR(VLOOKUP(CZ20,DIST_TBL,2,0),"") | DB20: =E_ITV*(V20="sí")+E_LIBRO*(W20="sí")+E_PROP*IF(Y20=1,1,IF(Y20=2,0.5,0))+E_CORREA*IF(OR(DA20="cadena",AND(X20="sí",BH20="sí")),1,IF(X20="sí",0.5,0))+E_FACT*(BI20="sí") | DC20: =MAX(0,MIN(100,IFERROR(VLOOKUP(CL20,ETQ_TBL,2,0),0)-IF(CM20="sí",ETQ_PEN_DUD,IF(AS20="regla",ETQ_PEN_REGLA,0)))) | DD20: =IF(K20<>"gasolina","",IFERROR(VLOOKUP(F20,CONS_MOD_TBL,2,0),IFERROR(VLOOKUP(L20,CONS_SEG_TBL,2,0),""))) | DE20: =IF(DD20="",NEUTRO,MAX(0,MIN(100,100*(CONS_REF_MAX-DD20)/(CONS_REF_MAX-CONS_REF_MIN)))) | DF20: =IFERROR(VLOOKUP(L20,SEGURO_TBL,3,0),"") | DG20: =IF(DF20="",NEUTRO,MAX(0,MIN(100,100*(SEG_REF_MAX-DF20)/(SEG_REF_MAX-SEG_REF_MIN)))) | DH20: =IFERROR(VLOOKUP(E20,MANT_MARCA_TBL,2,0)+0,NEUTRO) | DI20: =IF(DA20="",NEUTRO,IFERROR(VLOOKUP(DA20,DIST_PTS_TBL,2,0)+0,NEUTRO)) | DJ20: =(DH20+DI20)/2 | DK20: =W_CONS*DE20+W_SEG*DG20+W_MANT*DJ20 | DL20: =IF(N(AB20)>0,AB20,IF(AND(R20="profesional",SG_LEGAL_ON=1),GAR_LEGAL,0)) | DM20: =MAX(0,MIN(100,SG_GAR*MIN(1,DL20/SG_GAR_FULL)+SG_AMPL*(AC20="sí")+SG_KMC*(AF20="sí")+SG_REV*(N(AE20)>0)+SG_DEV*MIN(1,N(AG20)/SG_DEV_FULL)+SG_HIST*(W20="sí")-IF(AND(R20="particular",DL20=0),SG_PART_PEN,0))) | DN20: =IF(BK20="",NEUTRO,MAX(0,MIN(100,BK20/5*100))) | DO20: =IF(BL20="sí",100,IF(BL20="no",0,NEUTRO)) | DP20: =SV_W_NCAP*DN20+SV_W_ESP*DO20 | DQ20: =MAX(0,MIN(100,ATR_BASE+ATR_ACAB*(BD20<>"")+IF(BE20="16+",ATR_LL16,IF(BE20="sí",ATR_LL,0))+ATR_FAROS*(BF20="sí")+ATR_TINT*(BG20="sí")-ATR_CHAPA*(BE20="chapa"))) | DR20: =EST_W_MOD*(BB20-1)/4*100+EST_W_ATR*DQ20 | DS20: =IF(BA20="",NEUTRO,IFERROR(VLOOKUP(BA20,COLOR_TBL,2,0)+0,NEUTRO)) | DT20: =MAX(0,MIN(100,100*N(BM20)/RV_N_FULL)) | DU20: =IF(OR(BN20="",N(BO20)<RV_DIAS_MIN),NEUTRO,MAX(0,MIN(100,100*(RV_DIAS_CERO-BN20)/(RV_DIAS_CERO-RV_DIAS_FULL)))) | DV20: =RV_W_LIQ*DT20+RV_W_DIAS*DU20+RV_W_ETQ*DC20 | DW20: =IFERROR(VLOOKUP(L20,CARR_PEN_TBL,2,0),0) | DX20: =W_FIAB*CS20+W_PRECIO*CU20+W_KMEDAD*CY20+W_ESTADO*DB20+W_USO*DK20+W_SEGURIDAD*DM20+W_SEGVIAL*DP20+W_ESTETICA*DR20+W_COLOR*DS20+W_REVENTA*DV20-DW20-EG20 | DY20: =IF(N(I20)>0,I20,IFERROR(ROUND(_xlfn.NUMBERVALUE(LEFT(G20,FIND(" ",G20&" ")-1),".")*1000,0),99999)) | DZ20: =IF(R20="profesional",0,IF(O20<CUOTA_VALOR_MAX,IF(BW20>ITP_TRAMO_ALTO,SUMIFS(CF_CUOTA,CF_MAS,ITP_TRAMO_ALTO,CF_CCMIN,"<="&DY20,CF_CCMAX,">="&DY20),IF(BW20>ITP_TRAMO_BAJO,SUMIFS(CF_CUOTA,CF_MAS,ITP_TRAMO_BAJO,CF_CCMIN,"<="&DY20,CF_CCMAX,">="&DY20),O20*ITP_TIPO)),O20*ITP_TIPO)) | EA20: =IF(R20="profesional",N(AK20),0) | EB20: =IF(AND(R20="profesional",ISNUMBER(AK20),AL20="sí"),0,TASA_DGT) | EC20: =INFORME_DGT | ED20: =O20+EA20+DZ20+EB20+EC20 | EE20: =ED20+N(DF20) | EF20: =MAX(0,ED20-TOTAL_MAX) | EG20: =EF20/100*PEN_100 | EH20: =IF(R20="particular",ED20+IF(AND(DA20<>"cadena",X20<>"sí"),RES_CORREA,0)+IF(AND(BJ20<>"sí",BW20>=RES_NEUM_EDAD),RES_NEUM,0),"") | EI20: =IF(ED20<=TOTAL_MAX,"sí",IF(ED20<=TECHO,"negociar","no")) | EJ20: =ROUND(DX20,9) | EK20: =IF(EI20<>"no",SUMPRODUCT(($EI$2:$EI$209<>"no")*($EJ$2:$EJ$209>EJ20))+SUMPRODUCT(($EI$2:EI20<>"no")*($EJ$2:EJ20=EJ20)),"")
A21: cochesnet:71833160 | B21: cochesnet | C21: https://www.coches.net/peugeot-207-confort-14-75-5p-gasolina-2009-en-valencia-71833160-covo.aspx | D21: PEUGEOT 207 Confort 1.4 75 | E21: Peugeot | F21: Peugeot 207 | G21: 1.4 | H21: Confort 1.4 75 | K21: gasolina | L21: utilitario | M21: 2009 | N21: 95000 | O21: 3990 | P21: manual | Q21: no | R21: profesional | S21: Prime Cars Alzira Alzira | T21: 2026-10-26T12:09:55Z | U21: 10 | V21: sí | X21: sí | Z21: no | AH21: 3990 | AM21: 35.7 | AO21: 2009 | AP21: 2009 | AR21: C | AS21: anuncio | AU21: no | AV21: C | AX21: no | AY21: no | AZ21: COMMON.COLOR_BLUE | BA21: azul | BB21: 2 | BC21: (por segmento) | BH21: sí | BK21: 5 | BM21: 125 | BO21: 0 | BP21: 4750 | BQ21: 13 | BR21: modelo+año+km | BT21: vendedor profesional: sin ITP (operación con IVA/REBU, confirmar en factura); gastos de gestión del vendedor no indicados: se suma la tasa DGT; preguntar el precio final; fiabilidad del modelo PENDIENTE de fuente (puntuación neutra) | BU21: Peugeot 207 motor 1.4 gasolina con 75 CV. Se encuentra en buen estado general, tiene Aire acondicionado, control de velocidad de crucero, fijaciones Isofix, etc. Se entrega con ITV recién pasada hasta el 10/2027, distribución hecha a los 66.000 kilometros, se acepta prueba mecánica. | BV21: https://www.coches.net/peugeot-207-confort-14-75-5p-gasolina-2009-en-valencia-71833160-covo.aspx (window.__INITIAL_PROPS__.ad) /home/user/Alopecia/buscador-coches/raw/cochesnet/0b54a76ea589cdf3.json | BW21: =MAX(ANIO_ACTUAL-M21,0) | BX21: =N21/MAX(BW21,0.5) | BY21: =F21 | BZ21: =BY21&"|"&INT(M21/SEG_ANIO)*SEG_ANIO | CA21: =BZ21&"|"&INT(N21/SEG_KM)*SEG_KM | CB21: =COUNTIF($BY$2:$BY$209,BY21) | CC21: =COUNTIF($BZ$2:$BZ$209,BZ21) | CD21: =COUNTIF($CA$2:$CA$209,CA21) | CE21: {=IF(N(BQ21)>=MIN_N,BP21,IF(CD21>=MIN_N,MEDIAN(IF($CA$2:$CA$209=CA21,$O$2:$O$209)),IF(CC21>=MIN_N,MEDIAN(IF($BZ$2:$BZ$209=BZ21,$O$2:$O$209)),MEDIAN(IF($BY$2:$BY$209=BY21,$O$2:$O$209)))))} | CF21: =IF(N(BQ21)>=MIN_N,"mercado "&BR21,IF(CD21>=MIN_N,"modelo+año+km",IF(CC21>=MIN_N,"modelo+año","modelo"))) | CG21: =(CE21-O21)/CE21 | CH21: =IF(COUNTIFS(FR_FUEL,K21,FR_YEAR,AP21)>0,1,0) | CI21: =IF(COUNTIFS(FR_FUEL,K21,FR_YEAR,AP21-1)>0,1,0) | CJ21: =IF(N(AQ21)>0,AP21*100+AQ21,IF(AND(CH21=1,CI21=1),(AP21-1)*100+1,AP21*100+1)) | CK21: =IF(OR(K21="hibrido",K21="glp",K21="gnc",K21="phev"),"ECO",IF(K21="electrico","CERO",IF(K21="gasolina",IF(CJ21>=GAS_C_YM,"C",IF(CJ21>=GAS_B_YM,"B","A")),IF(K21="diesel",IF(CJ21>=DIE_C_YM,"C",IF(CJ21>=DIE_B_YM,"B","A")),"")))) | CL21: C | CM21: =IF(AU21="sí","sí",IF(AS21="regla",IF(AND(N(AQ21)=0,CH21=1),"sí","no"),"no")) | CN21: =IFERROR(VLOOKUP(F21,MOD_TBL,16,0),IFERROR(VLOOKUP(E21,OCU_TBL,2,0),NEUTRO)) | CO21: =SUMIFS(MOT_AJUSTE,MOT_MOTOR,G21,MOT_MARCA,E21,MOT_DESDE,"<="&M21,MOT_HASTA,">="&M21)+SUMIFS(MOT_AJUSTE,MOT_MOTOR,G21,MOT_MARCA,"(todas)",MOT_DESDE,"<="&M21,MOT_HASTA,">="&M21)+SUMIFS(MOT_AJUSTE,MOT_MOTOR,"(cualquiera)",MOT_MARCA,E21,MOT_DESDE,"<="&M21,MOT_HASTA,">="&M21) | CP21: =SUMIFS(COMB_AJUSTE,COMB_COMB,K21) | CQ21: =COUNTIFS(MOT_MOTOR,G21,MOT_MARCA,E21,MOT_DESDE,"<="&M21,MOT_HASTA,">="&M21)+COUNTIFS(MOT_MOTOR,G21,MOT_MARCA,"(todas)",MOT_DESDE,"<="&M21,MOT_HASTA,">="&M21)+COUNTIFS(MOT_MOTOR,"(cualquiera)",MOT_MARCA,E21,MOT_DESDE,"<="&M21,MOT_HASTA,">="&M21) | CR21: =IF(AND(K21="diesel",CQ21=0),MIN(CN21,NEUTRO),CN21) | CS21: =MAX(0,MIN(100,CR21+CO21+CP21-IF(AX21="sí",ROB_PEN,0))) | CT21: =100-MAX(0,N21-KM_TOPE_DESDE)/1000*KM_TOPE_PTS | CU21: =MAX(0,MIN(100,50+CG21*PRECIO_PEND,CT21)) | CV21: =MAX(0,100*(1-N21/KM_MAX)) | CW21: =IF(BX21<KMA_SOSP,IF(AA21="sí",100,KMA_PEN),IF(BX21<=KMA_IDEAL_MAX,100,MAX(0,100*(KMA_CERO-BX21)/(KMA_CERO-KMA_IDEAL_MAX)))) | CX21: =MAX(0,MIN(100,100*(M21-ANIO_MIN)/(ANIO_ACTUAL-ANIO_MIN))) | CY21: =W_KMT*CV21+W_KMA*CW21+W_EDAD*CX21 | CZ21: =E21&"|"&G21 | DA21: =IFERROR(VLOOKUP(CZ21,DIST_TBL,2,0),"") | DB21: =E_ITV*(V21="sí")+E_LIBRO*(W21="sí")+E_PROP*IF(Y21=1,1,IF(Y21=2,0.5,0))+E_CORREA*IF(OR(DA21="cadena",AND(X21="sí",BH21="sí")),1,IF(X21="sí",0.5,0))+E_FACT*(BI21="sí") | DC21: =MAX(0,MIN(100,IFERROR(VLOOKUP(CL21,ETQ_TBL,2,0),0)-IF(CM21="sí",ETQ_PEN_DUD,IF(AS21="regla",ETQ_PEN_REGLA,0)))) | DD21: =IF(K21<>"gasolina","",IFERROR(VLOOKUP(F21,CONS_MOD_TBL,2,0),IFERROR(VLOOKUP(L21,CONS_SEG_TBL,2,0),""))) | DE21: =IF(DD21="",NEUTRO,MAX(0,MIN(100,100*(CONS_REF_MAX-DD21)/(CONS_REF_MAX-CONS_REF_MIN)))) | DF21: =IFERROR(VLOOKUP(L21,SEGURO_TBL,3,0),"") | DG21: =IF(DF21="",NEUTRO,MAX(0,MIN(100,100*(SEG_REF_MAX-DF21)/(SEG_REF_MAX-SEG_REF_MIN)))) | DH21: =IFERROR(VLOOKUP(E21,MANT_MARCA_TBL,2,0)+0,NEUTRO) | DI21: =IF(DA21="",NEUTRO,IFERROR(VLOOKUP(DA21,DIST_PTS_TBL,2,0)+0,NEUTRO)) | DJ21: =(DH21+DI21)/2 | DK21: =W_CONS*DE21+W_SEG*DG21+W_MANT*DJ21 | DL21: =IF(N(AB21)>0,AB21,IF(AND(R21="profesional",SG_LEGAL_ON=1),GAR_LEGAL,0)) | DM21: =MAX(0,MIN(100,SG_GAR*MIN(1,DL21/SG_GAR_FULL)+SG_AMPL*(AC21="sí")+SG_KMC*(AF21="sí")+SG_REV*(N(AE21)>0)+SG_DEV*MIN(1,N(AG21)/SG_DEV_FULL)+SG_HIST*(W21="sí")-IF(AND(R21="particular",DL21=0),SG_PART_PEN,0))) | DN21: =IF(BK21="",NEUTRO,MAX(0,MIN(100,BK21/5*100))) | DO21: =IF(BL21="sí",100,IF(BL21="no",0,NEUTRO)) | DP21: =SV_W_NCAP*DN21+SV_W_ESP*DO21 | DQ21: =MAX(0,MIN(100,ATR_BASE+ATR_ACAB*(BD21<>"")+IF(BE21="16+",ATR_LL16,IF(BE21="sí",ATR_LL,0))+ATR_FAROS*(BF21="sí")+ATR_TINT*(BG21="sí")-ATR_CHAPA*(BE21="chapa"))) | DR21: =EST_W_MOD*(BB21-1)/4*100+EST_W_ATR*DQ21 | DS21: =IF(BA21="",NEUTRO,IFERROR(VLOOKUP(BA21,COLOR_TBL,2,0)+0,NEUTRO)) | DT21: =MAX(0,MIN(100,100*N(BM21)/RV_N_FULL)) | DU21: =IF(OR(BN21="",N(BO21)<RV_DIAS_MIN),NEUTRO,MAX(0,MIN(100,100*(RV_DIAS_CERO-BN21)/(RV_DIAS_CERO-RV_DIAS_FULL)))) | DV21: =RV_W_LIQ*DT21+RV_W_DIAS*DU21+RV_W_ETQ*DC21 | DW21: =IFERROR(VLOOKUP(L21,CARR_PEN_TBL,2,0),0) | DX21: =W_FIAB*CS21+W_PRECIO*CU21+W_KMEDAD*CY21+W_ESTADO*DB21+W_USO*DK21+W_SEGURIDAD*DM21+W_SEGVIAL*DP21+W_ESTETICA*DR21+W_COLOR*DS21+W_REVENTA*DV21-DW21-EG21 | DY21: =IF(N(I21)>0,I21,IFERROR(ROUND(_xlfn.NUMBERVALUE(LEFT(G21,FIND(" ",G21&" ")-1),".")*1000,0),99999)) | DZ21: =IF(R21="profesional",0,IF(O21<CUOTA_VALOR_MAX,IF(BW21>ITP_TRAMO_ALTO,SUMIFS(CF_CUOTA,CF_MAS,ITP_TRAMO_ALTO,CF_CCMIN,"<="&DY21,CF_CCMAX,">="&DY21),IF(BW21>ITP_TRAMO_BAJO,SUMIFS(CF_CUOTA,CF_MAS,ITP_TRAMO_BAJO,CF_CCMIN,"<="&DY21,CF_CCMAX,">="&DY21),O21*ITP_TIPO)),O21*ITP_TIPO)) | EA21: =IF(R21="profesional",N(AK21),0) | EB21: =IF(AND(R21="profesional",ISNUMBER(AK21),AL21="sí"),0,TASA_DGT) | EC21: =INFORME_DGT | ED21: =O21+EA21+DZ21+EB21+EC21 | EE21: =ED21+N(DF21) | EF21: =MAX(0,ED21-TOTAL_MAX) | EG21: =EF21/100*PEN_100 | EH21: =IF(R21="particular",ED21+IF(AND(DA21<>"cadena",X21<>"sí"),RES_CORREA,0)+IF(AND(BJ21<>"sí",BW21>=RES_NEUM_EDAD),RES_NEUM,0),"") | EI21: =IF(ED21<=TOTAL_MAX,"sí",IF(ED21<=TECHO,"negociar","no")) | EJ21: =ROUND(DX21,9) | EK21: =IF(EI21<>"no",SUMPRODUCT(($EI$2:$EI$209<>"no")*($EJ$2:$EJ$209>EJ21))+SUMPRODUCT(($EI$2:EI21<>"no")*($EJ$2:EJ21=EJ21)),"")
A22: cochesnet:71580818 | B22: cochesnet | C22: https://www.coches.net/citroen-c4-14-16v-lx-5p-gasolina-2005-en-valencia-71580818-covo.aspx | D22: CITROEN C4 1.4 16v LX | E22: Citroën | F22: Citroën C4 | G22: 1.4 | H22: 1.4 16v LX | K22: gasolina | L22: compacto | M22: 2008 | N22: 148000 | O22: 4390 | P22: manual | Q22: no | R22: profesional | S22: Only Cars Valencia Aldaia | T22: 2026-09-23T13:56:52Z | U22: 11 | Y22: 1 | Z22: sí | AB22: 12 | AH22: 4390 | AM22: 7.5 | AO22: 2008 | AP22: 2008 | AR22: B | AS22: anuncio | AT22: 2005 | AU22: sí | AV22: B/C | AX22: no | AY22: no | AZ22: COMMON.COLOR_GRAY | BA22: gris_medio | BB22: 3 | BC22: (por segmento) | BK22: 5 | BM22: 345 | BN22: 0.051261574 | BO22: 4 | BP22: 3790 | BQ22: 7 | BR22: modelo+año+km | BT22: etiqueta dudosa (B/C): se puntúa la peor (B); confirmar con la DGT antes de comprar; año a confirmar: la URL/título dice 2005; vendedor profesional: sin ITP (operación con IVA/REBU, confirmar en factura); gastos de gestión del vendedor no indicados: se suma la tasa DGT; preguntar el precio final; revisar: no menciona la ITV; fiabilidad del modelo PENDIENTE de fuente (puntuación neutra) | BU22: Citroen C4 1.4 LX año 2008 con 148.000Kms 88CV. UNICO PROPIETARIO Equipamiento: - elevalunas eléctricos - Espejos eléctricos - Aire acondicionado - Dirección asistida - Mando a distancia - Ordenador de abordo - Control de velocidad - Velocidad crucero Mantenimiento: - cambio de filtro de aire - cambio de filtro de aceite - cambio de aceite - Dos juegos de llave - Alfombrillas | BV22: https://www.coches.net/citroen-c4-14-16v-lx-5p-gasolina-2005-en-valencia-71580818-covo.aspx (window.__INITIAL_PROPS__.ad) /home/user/Alopecia/buscador-coches/raw/cochesnet/50707d9d0aa0d3c2.json | BW22: =MAX(ANIO_ACTUAL-M22,0) | BX22: =N22/MAX(BW22,0.5) | BY22: =F22 | BZ22: =BY22&"|"&INT(M22/SEG_ANIO)*SEG_ANIO | CA22: =BZ22&"|"&INT(N22/SEG_KM)*SEG_KM | CB22: =COUNTIF($BY$2:$BY$209,BY22) | CC22: =COUNTIF($BZ$2:$BZ$209,BZ22) | CD22: =COUNTIF($CA$2:$CA$209,CA22) | CE22: {=IF(N(BQ22)>=MIN_N,BP22,IF(CD22>=MIN_N,MEDIAN(IF($CA$2:$CA$209=CA22,$O$2:$O$209)),IF(CC22>=MIN_N,MEDIAN(IF($BZ$2:$BZ$209=BZ22,$O$2:$O$209)),MEDIAN(IF($BY$2:$BY$209=BY22,$O$2:$O$209)))))} | CF22: =IF(N(BQ22)>=MIN_N,"mercado "&BR22,IF(CD22>=MIN_N,"modelo+año+km",IF(CC22>=MIN_N,"modelo+año","modelo"))) | CG22: =(CE22-O22)/CE22 | CH22: =IF(COUNTIFS(FR_FUEL,K22,FR_YEAR,AP22)>0,1,0) | CI22: =IF(COUNTIFS(FR_FUEL,K22,FR_YEAR,AP22-1)>0,1,0) | CJ22: =IF(N(AQ22)>0,AP22*100+AQ22,IF(AND(CH22=1,CI22=1),(AP22-1)*100+1,AP22*100+1)) | CK22: =IF(OR(K22="hibrido",K22="glp",K22="gnc",K22="phev"),"ECO",IF(K22="electrico","CERO",IF(K22="gasolina",IF(CJ22>=GAS_C_YM,"C",IF(CJ22>=GAS_B_YM,"B","A")),IF(K22="diesel",IF(CJ22>=DIE_C_YM,"C",IF(CJ22>=DIE_B_YM,"B","A")),"")))) | CL22: B | CM22: =IF(AU22="sí","sí",IF(AS22="regla",IF(AND(N(AQ22)=0,CH22=1),"sí","no"),"no")) | CN22: =IFERROR(VLOOKUP(F22,MOD_TBL,16,0),IFERROR(VLOOKUP(E22,OCU_TBL,2,0),NEUTRO)) | CO22: =SUMIFS(MOT_AJUSTE,MOT_MOTOR,G22,MOT_MARCA,E22,MOT_DESDE,"<="&M22,MOT_HASTA,">="&M22)+SUMIFS(MOT_AJUSTE,MOT_MOTOR,G22,MOT_MARCA,"(todas)",MOT_DESDE,"<="&M22,MOT_HASTA,">="&M22)+SUMIFS(MOT_AJUSTE,MOT_MOTOR,"(cualquiera)",MOT_MARCA,E22,MOT_DESDE,"<="&M22,MOT_HASTA,">="&M22) | CP22: =SUMIFS(COMB_AJUSTE,COMB_COMB,K22) | CQ22: =COUNTIFS(MOT_MOTOR,G22,MOT_MARCA,E22,MOT_DESDE,"<="&M22,MOT_HASTA,">="&M22)+COUNTIFS(MOT_MOTOR,G22,MOT_MARCA,"(todas)",MOT_DESDE,"<="&M22,MOT_HASTA,">="&M22)+COUNTIFS(MOT_MOTOR,"(cualquiera)",MOT_MARCA,E22,MOT_DESDE,"<="&M22,MOT_HASTA,">="&M22) | CR22: =IF(AND(K22="diesel",CQ22=0),MIN(CN22,NEUTRO),CN22) | CS22: =MAX(0,MIN(100,CR22+CO22+CP22-IF(AX22="sí",ROB_PEN,0))) | CT22: =100-MAX(0,N22-KM_TOPE_DESDE)/1000*KM_TOPE_PTS | CU22: =MAX(0,MIN(100,50+CG22*PRECIO_PEND,CT22)) | CV22: =MAX(0,100*(1-N22/KM_MAX)) | CW22: =IF(BX22<KMA_SOSP,IF(AA22="sí",100,KMA_PEN),IF(BX22<=KMA_IDEAL_MAX,100,MAX(0,100*(KMA_CERO-BX22)/(KMA_CERO-KMA_IDEAL_MAX)))) | CX22: =MAX(0,MIN(100,100*(M22-ANIO_MIN)/(ANIO_ACTUAL-ANIO_MIN))) | CY22: =W_KMT*CV22+W_KMA*CW22+W_EDAD*CX22 | CZ22: =E22&"|"&G22 | DA22: =IFERROR(VLOOKUP(CZ22,DIST_TBL,2,0),"") | DB22: =E_ITV*(V22="sí")+E_LIBRO*(W22="sí")+E_PROP*IF(Y22=1,1,IF(Y22=2,0.5,0))+E_CORREA*IF(OR(DA22="cadena",AND(X22="sí",BH22="sí")),1,IF(X22="sí",0.5,0))+E_FACT*(BI22="sí") | DC22: =MAX(0,MIN(100,IFERROR(VLOOKUP(CL22,ETQ_TBL,2,0),0)-IF(CM22="sí",ETQ_PEN_DUD,IF(AS22="regla",ETQ_PEN_REGLA,0)))) | DD22: =IF(K22<>"gasolina","",IFERROR(VLOOKUP(F22,CONS_MOD_TBL,2,0),IFERROR(VLOOKUP(L22,CONS_SEG_TBL,2,0),""))) | DE22: =IF(DD22="",NEUTRO,MAX(0,MIN(100,100*(CONS_REF_MAX-DD22)/(CONS_REF_MAX-CONS_REF_MIN)))) | DF22: =IFERROR(VLOOKUP(L22,SEGURO_TBL,3,0),"") | DG22: =IF(DF22="",NEUTRO,MAX(0,MIN(100,100*(SEG_REF_MAX-DF22)/(SEG_REF_MAX-SEG_REF_MIN)))) | DH22: =IFERROR(VLOOKUP(E22,MANT_MARCA_TBL,2,0)+0,NEUTRO) | DI22: =IF(DA22="",NEUTRO,IFERROR(VLOOKUP(DA22,DIST_PTS_TBL,2,0)+0,NEUTRO)) | DJ22: =(DH22+DI22)/2 | DK22: =W_CONS*DE22+W_SEG*DG22+W_MANT*DJ22 | DL22: =IF(N(AB22)>0,AB22,IF(AND(R22="profesional",SG_LEGAL_ON=1),GAR_LEGAL,0)) | DM22: =MAX(0,MIN(100,SG_GAR*MIN(1,DL22/SG_GAR_FULL)+SG_AMPL*(AC22="sí")+SG_KMC*(AF22="sí")+SG_REV*(N(AE22)>0)+SG_DEV*MIN(1,N(AG22)/SG_DEV_FULL)+SG_HIST*(W22="sí")-IF(AND(R22="particular",DL22=0),SG_PART_PEN,0))) | DN22: =IF(BK22="",NEUTRO,MAX(0,MIN(100,BK22/5*100))) | DO22: =IF(BL22="sí",100,IF(BL22="no",0,NEUTRO)) | DP22: =SV_W_NCAP*DN22+SV_W_ESP*DO22 | DQ22: =MAX(0,MIN(100,ATR_BASE+ATR_ACAB*(BD22<>"")+IF(BE22="16+",ATR_LL16,IF(BE22="sí",ATR_LL,0))+ATR_FAROS*(BF22="sí")+ATR_TINT*(BG22="sí")-ATR_CHAPA*(BE22="chapa"))) | DR22: =EST_W_MOD*(BB22-1)/4*100+EST_W_ATR*DQ22 | DS22: =IF(BA22="",NEUTRO,IFERROR(VLOOKUP(BA22,COLOR_TBL,2,0)+0,NEUTRO)) | DT22: =MAX(0,MIN(100,100*N(BM22)/RV_N_FULL)) | DU22: =IF(OR(BN22="",N(BO22)<RV_DIAS_MIN),NEUTRO,MAX(0,MIN(100,100*(RV_DIAS_CERO-BN22)/(RV_DIAS_CERO-RV_DIAS_FULL)))) | DV22: =RV_W_LIQ*DT22+RV_W_DIAS*DU22+RV_W_ETQ*DC22 | DW22: =IFERROR(VLOOKUP(L22,CARR_PEN_TBL,2,0),0) | DX22: =W_FIAB*CS22+W_PRECIO*CU22+W_KMEDAD*CY22+W_ESTADO*DB22+W_USO*DK22+W_SEGURIDAD*DM22+W_SEGVIAL*DP22+W_ESTETICA*DR22+W_COLOR*DS22+W_REVENTA*DV22-DW22-EG22 | DY22: =IF(N(I22)>0,I22,IFERROR(ROUND(_xlfn.NUMBERVALUE(LEFT(G22,FIND(" ",G22&" ")-1),".")*1000,0),99999)) | DZ22: =IF(R22="profesional",0,IF(O22<CUOTA_VALOR_MAX,IF(BW22>ITP_TRAMO_ALTO,SUMIFS(CF_CUOTA,CF_MAS,ITP_TRAMO_ALTO,CF_CCMIN,"<="&DY22,CF_CCMAX,">="&DY22),IF(BW22>ITP_TRAMO_BAJO,SUMIFS(CF_CUOTA,CF_MAS,ITP_TRAMO_BAJO,CF_CCMIN,"<="&DY22,CF_CCMAX,">="&DY22),O22*ITP_TIPO)),O22*ITP_TIPO)) | EA22: =IF(R22="profesional",N(AK22),0) | EB22: =IF(AND(R22="profesional",ISNUMBER(AK22),AL22="sí"),0,TASA_DGT) | EC22: =INFORME_DGT | ED22: =O22+EA22+DZ22+EB22+EC22 | EE22: =ED22+N(DF22) | EF22: =MAX(0,ED22-TOTAL_MAX) | EG22: =EF22/100*PEN_100 | EH22: =IF(R22="particular",ED22+IF(AND(DA22<>"cadena",X22<>"sí"),RES_CORREA,0)+IF(AND(BJ22<>"sí",BW22>=RES_NEUM_EDAD),RES_NEUM,0),"") | EI22: =IF(ED22<=TOTAL_MAX,"sí",IF(ED22<=TECHO,"negociar","no")) | EJ22: =ROUND(DX22,9) | EK22: =IF(EI22<>"no",SUMPRODUCT(($EI$2:$EI$209<>"no")*($EJ$2:$EJ$209>EJ22))+SUMPRODUCT(($EI$2:EI22<>"no")*($EJ$2:EJ22=EJ22)),"")
A23: cochesnet:71569576 | B23: cochesnet | C23: https://www.coches.net/ford-ka-12-trend-3p-gasolina-2010-en-valencia-71569576-covo.aspx | D23: FORD Ka 1.2 Trend | E23: Ford | F23: Ford Ka | G23: 1.2 | H23: 1.2 Trend | K23: gasolina | L23: utilitario | M23: 2010 | N23: 157000 | O23: 3500 | P23: manual | Q23: no | R23: profesional | S23: Beniparrell | T23: 2026-09-22T12:09:29Z | U23: 13 | Z23: sí | AB23: 12 | AH23: 3500 | AM23: 10.2 | AO23: 2010 | AP23: 2010 | AR23: C | AS23: anuncio | AU23: no | AV23: C | AX23: no | AY23: no | AZ23: COMMON.COLOR_RED | BA23: rojo | BB23: 2 | BC23: (por segmento) | BG23: sí | BM23: 50 | BO23: 0 | BP23: 3000 | BQ23: 9 | BR23: modelo+año | BT23: vendedor profesional: sin ITP (operación con IVA/REBU, confirmar en factura); gastos de gestión del vendedor no indicados: se suma la tasa DGT; preguntar el precio final; Euro NCAP de la generación PENDIENTE (seguridad neutra); revisar: no menciona la ITV; fiabilidad del modelo PENDIENTE de fuente (puntuación neutra) | BU23: Este Ford Ka Trend+ destaca por su equipamiento práctico orientado al día a día: control de crucero, ordenador de viaje con información de consumo e autonomía, y elevalunas eléctricos delanteros con función de un solo toque. Dispone de dirección asistida, cierre centralizado con mando a distancia de doble cierre, retrovisores exteriores eléctricos y desempañables, además de cristales tintados que mejoran la privacidad. El interior combina asientos ajustables en altura con compartimentos de almacenamiento bajo el asiento del acompañante. Su etiqueta medioambiental C facilita el acceso a zonas de tráfico restringido. Transmisión manual con cambio de marchas directo. | BV23: https://www.coches.net/ford-ka-12-trend-3p-gasolina-2010-en-valencia-71569576-covo.aspx (window.__INITIAL_PROPS__.ad) /home/user/Alopecia/buscador-coches/raw/cochesnet/f615001a1b31829d.json | BW23: =MAX(ANIO_ACTUAL-M23,0) | BX23: =N23/MAX(BW23,0.5) | BY23: =F23 | BZ23: =BY23&"|"&INT(M23/SEG_ANIO)*SEG_ANIO | CA23: =BZ23&"|"&INT(N23/SEG_KM)*SEG_KM | CB23: =COUNTIF($BY$2:$BY$209,BY23) | CC23: =COUNTIF($BZ$2:$BZ$209,BZ23) | CD23: =COUNTIF($CA$2:$CA$209,CA23) | CE23: {=IF(N(BQ23)>=MIN_N,BP23,IF(CD23>=MIN_N,MEDIAN(IF($CA$2:$CA$209=CA23,$O$2:$O$209)),IF(CC23>=MIN_N,MEDIAN(IF($BZ$2:$BZ$209=BZ23,$O$2:$O$209)),MEDIAN(IF($BY$2:$BY$209=BY23,$O$2:$O$209)))))} | CF23: =IF(N(BQ23)>=MIN_N,"mercado "&BR23,IF(CD23>=MIN_N,"modelo+año+km",IF(CC23>=MIN_N,"modelo+año","modelo"))) | CG23: =(CE23-O23)/CE23 | CH23: =IF(COUNTIFS(FR_FUEL,K23,FR_YEAR,AP23)>0,1,0) | CI23: =IF(COUNTIFS(FR_FUEL,K23,FR_YEAR,AP23-1)>0,1,0) | CJ23: =IF(N(AQ23)>0,AP23*100+AQ23,IF(AND(CH23=1,CI23=1),(AP23-1)*100+1,AP23*100+1)) | CK23: =IF(OR(K23="hibrido",K23="glp",K23="gnc",K23="phev"),"ECO",IF(K23="electrico","CERO",IF(K23="gasolina",IF(CJ23>=GAS_C_YM,"C",IF(CJ23>=GAS_B_YM,"B","A")),IF(K23="diesel",IF(CJ23>=DIE_C_YM,"C",IF(CJ23>=DIE_B_YM,"B","A")),"")))) | CL23: C | CM23: =IF(AU23="sí","sí",IF(AS23="regla",IF(AND(N(AQ23)=0,CH23=1),"sí","no"),"no")) | CN23: =IFERROR(VLOOKUP(F23,MOD_TBL,16,0),IFERROR(VLOOKUP(E23,OCU_TBL,2,0),NEUTRO)) | CO23: =SUMIFS(MOT_AJUSTE,MOT_MOTOR,G23,MOT_MARCA,E23,MOT_DESDE,"<="&M23,MOT_HASTA,">="&M23)+SUMIFS(MOT_AJUSTE,MOT_MOTOR,G23,MOT_MARCA,"(todas)",MOT_DESDE,"<="&M23,MOT_HASTA,">="&M23)+SUMIFS(MOT_AJUSTE,MOT_MOTOR,"(cualquiera)",MOT_MARCA,E23,MOT_DESDE,"<="&M23,MOT_HASTA,">="&M23) | CP23: =SUMIFS(COMB_AJUSTE,COMB_COMB,K23) | CQ23: =COUNTIFS(MOT_MOTOR,G23,MOT_MARCA,E23,MOT_DESDE,"<="&M23,MOT_HASTA,">="&M23)+COUNTIFS(MOT_MOTOR,G23,MOT_MARCA,"(todas)",MOT_DESDE,"<="&M23,MOT_HASTA,">="&M23)+COUNTIFS(MOT_MOTOR,"(cualquiera)",MOT_MARCA,E23,MOT_DESDE,"<="&M23,MOT_HASTA,">="&M23) | CR23: =IF(AND(K23="diesel",CQ23=0),MIN(CN23,NEUTRO),CN23) | CS23: =MAX(0,MIN(100,CR23+CO23+CP23-IF(AX23="sí",ROB_PEN,0))) | CT23: =100-MAX(0,N23-KM_TOPE_DESDE)/1000*KM_TOPE_PTS | CU23: =MAX(0,MIN(100,50+CG23*PRECIO_PEND,CT23)) | CV23: =MAX(0,100*(1-N23/KM_MAX)) | CW23: =IF(BX23<KMA_SOSP,IF(AA23="sí",100,KMA_PEN),IF(BX23<=KMA_IDEAL_MAX,100,MAX(0,100*(KMA_CERO-BX23)/(KMA_CERO-KMA_IDEAL_MAX)))) | CX23: =MAX(0,MIN(100,100*(M23-ANIO_MIN)/(ANIO_ACTUAL-ANIO_MIN))) | CY23: =W_KMT*CV23+W_KMA*CW23+W_EDAD*CX23 | CZ23: =E23&"|"&G23 | DA23: =IFERROR(VLOOKUP(CZ23,DIST_TBL,2,0),"") | DB23: =E_ITV*(V23="sí")+E_LIBRO*(W23="sí")+E_PROP*IF(Y23=1,1,IF(Y23=2,0.5,0))+E_CORREA*IF(OR(DA23="cadena",AND(X23="sí",BH23="sí")),1,IF(X23="sí",0.5,0))+E_FACT*(BI23="sí") | DC23: =MAX(0,MIN(100,IFERROR(VLOOKUP(CL23,ETQ_TBL,2,0),0)-IF(CM23="sí",ETQ_PEN_DUD,IF(AS23="regla",ETQ_PEN_REGLA,0)))) | DD23: =IF(K23<>"gasolina","",IFERROR(VLOOKUP(F23,CONS_MOD_TBL,2,0),IFERROR(VLOOKUP(L23,CONS_SEG_TBL,2,0),""))) | DE23: =IF(DD23="",NEUTRO,MAX(0,MIN(100,100*(CONS_REF_MAX-DD23)/(CONS_REF_MAX-CONS_REF_MIN)))) | DF23: =IFERROR(VLOOKUP(L23,SEGURO_TBL,3,0),"") | DG23: =IF(DF23="",NEUTRO,MAX(0,MIN(100,100*(SEG_REF_MAX-DF23)/(SEG_REF_MAX-SEG_REF_MIN)))) | DH23: =IFERROR(VLOOKUP(E23,MANT_MARCA_TBL,2,0)+0,NEUTRO) | DI23: =IF(DA23="",NEUTRO,IFERROR(VLOOKUP(DA23,DIST_PTS_TBL,2,0)+0,NEUTRO)) | DJ23: =(DH23+DI23)/2 | DK23: =W_CONS*DE23+W_SEG*DG23+W_MANT*DJ23 | DL23: =IF(N(AB23)>0,AB23,IF(AND(R23="profesional",SG_LEGAL_ON=1),GAR_LEGAL,0)) | DM23: =MAX(0,MIN(100,SG_GAR*MIN(1,DL23/SG_GAR_FULL)+SG_AMPL*(AC23="sí")+SG_KMC*(AF23="sí")+SG_REV*(N(AE23)>0)+SG_DEV*MIN(1,N(AG23)/SG_DEV_FULL)+SG_HIST*(W23="sí")-IF(AND(R23="particular",DL23=0),SG_PART_PEN,0))) | DN23: =IF(BK23="",NEUTRO,MAX(0,MIN(100,BK23/5*100))) | DO23: =IF(BL23="sí",100,IF(BL23="no",0,NEUTRO)) | DP23: =SV_W_NCAP*DN23+SV_W_ESP*DO23 | DQ23: =MAX(0,MIN(100,ATR_BASE+ATR_ACAB*(BD23<>"")+IF(BE23="16+",ATR_LL16,IF(BE23="sí",ATR_LL,0))+ATR_FAROS*(BF23="sí")+ATR_TINT*(BG23="sí")-ATR_CHAPA*(BE23="chapa"))) | DR23: =EST_W_MOD*(BB23-1)/4*100+EST_W_ATR*DQ23 | DS23: =IF(BA23="",NEUTRO,IFERROR(VLOOKUP(BA23,COLOR_TBL,2,0)+0,NEUTRO)) | DT23: =MAX(0,MIN(100,100*N(BM23)/RV_N_FULL)) | DU23: =IF(OR(BN23="",N(BO23)<RV_DIAS_MIN),NEUTRO,MAX(0,MIN(100,100*(RV_DIAS_CERO-BN23)/(RV_DIAS_CERO-RV_DIAS_FULL)))) | DV23: =RV_W_LIQ*DT23+RV_W_DIAS*DU23+RV_W_ETQ*DC23 | DW23: =IFERROR(VLOOKUP(L23,CARR_PEN_TBL,2,0),0) | DX23: =W_FIAB*CS23+W_PRECIO*CU23+W_KMEDAD*CY23+W_ESTADO*DB23+W_USO*DK23+W_SEGURIDAD*DM23+W_SEGVIAL*DP23+W_ESTETICA*DR23+W_COLOR*DS23+W_REVENTA*DV23-DW23-EG23 | DY23: =IF(N(I23)>0,I23,IFERROR(ROUND(_xlfn.NUMBERVALUE(LEFT(G23,FIND(" ",G23&" ")-1),".")*1000,0),99999)) | DZ23: =IF(R23="profesional",0,IF(O23<CUOTA_VALOR_MAX,IF(BW23>ITP_TRAMO_ALTO,SUMIFS(CF_CUOTA,CF_MAS,ITP_TRAMO_ALTO,CF_CCMIN,"<="&DY23,CF_CCMAX,">="&DY23),IF(BW23>ITP_TRAMO_BAJO,SUMIFS(CF_CUOTA,CF_MAS,ITP_TRAMO_BAJO,CF_CCMIN,"<="&DY23,CF_CCMAX,">="&DY23),O23*ITP_TIPO)),O23*ITP_TIPO)) | EA23: =IF(R23="profesional",N(AK23),0) | EB23: =IF(AND(R23="profesional",ISNUMBER(AK23),AL23="sí"),0,TASA_DGT) | EC23: =INFORME_DGT | ED23: =O23+EA23+DZ23+EB23+EC23 | EE23: =ED23+N(DF23) | EF23: =MAX(0,ED23-TOTAL_MAX) | EG23: =EF23/100*PEN_100 | EH23: =IF(R23="particular",ED23+IF(AND(DA23<>"cadena",X23<>"sí"),RES_CORREA,0)+IF(AND(BJ23<>"sí",BW23>=RES_NEUM_EDAD),RES_NEUM,0),"") | EI23: =IF(ED23<=TOTAL_MAX,"sí",IF(ED23<=TECHO,"negociar","no")) | EJ23: =ROUND(DX23,9) | EK23: =IF(EI23<>"no",SUMPRODUCT(($EI$2:$EI$209<>"no")*($EJ$2:$EJ$209>EJ23))+SUMPRODUCT(($EI$2:EI23<>"no")*($EJ$2:EJ23=EJ23)),"")
A24: cochesnet:70592187 | B24: cochesnet | C24: https://www.coches.net/ford-fiesta-14-tdci-trend-5p-diesel-2011-en-valencia-70592187-covo.aspx | D24: FORD Fiesta 1.4 TDCi Trend | E24: Ford | F24: Ford Fiesta | G24: 1.4 TDCi | H24: 1.4 TDCi Trend | K24: diesel | L24: utilitario | M24: 2011 | N24: 199000 | O24: 4490 | P24: manual | Q24: no | R24: profesional | S24: V.O. Eliana San Antonio de Benagéber | T24: 2026-08-05T20:05:58Z | U24: 18 | Z24: sí | AB24: 12 | AH24: 4490 | AM24: 19.1 | AO24: 2011 | AP24: 2011 | AR24: B | AS24: anuncio | AU24: no | AV24: B | AX24: no | AY24: no | AZ24: COMMON.COLOR_WHITE | BA24: blanco | BB24: 2 | BC24: (por segmento) | BK24: 5 | BL24: sí | BM24: 302 | BN24: 0.074340278 | BO24: 3 | BP24: 4490 | BQ24: 19 | BR24: modelo+año+km | BT24: vendedor profesional: sin ITP (operación con IVA/REBU, confirmar en factura); gastos de gestión del vendedor no indicados: se suma la tasa DGT; preguntar el precio final; diésel: motor sin fuente de fiabilidad (fiabilidad limitada a neutra); revisar: no menciona la ITV | BU24: Este Ford Fiesta 1.4 TDCi Trend es un vehículo compacto y eficiente, particularmente adecuado para uso urbano y desplazamientos diarios. Su motor diésel de 70 CV proporciona un consumo contenido —en torno a 4,1 l/100 km en ciclo mixto— lo que permite una autonomía de casi 1.000 kilómetros con el depósito lleno de 40 litros. El habitáculo ofrece espacio suficiente para cinco ocupantes con comodidad en los desplazamientos cortos y medios. Los asientos delanteros cuentan con ajuste manual en altura, mientras que la banqueta trasera dispone de respaldo abatible asimétrico, facilitando la versatilidad de carga. El maletero de 295 litros se expande hasta 979 litros con los asientos plegados, una capacidad práctica para compras y pequeños viajes. En cuanto a equipamiento de confort, este incluye dirección asistida eléctrica con endurecimiento progresivo, elevalunas eléctricos delanteros, cierre centralizado con mando a distancia de doble cierre y apertura remota del maletero. El sistema de ventilación incorpora filtro de pólen. El volante es ajustable en altura y profundidad, y los retrovisores exteriores son eléctricos, desempañables y cuentan con intermitente integrado. La seguridad está garantizada con airbags frontales inteligentes y laterales delanteros, cinturones de seguridad con pretensores en los asientos delanteros, ABS, control electrónico de tracción y control de estabilidad. Dispone de preparación Isofix para sistemas de retención infantil. Este modelo cuenta con et | BV24: https://www.coches.net/ford-fiesta-14-tdci-trend-5p-diesel-2011-en-valencia-70592187-covo.aspx (window.__INITIAL_PROPS__.ad) /home/user/Alopecia/buscador-coches/raw/cochesnet/b52cc027b9556748.json | BW24: =MAX(ANIO_ACTUAL-M24,0) | BX24: =N24/MAX(BW24,0.5) | BY24: =F24 | BZ24: =BY24&"|"&INT(M24/SEG_ANIO)*SEG_ANIO | CA24: =BZ24&"|"&INT(N24/SEG_KM)*SEG_KM | CB24: =COUNTIF($BY$2:$BY$209,BY24) | CC24: =COUNTIF($BZ$2:$BZ$209,BZ24) | CD24: =COUNTIF($CA$2:$CA$209,CA24) | CE24: {=IF(N(BQ24)>=MIN_N,BP24,IF(CD24>=MIN_N,MEDIAN(IF($CA$2:$CA$209=CA24,$O$2:$O$209)),IF(CC24>=MIN_N,MEDIAN(IF($BZ$2:$BZ$209=BZ24,$O$2:$O$209)),MEDIAN(IF($BY$2:$BY$209=BY24,$O$2:$O$209)))))} | CF24: =IF(N(BQ24)>=MIN_N,"mercado "&BR24,IF(CD24>=MIN_N,"modelo+año+km",IF(CC24>=MIN_N,"modelo+año","modelo"))) | CG24: =(CE24-O24)/CE24 | CH24: =IF(COUNTIFS(FR_FUEL,K24,FR_YEAR,AP24)>0,1,0) | CI24: =IF(COUNTIFS(FR_FUEL,K24,FR_YEAR,AP24-1)>0,1,0) | CJ24: =IF(N(AQ24)>0,AP24*100+AQ24,IF(AND(CH24=1,CI24=1),(AP24-1)*100+1,AP24*100+1)) | CK24: =IF(OR(K24="hibrido",K24="glp",K24="gnc",K24="phev"),"ECO",IF(K24="electrico","CERO",IF(K24="gasolina",IF(CJ24>=GAS_C_YM,"C",IF(CJ24>=GAS_B_YM,"B","A")),IF(K24="diesel",IF(CJ24>=DIE_C_YM,"C",IF(CJ24>=DIE_B_YM,"B","A")),"")))) | CL24: B | CM24: =IF(AU24="sí","sí",IF(AS24="regla",IF(AND(N(AQ24)=0,CH24=1),"sí","no"),"no")) | CN24: =IFERROR(VLOOKUP(F24,MOD_TBL,16,0),IFERROR(VLOOKUP(E24,OCU_TBL,2,0),NEUTRO)) | CO24: =SUMIFS(MOT_AJUSTE,MOT_MOTOR,G24,MOT_MARCA,E24,MOT_DESDE,"<="&M24,MOT_HASTA,">="&M24)+SUMIFS(MOT_AJUSTE,MOT_MOTOR,G24,MOT_MARCA,"(todas)",MOT_DESDE,"<="&M24,MOT_HASTA,">="&M24)+SUMIFS(MOT_AJUSTE,MOT_MOTOR,"(cualquiera)",MOT_MARCA,E24,MOT_DESDE,"<="&M24,MOT_HASTA,">="&M24) | CP24: =SUMIFS(COMB_AJUSTE,COMB_COMB,K24) | CQ24: =COUNTIFS(MOT_MOTOR,G24,MOT_MARCA,E24,MOT_DESDE,"<="&M24,MOT_HASTA,">="&M24)+COUNTIFS(MOT_MOTOR,G24,MOT_MARCA,"(todas)",MOT_DESDE,"<="&M24,MOT_HASTA,">="&M24)+COUNTIFS(MOT_MOTOR,"(cualquiera)",MOT_MARCA,E24,MOT_DESDE,"<="&M24,MOT_HASTA,">="&M24) | CR24: =IF(AND(K24="diesel",CQ24=0),MIN(CN24,NEUTRO),CN24) | CS24: =MAX(0,MIN(100,CR24+CO24+CP24-IF(AX24="sí",ROB_PEN,0))) | CT24: =100-MAX(0,N24-KM_TOPE_DESDE)/1000*KM_TOPE_PTS | CU24: =MAX(0,MIN(100,50+CG24*PRECIO_PEND,CT24)) | CV24: =MAX(0,100*(1-N24/KM_MAX)) | CW24: =IF(BX24<KMA_SOSP,IF(AA24="sí",100,KMA_PEN),IF(BX24<=KMA_IDEAL_MAX,100,MAX(0,100*(KMA_CERO-BX24)/(KMA_CERO-KMA_IDEAL_MAX)))) | CX24: =MAX(0,MIN(100,100*(M24-ANIO_MIN)/(ANIO_ACTUAL-ANIO_MIN))) | CY24: =W_KMT*CV24+W_KMA*CW24+W_EDAD*CX24 | CZ24: =E24&"|"&G24 | DA24: =IFERROR(VLOOKUP(CZ24,DIST_TBL,2,0),"") | DB24: =E_ITV*(V24="sí")+E_LIBRO*(W24="sí")+E_PROP*IF(Y24=1,1,IF(Y24=2,0.5,0))+E_CORREA*IF(OR(DA24="cadena",AND(X24="sí",BH24="sí")),1,IF(X24="sí",0.5,0))+E_FACT*(BI24="sí") | DC24: =MAX(0,MIN(100,IFERROR(VLOOKUP(CL24,ETQ_TBL,2,0),0)-IF(CM24="sí",ETQ_PEN_DUD,IF(AS24="regla",ETQ_PEN_REGLA,0)))) | DD24: =IF(K24<>"gasolina","",IFERROR(VLOOKUP(F24,CONS_MOD_TBL,2,0),IFERROR(VLOOKUP(L24,CONS_SEG_TBL,2,0),""))) | DE24: =IF(DD24="",NEUTRO,MAX(0,MIN(100,100*(CONS_REF_MAX-DD24)/(CONS_REF_MAX-CONS_REF_MIN)))) | DF24: =IFERROR(VLOOKUP(L24,SEGURO_TBL,3,0),"") | DG24: =IF(DF24="",NEUTRO,MAX(0,MIN(100,100*(SEG_REF_MAX-DF24)/(SEG_REF_MAX-SEG_REF_MIN)))) | DH24: =IFERROR(VLOOKUP(E24,MANT_MARCA_TBL,2,0)+0,NEUTRO) | DI24: =IF(DA24="",NEUTRO,IFERROR(VLOOKUP(DA24,DIST_PTS_TBL,2,0)+0,NEUTRO)) | DJ24: =(DH24+DI24)/2 | DK24: =W_CONS*DE24+W_SEG*DG24+W_MANT*DJ24 | DL24: =IF(N(AB24)>0,AB24,IF(AND(R24="profesional",SG_LEGAL_ON=1),GAR_LEGAL,0)) | DM24: =MAX(0,MIN(100,SG_GAR*MIN(1,DL24/SG_GAR_FULL)+SG_AMPL*(AC24="sí")+SG_KMC*(AF24="sí")+SG_REV*(N(AE24)>0)+SG_DEV*MIN(1,N(AG24)/SG_DEV_FULL)+SG_HIST*(W24="sí")-IF(AND(R24="particular",DL24=0),SG_PART_PEN,0))) | DN24: =IF(BK24="",NEUTRO,MAX(0,MIN(100,BK24/5*100))) | DO24: =IF(BL24="sí",100,IF(BL24="no",0,NEUTRO)) | DP24: =SV_W_NCAP*DN24+SV_W_ESP*DO24 | DQ24: =MAX(0,MIN(100,ATR_BASE+ATR_ACAB*(BD24<>"")+IF(BE24="16+",ATR_LL16,IF(BE24="sí",ATR_LL,0))+ATR_FAROS*(BF24="sí")+ATR_TINT*(BG24="sí")-ATR_CHAPA*(BE24="chapa"))) | DR24: =EST_W_MOD*(BB24-1)/4*100+EST_W_ATR*DQ24 | DS24: =IF(BA24="",NEUTRO,IFERROR(VLOOKUP(BA24,COLOR_TBL,2,0)+0,NEUTRO)) | DT24: =MAX(0,MIN(100,100*N(BM24)/RV_N_FULL)) | DU24: =IF(OR(BN24="",N(BO24)<RV_DIAS_MIN),NEUTRO,MAX(0,MIN(100,100*(RV_DIAS_CERO-BN24)/(RV_DIAS_CERO-RV_DIAS_FULL)))) | DV24: =RV_W_LIQ*DT24+RV_W_DIAS*DU24+RV_W_ETQ*DC24 | DW24: =IFERROR(VLOOKUP(L24,CARR_PEN_TBL,2,0),0) | DX24: =W_FIAB*CS24+W_PRECIO*CU24+W_KMEDAD*CY24+W_ESTADO*DB24+W_USO*DK24+W_SEGURIDAD*DM24+W_SEGVIAL*DP24+W_ESTETICA*DR24+W_COLOR*DS24+W_REVENTA*DV24-DW24-EG24 | DY24: =IF(N(I24)>0,I24,IFERROR(ROUND(_xlfn.NUMBERVALUE(LEFT(G24,FIND(" ",G24&" ")-1),".")*1000,0),99999)) | DZ24: =IF(R24="profesional",0,IF(O24<CUOTA_VALOR_MAX,IF(BW24>ITP_TRAMO_ALTO,SUMIFS(CF_CUOTA,CF_MAS,ITP_TRAMO_ALTO,CF_CCMIN,"<="&DY24,CF_CCMAX,">="&DY24),IF(BW24>ITP_TRAMO_BAJO,SUMIFS(CF_CUOTA,CF_MAS,ITP_TRAMO_BAJO,CF_CCMIN,"<="&DY24,CF_CCMAX,">="&DY24),O24*ITP_TIPO)),O24*ITP_TIPO)) | EA24: =IF(R24="profesional",N(AK24),0) | EB24: =IF(AND(R24="profesional",ISNUMBER(AK24),AL24="sí"),0,TASA_DGT) | EC24: =INFORME_DGT | ED24: =O24+EA24+DZ24+EB24+EC24 | EE24: =ED24+N(DF24) | EF24: =MAX(0,ED24-TOTAL_MAX) | EG24: =EF24/100*PEN_100 | EH24: =IF(R24="particular",ED24+IF(AND(DA24<>"cadena",X24<>"sí"),RES_CORREA,0)+IF(AND(BJ24<>"sí",BW24>=RES_NEUM_EDAD),RES_NEUM,0),"") | EI24: =IF(ED24<=TOTAL_MAX,"sí",IF(ED24<=TECHO,"negociar","no")) | EJ24: =ROUND(DX24,9) | EK24: =IF(EI24<>"no",SUMPRODUCT(($EI$2:$EI$209<>"no")*($EJ$2:$EJ$209>EJ24))+SUMPRODUCT(($EI$2:EI24<>"no")*($EJ$2:EJ24=EJ24)),"")
A25: cochesnet:71146219 | B25: cochesnet | C25: https://www.coches.net/ford-fiesta-14-tdci-trend-5p-diesel-2011-en-valencia-71146219-covo.aspx | D25: FORD Fiesta 1.4 TDCi Trend | E25: Ford | F25: Ford Fiesta | G25: 1.4 TDCi | H25: 1.4 TDCi Trend | K25: diesel | L25: utilitario | M25: 2010 | N25: 196000 | O25: 4000 | P25: manual | Q25: no | R25: profesional | S25: Beniparrell | T25: 2026-10-20T18:06:18Z | U25: 13 | Z25: sí | AB25: 12 | AH25: 4000 | AM25: 10.2 | AO25: 2010 | AP25: 2010 | AR25: B | AS25: anuncio | AT25: 2011 | AU25: no | AV25: B | AX25: no | AY25: no | AZ25: COMMON.COLOR_BLUE | BA25: azul | BB25: 2 | BC25: (por segmento) | BK25: 5 | BM25: 302 | BN25: 0.074340278 | BO25: 3 | BP25: 4490 | BQ25: 19 | BR25: modelo+año+km | BT25: año a confirmar: la URL/título dice 2011; vendedor profesional: sin ITP (operación con IVA/REBU, confirmar en factura); gastos de gestión del vendedor no indicados: se suma la tasa DGT; preguntar el precio final; diésel: motor sin fuente de fiabilidad (fiabilidad limitada a neutra); revisar: no menciona la ITV | BU25: Este Ford Fiesta 1.4 TDCi Trend es un compacto versátil diseñado para quienes buscan eficiencia sin renunciar a la practicidad. Su motor diésel de 70 CV ofrece un consumo contenido —4,1 l/100 km en ciclo mixto— con una autonomía cercana a los 1.000 km, características que lo hacen económico en uso y especialmente adecuado para desplazamientos regulares. El espacio interior está bien aprovechado: 295 litros de maletero con asientos montados se amplían a 979 litros al abatirlos, lo que permite transportar carga considerable sin perder la versatilidad de cinco plazas. El habitáculo ofrece comodidad suficiente para el día a día, con asientos delanteros ajustables manualmente, dirección asistida eléctrica y volante regulable en altura y profundidad. En seguridad, este vehículo incluye airbags frontales y laterales delanteros, ABS, control de tracción y de estabilidad, además de cinturones con pretensores en las plazas delanteras. La preparación Isofix facilita la instalación de sistemas de retención infantil. El equipamiento de serie contempla cierre centralizado con mando a distancia, elevalunas eléctricos delanteros, retrovisores exteriores eléctricos con intermitente integrado, limpiaparabrisas y sistema de ventilación con filtro de pólen. Cuenta con ordenador de viaje que muestra consumo medio y autonomía estimada. La transmisión manual de cinco velocidades proporciona control directo, mientras que la tracción delantera mejora la estabilidad en curvas. Con etiqueta medioam | BV25: https://www.coches.net/ford-fiesta-14-tdci-trend-5p-diesel-2011-en-valencia-71146219-covo.aspx (window.__INITIAL_PROPS__.ad) /home/user/Alopecia/buscador-coches/raw/cochesnet/c873a4c39ee94bcd.json | BW25: =MAX(ANIO_ACTUAL-M25,0) | BX25: =N25/MAX(BW25,0.5) | BY25: =F25 | BZ25: =BY25&"|"&INT(M25/SEG_ANIO)*SEG_ANIO | CA25: =BZ25&"|"&INT(N25/SEG_KM)*SEG_KM | CB25: =COUNTIF($BY$2:$BY$209,BY25) | CC25: =COUNTIF($BZ$2:$BZ$209,BZ25) | CD25: =COUNTIF($CA$2:$CA$209,CA25) | CE25: {=IF(N(BQ25)>=MIN_N,BP25,IF(CD25>=MIN_N,MEDIAN(IF($CA$2:$CA$209=CA25,$O$2:$O$209)),IF(CC25>=MIN_N,MEDIAN(IF($BZ$2:$BZ$209=BZ25,$O$2:$O$209)),MEDIAN(IF($BY$2:$BY$209=BY25,$O$2:$O$209)))))} | CF25: =IF(N(BQ25)>=MIN_N,"mercado "&BR25,IF(CD25>=MIN_N,"modelo+año+km",IF(CC25>=MIN_N,"modelo+año","modelo"))) | CG25: =(CE25-O25)/CE25 | CH25: =IF(COUNTIFS(FR_FUEL,K25,FR_YEAR,AP25)>0,1,0) | CI25: =IF(COUNTIFS(FR_FUEL,K25,FR_YEAR,AP25-1)>0,1,0) | CJ25: =IF(N(AQ25)>0,AP25*100+AQ25,IF(AND(CH25=1,CI25=1),(AP25-1)*100+1,AP25*100+1)) | CK25: =IF(OR(K25="hibrido",K25="glp",K25="gnc",K25="phev"),"ECO",IF(K25="electrico","CERO",IF(K25="gasolina",IF(CJ25>=GAS_C_YM,"C",IF(CJ25>=GAS_B_YM,"B","A")),IF(K25="diesel",IF(CJ25>=DIE_C_YM,"C",IF(CJ25>=DIE_B_YM,"B","A")),"")))) | CL25: B | CM25: =IF(AU25="sí","sí",IF(AS25="regla",IF(AND(N(AQ25)=0,CH25=1),"sí","no"),"no")) | CN25: =IFERROR(VLOOKUP(F25,MOD_TBL,16,0),IFERROR(VLOOKUP(E25,OCU_TBL,2,0),NEUTRO)) | CO25: =SUMIFS(MOT_AJUSTE,MOT_MOTOR,G25,MOT_MARCA,E25,MOT_DESDE,"<="&M25,MOT_HASTA,">="&M25)+SUMIFS(MOT_AJUSTE,MOT_MOTOR,G25,MOT_MARCA,"(todas)",MOT_DESDE,"<="&M25,MOT_HASTA,">="&M25)+SUMIFS(MOT_AJUSTE,MOT_MOTOR,"(cualquiera)",MOT_MARCA,E25,MOT_DESDE,"<="&M25,MOT_HASTA,">="&M25) | CP25: =SUMIFS(COMB_AJUSTE,COMB_COMB,K25) | CQ25: =COUNTIFS(MOT_MOTOR,G25,MOT_MARCA,E25,MOT_DESDE,"<="&M25,MOT_HASTA,">="&M25)+COUNTIFS(MOT_MOTOR,G25,MOT_MARCA,"(todas)",MOT_DESDE,"<="&M25,MOT_HASTA,">="&M25)+COUNTIFS(MOT_MOTOR,"(cualquiera)",MOT_MARCA,E25,MOT_DESDE,"<="&M25,MOT_HASTA,">="&M25) | CR25: =IF(AND(K25="diesel",CQ25=0),MIN(CN25,NEUTRO),CN25) | CS25: =MAX(0,MIN(100,CR25+CO25+CP25-IF(AX25="sí",ROB_PEN,0))) | CT25: =100-MAX(0,N25-KM_TOPE_DESDE)/1000*KM_TOPE_PTS | CU25: =MAX(0,MIN(100,50+CG25*PRECIO_PEND,CT25)) | CV25: =MAX(0,100*(1-N25/KM_MAX)) | CW25: =IF(BX25<KMA_SOSP,IF(AA25="sí",100,KMA_PEN),IF(BX25<=KMA_IDEAL_MAX,100,MAX(0,100*(KMA_CERO-BX25)/(KMA_CERO-KMA_IDEAL_MAX)))) | CX25: =MAX(0,MIN(100,100*(M25-ANIO_MIN)/(ANIO_ACTUAL-ANIO_MIN))) | CY25: =W_KMT*CV25+W_KMA*CW25+W_EDAD*CX25 | CZ25: =E25&"|"&G25 | DA25: =IFERROR(VLOOKUP(CZ25,DIST_TBL,2,0),"") | DB25: =E_ITV*(V25="sí")+E_LIBRO*(W25="sí")+E_PROP*IF(Y25=1,1,IF(Y25=2,0.5,0))+E_CORREA*IF(OR(DA25="cadena",AND(X25="sí",BH25="sí")),1,IF(X25="sí",0.5,0))+E_FACT*(BI25="sí") | DC25: =MAX(0,MIN(100,IFERROR(VLOOKUP(CL25,ETQ_TBL,2,0),0)-IF(CM25="sí",ETQ_PEN_DUD,IF(AS25="regla",ETQ_PEN_REGLA,0)))) | DD25: =IF(K25<>"gasolina","",IFERROR(VLOOKUP(F25,CONS_MOD_TBL,2,0),IFERROR(VLOOKUP(L25,CONS_SEG_TBL,2,0),""))) | DE25: =IF(DD25="",NEUTRO,MAX(0,MIN(100,100*(CONS_REF_MAX-DD25)/(CONS_REF_MAX-CONS_REF_MIN)))) | DF25: =IFERROR(VLOOKUP(L25,SEGURO_TBL,3,0),"") | DG25: =IF(DF25="",NEUTRO,MAX(0,MIN(100,100*(SEG_REF_MAX-DF25)/(SEG_REF_MAX-SEG_REF_MIN)))) | DH25: =IFERROR(VLOOKUP(E25,MANT_MARCA_TBL,2,0)+0,NEUTRO) | DI25: =IF(DA25="",NEUTRO,IFERROR(VLOOKUP(DA25,DIST_PTS_TBL,2,0)+0,NEUTRO)) | DJ25: =(DH25+DI25)/2 | DK25: =W_CONS*DE25+W_SEG*DG25+W_MANT*DJ25 | DL25: =IF(N(AB25)>0,AB25,IF(AND(R25="profesional",SG_LEGAL_ON=1),GAR_LEGAL,0)) | DM25: =MAX(0,MIN(100,SG_GAR*MIN(1,DL25/SG_GAR_FULL)+SG_AMPL*(AC25="sí")+SG_KMC*(AF25="sí")+SG_REV*(N(AE25)>0)+SG_DEV*MIN(1,N(AG25)/SG_DEV_FULL)+SG_HIST*(W25="sí")-IF(AND(R25="particular",DL25=0),SG_PART_PEN,0))) | DN25: =IF(BK25="",NEUTRO,MAX(0,MIN(100,BK25/5*100))) | DO25: =IF(BL25="sí",100,IF(BL25="no",0,NEUTRO)) | DP25: =SV_W_NCAP*DN25+SV_W_ESP*DO25 | DQ25: =MAX(0,MIN(100,ATR_BASE+ATR_ACAB*(BD25<>"")+IF(BE25="16+",ATR_LL16,IF(BE25="sí",ATR_LL,0))+ATR_FAROS*(BF25="sí")+ATR_TINT*(BG25="sí")-ATR_CHAPA*(BE25="chapa"))) | DR25: =EST_W_MOD*(BB25-1)/4*100+EST_W_ATR*DQ25 | DS25: =IF(BA25="",NEUTRO,IFERROR(VLOOKUP(BA25,COLOR_TBL,2,0)+0,NEUTRO)) | DT25: =MAX(0,MIN(100,100*N(BM25)/RV_N_FULL)) | DU25: =IF(OR(BN25="",N(BO25)<RV_DIAS_MIN),NEUTRO,MAX(0,MIN(100,100*(RV_DIAS_CERO-BN25)/(RV_DIAS_CERO-RV_DIAS_FULL)))) | DV25: =RV_W_LIQ*DT25+RV_W_DIAS*DU25+RV_W_ETQ*DC25 | DW25: =IFERROR(VLOOKUP(L25,CARR_PEN_TBL,2,0),0) | DX25: =W_FIAB*CS25+W_PRECIO*CU25+W_KMEDAD*CY25+W_ESTADO*DB25+W_USO*DK25+W_SEGURIDAD*DM25+W_SEGVIAL*DP25+W_ESTETICA*DR25+W_COLOR*DS25+W_REVENTA*DV25-DW25-EG25 | DY25: =IF(N(I25)>0,I25,IFERROR(ROUND(_xlfn.NUMBERVALUE(LEFT(G25,FIND(" ",G25&" ")-1),".")*1000,0),99999)) | DZ25: =IF(R25="profesional",0,IF(O25<CUOTA_VALOR_MAX,IF(BW25>ITP_TRAMO_ALTO,SUMIFS(CF_CUOTA,CF_MAS,ITP_TRAMO_ALTO,CF_CCMIN,"<="&DY25,CF_CCMAX,">="&DY25),IF(BW25>ITP_TRAMO_BAJO,SUMIFS(CF_CUOTA,CF_MAS,ITP_TRAMO_BAJO,CF_CCMIN,"<="&DY25,CF_CCMAX,">="&DY25),O25*ITP_TIPO)),O25*ITP_TIPO)) | EA25: =IF(R25="profesional",N(AK25),0) | EB25: =IF(AND(R25="profesional",ISNUMBER(AK25),AL25="sí"),0,TASA_DGT) | EC25: =INFORME_DGT | ED25: =O25+EA25+DZ25+EB25+EC25 | EE25: =ED25+N(DF25) | EF25: =MAX(0,ED25-TOTAL_MAX) | EG25: =EF25/100*PEN_100 | EH25: =IF(R25="particular",ED25+IF(AND(DA25<>"cadena",X25<>"sí"),RES_CORREA,0)+IF(AND(BJ25<>"sí",BW25>=RES_NEUM_EDAD),RES_NEUM,0),"") | EI25: =IF(ED25<=TOTAL_MAX,"sí",IF(ED25<=TECHO,"negociar","no")) | EJ25: =ROUND(DX25,9) | EK25: =IF(EI25<>"no",SUMPRODUCT(($EI$2:$EI$209<>"no")*($EJ$2:$EJ$209>EJ25))+SUMPRODUCT(($EI$2:EI25<>"no")*($EJ$2:EJ25=EJ25)),"")
A26: cochesnet:71533850 | B26: cochesnet | C26: https://www.coches.net/chevrolet-aveo-14-16v-ls-5p-gasolina-2010-en-valencia-71533850-covo.aspx | D26: CHEVROLET Aveo 1.4 16v LS | E26: Chevrolet | F26: Chevrolet Aveo | G26: 1.4 | H26: 1.4 16v LS | K26: gasolina | L26: utilitario | M26: 2009 | N26: 110000 | O26: 4290 | P26: manual | Q26: no | R26: profesional | S26: Only Cars Valencia Aldaia | T26: 2026-09-17T10:24:43Z | U26: 11 | Z26: sí | AB26: 12 | AH26: 4290 | AM26: 7.5 | AO26: 2009 | AP26: 2009 | AR26: C | AS26: anuncio | AT26: 2010 | AU26: no | AV26: C | AX26: no | AY26: no | AZ26: COMMON.COLOR_BLUE | BA26: azul | BB26: 2 | BC26: (por segmento) | BK26: 2 | BL26: no | BM26: 27 | BO26: 0 | BP26: 3990 | BQ26: 4 | BR26: modelo+año+km | BT26: año a confirmar: la URL/título dice 2010; vendedor profesional: sin ITP (operación con IVA/REBU, confirmar en factura); gastos de gestión del vendedor no indicados: se suma la tasa DGT; preguntar el precio final; revisar: no menciona la ITV; fiabilidad del modelo PENDIENTE de fuente (puntuación neutra) | BU26: Chevrolet Aveo 1.4 LS año 2009 con 110.000Kms 100CV. Equipamiento: - elevalunas eléctricos - Espejos eléctricos - Aire acondicionado - Dirección asistida - Mando a distancia - Ordenador de abordo Mantenimiento: - cambio de filtro de aire - cambio de filtro de aceite - cambio de aceite - Dos juegos de llave - Alfombrillas | BV26: https://www.coches.net/chevrolet-aveo-14-16v-ls-5p-gasolina-2010-en-valencia-71533850-covo.aspx (window.__INITIAL_PROPS__.ad) /home/user/Alopecia/buscador-coches/raw/cochesnet/f4665f6b14e63416.json | BW26: =MAX(ANIO_ACTUAL-M26,0) | BX26: =N26/MAX(BW26,0.5) | BY26: =F26 | BZ26: =BY26&"|"&INT(M26/SEG_ANIO)*SEG_ANIO | CA26: =BZ26&"|"&INT(N26/SEG_KM)*SEG_KM | CB26: =COUNTIF($BY$2:$BY$209,BY26) | CC26: =COUNTIF($BZ$2:$BZ$209,BZ26) | CD26: =COUNTIF($CA$2:$CA$209,CA26) | CE26: {=IF(N(BQ26)>=MIN_N,BP26,IF(CD26>=MIN_N,MEDIAN(IF($CA$2:$CA$209=CA26,$O$2:$O$209)),IF(CC26>=MIN_N,MEDIAN(IF($BZ$2:$BZ$209=BZ26,$O$2:$O$209)),MEDIAN(IF($BY$2:$BY$209=BY26,$O$2:$O$209)))))} | CF26: =IF(N(BQ26)>=MIN_N,"mercado "&BR26,IF(CD26>=MIN_N,"modelo+año+km",IF(CC26>=MIN_N,"modelo+año","modelo"))) | CG26: =(CE26-O26)/CE26 | CH26: =IF(COUNTIFS(FR_FUEL,K26,FR_YEAR,AP26)>0,1,0) | CI26: =IF(COUNTIFS(FR_FUEL,K26,FR_YEAR,AP26-1)>0,1,0) | CJ26: =IF(N(AQ26)>0,AP26*100+AQ26,IF(AND(CH26=1,CI26=1),(AP26-1)*100+1,AP26*100+1)) | CK26: =IF(OR(K26="hibrido",K26="glp",K26="gnc",K26="phev"),"ECO",IF(K26="electrico","CERO",IF(K26="gasolina",IF(CJ26>=GAS_C_YM,"C",IF(CJ26>=GAS_B_YM,"B","A")),IF(K26="diesel",IF(CJ26>=DIE_C_YM,"C",IF(CJ26>=DIE_B_YM,"B","A")),"")))) | CL26: C | CM26: =IF(AU26="sí","sí",IF(AS26="regla",IF(AND(N(AQ26)=0,CH26=1),"sí","no"),"no")) | CN26: =IFERROR(VLOOKUP(F26,MOD_TBL,16,0),IFERROR(VLOOKUP(E26,OCU_TBL,2,0),NEUTRO)) | CO26: =SUMIFS(MOT_AJUSTE,MOT_MOTOR,G26,MOT_MARCA,E26,MOT_DESDE,"<="&M26,MOT_HASTA,">="&M26)+SUMIFS(MOT_AJUSTE,MOT_MOTOR,G26,MOT_MARCA,"(todas)",MOT_DESDE,"<="&M26,MOT_HASTA,">="&M26)+SUMIFS(MOT_AJUSTE,MOT_MOTOR,"(cualquiera)",MOT_MARCA,E26,MOT_DESDE,"<="&M26,MOT_HASTA,">="&M26) | CP26: =SUMIFS(COMB_AJUSTE,COMB_COMB,K26) | CQ26: =COUNTIFS(MOT_MOTOR,G26,MOT_MARCA,E26,MOT_DESDE,"<="&M26,MOT_HASTA,">="&M26)+COUNTIFS(MOT_MOTOR,G26,MOT_MARCA,"(todas)",MOT_DESDE,"<="&M26,MOT_HASTA,">="&M26)+COUNTIFS(MOT_MOTOR,"(cualquiera)",MOT_MARCA,E26,MOT_DESDE,"<="&M26,MOT_HASTA,">="&M26) | CR26: =IF(AND(K26="diesel",CQ26=0),MIN(CN26,NEUTRO),CN26) | CS26: =MAX(0,MIN(100,CR26+CO26+CP26-IF(AX26="sí",ROB_PEN,0))) | CT26: =100-MAX(0,N26-KM_TOPE_DESDE)/1000*KM_TOPE_PTS | CU26: =MAX(0,MIN(100,50+CG26*PRECIO_PEND,CT26)) | CV26: =MAX(0,100*(1-N26/KM_MAX)) | CW26: =IF(BX26<KMA_SOSP,IF(AA26="sí",100,KMA_PEN),IF(BX26<=KMA_IDEAL_MAX,100,MAX(0,100*(KMA_CERO-BX26)/(KMA_CERO-KMA_IDEAL_MAX)))) | CX26: =MAX(0,MIN(100,100*(M26-ANIO_MIN)/(ANIO_ACTUAL-ANIO_MIN))) | CY26: =W_KMT*CV26+W_KMA*CW26+W_EDAD*CX26 | CZ26: =E26&"|"&G26 | DA26: =IFERROR(VLOOKUP(CZ26,DIST_TBL,2,0),"") | DB26: =E_ITV*(V26="sí")+E_LIBRO*(W26="sí")+E_PROP*IF(Y26=1,1,IF(Y26=2,0.5,0))+E_CORREA*IF(OR(DA26="cadena",AND(X26="sí",BH26="sí")),1,IF(X26="sí",0.5,0))+E_FACT*(BI26="sí") | DC26: =MAX(0,MIN(100,IFERROR(VLOOKUP(CL26,ETQ_TBL,2,0),0)-IF(CM26="sí",ETQ_PEN_DUD,IF(AS26="regla",ETQ_PEN_REGLA,0)))) | DD26: =IF(K26<>"gasolina","",IFERROR(VLOOKUP(F26,CONS_MOD_TBL,2,0),IFERROR(VLOOKUP(L26,CONS_SEG_TBL,2,0),""))) | DE26: =IF(DD26="",NEUTRO,MAX(0,MIN(100,100*(CONS_REF_MAX-DD26)/(CONS_REF_MAX-CONS_REF_MIN)))) | DF26: =IFERROR(VLOOKUP(L26,SEGURO_TBL,3,0),"") | DG26: =IF(DF26="",NEUTRO,MAX(0,MIN(100,100*(SEG_REF_MAX-DF26)/(SEG_REF_MAX-SEG_REF_MIN)))) | DH26: =IFERROR(VLOOKUP(E26,MANT_MARCA_TBL,2,0)+0,NEUTRO) | DI26: =IF(DA26="",NEUTRO,IFERROR(VLOOKUP(DA26,DIST_PTS_TBL,2,0)+0,NEUTRO)) | DJ26: =(DH26+DI26)/2 | DK26: =W_CONS*DE26+W_SEG*DG26+W_MANT*DJ26 | DL26: =IF(N(AB26)>0,AB26,IF(AND(R26="profesional",SG_LEGAL_ON=1),GAR_LEGAL,0)) | DM26: =MAX(0,MIN(100,SG_GAR*MIN(1,DL26/SG_GAR_FULL)+SG_AMPL*(AC26="sí")+SG_KMC*(AF26="sí")+SG_REV*(N(AE26)>0)+SG_DEV*MIN(1,N(AG26)/SG_DEV_FULL)+SG_HIST*(W26="sí")-IF(AND(R26="particular",DL26=0),SG_PART_PEN,0))) | DN26: =IF(BK26="",NEUTRO,MAX(0,MIN(100,BK26/5*100))) | DO26: =IF(BL26="sí",100,IF(BL26="no",0,NEUTRO)) | DP26: =SV_W_NCAP*DN26+SV_W_ESP*DO26 | DQ26: =MAX(0,MIN(100,ATR_BASE+ATR_ACAB*(BD26<>"")+IF(BE26="16+",ATR_LL16,IF(BE26="sí",ATR_LL,0))+ATR_FAROS*(BF26="sí")+ATR_TINT*(BG26="sí")-ATR_CHAPA*(BE26="chapa"))) | DR26: =EST_W_MOD*(BB26-1)/4*100+EST_W_ATR*DQ26 | DS26: =IF(BA26="",NEUTRO,IFERROR(VLOOKUP(BA26,COLOR_TBL,2,0)+0,NEUTRO)) | DT26: =MAX(0,MIN(100,100*N(BM26)/RV_N_FULL)) | DU26: =IF(OR(BN26="",N(BO26)<RV_DIAS_MIN),NEUTRO,MAX(0,MIN(100,100*(RV_DIAS_CERO-BN26)/(RV_DIAS_CERO-RV_DIAS_FULL)))) | DV26: =RV_W_LIQ*DT26+RV_W_DIAS*DU26+RV_W_ETQ*DC26 | DW26: =IFERROR(VLOOKUP(L26,CARR_PEN_TBL,2,0),0) | DX26: =W_FIAB*CS26+W_PRECIO*CU26+W_KMEDAD*CY26+W_ESTADO*DB26+W_USO*DK26+W_SEGURIDAD*DM26+W_SEGVIAL*DP26+W_ESTETICA*DR26+W_COLOR*DS26+W_REVENTA*DV26-DW26-EG26 | DY26: =IF(N(I26)>0,I26,IFERROR(ROUND(_xlfn.NUMBERVALUE(LEFT(G26,FIND(" ",G26&" ")-1),".")*1000,0),99999)) | DZ26: =IF(R26="profesional",0,IF(O26<CUOTA_VALOR_MAX,IF(BW26>ITP_TRAMO_ALTO,SUMIFS(CF_CUOTA,CF_MAS,ITP_TRAMO_ALTO,CF_CCMIN,"<="&DY26,CF_CCMAX,">="&DY26),IF(BW26>ITP_TRAMO_BAJO,SUMIFS(CF_CUOTA,CF_MAS,ITP_TRAMO_BAJO,CF_CCMIN,"<="&DY26,CF_CCMAX,">="&DY26),O26*ITP_TIPO)),O26*ITP_TIPO)) | EA26: =IF(R26="profesional",N(AK26),0) | EB26: =IF(AND(R26="profesional",ISNUMBER(AK26),AL26="sí"),0,TASA_DGT) | EC26: =INFORME_DGT | ED26: =O26+EA26+DZ26+EB26+EC26 | EE26: =ED26+N(DF26) | EF26: =MAX(0,ED26-TOTAL_MAX) | EG26: =EF26/100*PEN_100 | EH26: =IF(R26="particular",ED26+IF(AND(DA26<>"cadena",X26<>"sí"),RES_CORREA,0)+IF(AND(BJ26<>"sí",BW26>=RES_NEUM_EDAD),RES_NEUM,0),"") | EI26: =IF(ED26<=TOTAL_MAX,"sí",IF(ED26<=TECHO,"negociar","no")) | EJ26: =ROUND(DX26,9) | EK26: =IF(EI26<>"no",SUMPRODUCT(($EI$2:$EI$209<>"no")*($EJ$2:$EJ$209>EJ26))+SUMPRODUCT(($EI$2:EI26<>"no")*($EJ$2:EJ26=EJ26)),"")
A27: cochesnet:71678496 | B27: cochesnet | C27: https://www.coches.net/chevrolet-cruze-16-ls-clima-4p-gasolina-2011-en-valencia-71678496-covo.aspx | D27: CHEVROLET Cruze 1.6 LS Clima | E27: Chevrolet | F27: Chevrolet Cruze | G27: 1.6 | H27: 1.6 LS Clima | K27: gasolina | L27: compacto | M27: 2011 | N27: 205000 | O27: 3950 | P27: manual | Q27: no | R27: profesional | S27: NRGCARS La Pobla de Vallbona | T27: 2026-10-05T18:04:21Z | U27: 13 | V27: sí | Z27: sí | AB27: 12 | AH27: 3950 | AI27: 3950 | AM27: 20.8 | AO27: 2011 | AP27: 2011 | AS27: regla | AU27: no | AV27: C | AX27: no | AY27: no | AZ27: COMMON.COLOR_WHITE | BA27: blanco | BB27: 3 | BC27: (por segmento) | BM27: 26 | BO27: 0 | BP27: 3100 | BQ27: 6 | BR27: modelo+año+km | BT27: vendedor profesional: sin ITP (operación con IVA/REBU, confirmar en factura); gastos de gestión del vendedor no indicados: se suma la tasa DGT; preguntar el precio final; Euro NCAP de la generación PENDIENTE (seguridad neutra); etiqueta C deducida por fecha (sin matrícula ni dato del anuncio); fiabilidad del modelo PENDIENTE de fuente (puntuación neutra) | BU27: ITV EN VIGOR RECIEN REVISADO ACEPTO VEHÍCULO COMO PARTE DE PAGO EMBRAGUE RECIEN CAMBIADO | BV27: https://www.coches.net/chevrolet-cruze-16-ls-clima-4p-gasolina-2011-en-valencia-71678496-covo.aspx (window.__INITIAL_PROPS__.ad) /home/user/Alopecia/buscador-coches/raw/cochesnet/84c294324eca9271.json | BW27: =MAX(ANIO_ACTUAL-M27,0) | BX27: =N27/MAX(BW27,0.5) | BY27: =F27 | BZ27: =BY27&"|"&INT(M27/SEG_ANIO)*SEG_ANIO | CA27: =BZ27&"|"&INT(N27/SEG_KM)*SEG_KM | CB27: =COUNTIF($BY$2:$BY$209,BY27) | CC27: =COUNTIF($BZ$2:$BZ$209,BZ27) | CD27: =COUNTIF($CA$2:$CA$209,CA27) | CE27: {=IF(N(BQ27)>=MIN_N,BP27,IF(CD27>=MIN_N,MEDIAN(IF($CA$2:$CA$209=CA27,$O$2:$O$209)),IF(CC27>=MIN_N,MEDIAN(IF($BZ$2:$BZ$209=BZ27,$O$2:$O$209)),MEDIAN(IF($BY$2:$BY$209=BY27,$O$2:$O$209)))))} | CF27: =IF(N(BQ27)>=MIN_N,"mercado "&BR27,IF(CD27>=MIN_N,"modelo+año+km",IF(CC27>=MIN_N,"modelo+año","modelo"))) | CG27: =(CE27-O27)/CE27 | CH27: =IF(COUNTIFS(FR_FUEL,K27,FR_YEAR,AP27)>0,1,0) | CI27: =IF(COUNTIFS(FR_FUEL,K27,FR_YEAR,AP27-1)>0,1,0) | CJ27: =IF(N(AQ27)>0,AP27*100+AQ27,IF(AND(CH27=1,CI27=1),(AP27-1)*100+1,AP27*100+1)) | CK27: =IF(OR(K27="hibrido",K27="glp",K27="gnc",K27="phev"),"ECO",IF(K27="electrico","CERO",IF(K27="gasolina",IF(CJ27>=GAS_C_YM,"C",IF(CJ27>=GAS_B_YM,"B","A")),IF(K27="diesel",IF(CJ27>=DIE_C_YM,"C",IF(CJ27>=DIE_B_YM,"B","A")),"")))) | CL27: =CK27 | CM27: =IF(AU27="sí","sí",IF(AS27="regla",IF(AND(N(AQ27)=0,CH27=1),"sí","no"),"no")) | CN27: =IFERROR(VLOOKUP(F27,MOD_TBL,16,0),IFERROR(VLOOKUP(E27,OCU_TBL,2,0),NEUTRO)) | CO27: =SUMIFS(MOT_AJUSTE,MOT_MOTOR,G27,MOT_MARCA,E27,MOT_DESDE,"<="&M27,MOT_HASTA,">="&M27)+SUMIFS(MOT_AJUSTE,MOT_MOTOR,G27,MOT_MARCA,"(todas)",MOT_DESDE,"<="&M27,MOT_HASTA,">="&M27)+SUMIFS(MOT_AJUSTE,MOT_MOTOR,"(cualquiera)",MOT_MARCA,E27,MOT_DESDE,"<="&M27,MOT_HASTA,">="&M27) | CP27: =SUMIFS(COMB_AJUSTE,COMB_COMB,K27) | CQ27: =COUNTIFS(MOT_MOTOR,G27,MOT_MARCA,E27,MOT_DESDE,"<="&M27,MOT_HASTA,">="&M27)+COUNTIFS(MOT_MOTOR,G27,MOT_MARCA,"(todas)",MOT_DESDE,"<="&M27,MOT_HASTA,">="&M27)+COUNTIFS(MOT_MOTOR,"(cualquiera)",MOT_MARCA,E27,MOT_DESDE,"<="&M27,MOT_HASTA,">="&M27) | CR27: =IF(AND(K27="diesel",CQ27=0),MIN(CN27,NEUTRO),CN27) | CS27: =MAX(0,MIN(100,CR27+CO27+CP27-IF(AX27="sí",ROB_PEN,0))) | CT27: =100-MAX(0,N27-KM_TOPE_DESDE)/1000*KM_TOPE_PTS | CU27: =MAX(0,MIN(100,50+CG27*PRECIO_PEND,CT27)) | CV27: =MAX(0,100*(1-N27/KM_MAX)) | CW27: =IF(BX27<KMA_SOSP,IF(AA27="sí",100,KMA_PEN),IF(BX27<=KMA_IDEAL_MAX,100,MAX(0,100*(KMA_CERO-BX27)/(KMA_CERO-KMA_IDEAL_MAX)))) | CX27: =MAX(0,MIN(100,100*(M27-ANIO_MIN)/(ANIO_ACTUAL-ANIO_MIN))) | CY27: =W_KMT*CV27+W_KMA*CW27+W_EDAD*CX27 | CZ27: =E27&"|"&G27 | DA27: =IFERROR(VLOOKUP(CZ27,DIST_TBL,2,0),"") | DB27: =E_ITV*(V27="sí")+E_LIBRO*(W27="sí")+E_PROP*IF(Y27=1,1,IF(Y27=2,0.5,0))+E_CORREA*IF(OR(DA27="cadena",AND(X27="sí",BH27="sí")),1,IF(X27="sí",0.5,0))+E_FACT*(BI27="sí") | DC27: =MAX(0,MIN(100,IFERROR(VLOOKUP(CL27,ETQ_TBL,2,0),0)-IF(CM27="sí",ETQ_PEN_DUD,IF(AS27="regla",ETQ_PEN_REGLA,0)))) | DD27: =IF(K27<>"gasolina","",IFERROR(VLOOKUP(F27,CONS_MOD_TBL,2,0),IFERROR(VLOOKUP(L27,CONS_SEG_TBL,2,0),""))) | DE27: =IF(DD27="",NEUTRO,MAX(0,MIN(100,100*(CONS_REF_MAX-DD27)/(CONS_REF_MAX-CONS_REF_MIN)))) | DF27: =IFERROR(VLOOKUP(L27,SEGURO_TBL,3,0),"") | DG27: =IF(DF27="",NEUTRO,MAX(0,MIN(100,100*(SEG_REF_MAX-DF27)/(SEG_REF_MAX-SEG_REF_MIN)))) | DH27: =IFERROR(VLOOKUP(E27,MANT_MARCA_TBL,2,0)+0,NEUTRO) | DI27: =IF(DA27="",NEUTRO,IFERROR(VLOOKUP(DA27,DIST_PTS_TBL,2,0)+0,NEUTRO)) | DJ27: =(DH27+DI27)/2 | DK27: =W_CONS*DE27+W_SEG*DG27+W_MANT*DJ27 | DL27: =IF(N(AB27)>0,AB27,IF(AND(R27="profesional",SG_LEGAL_ON=1),GAR_LEGAL,0)) | DM27: =MAX(0,MIN(100,SG_GAR*MIN(1,DL27/SG_GAR_FULL)+SG_AMPL*(AC27="sí")+SG_KMC*(AF27="sí")+SG_REV*(N(AE27)>0)+SG_DEV*MIN(1,N(AG27)/SG_DEV_FULL)+SG_HIST*(W27="sí")-IF(AND(R27="particular",DL27=0),SG_PART_PEN,0))) | DN27: =IF(BK27="",NEUTRO,MAX(0,MIN(100,BK27/5*100))) | DO27: =IF(BL27="sí",100,IF(BL27="no",0,NEUTRO)) | DP27: =SV_W_NCAP*DN27+SV_W_ESP*DO27 | DQ27: =MAX(0,MIN(100,ATR_BASE+ATR_ACAB*(BD27<>"")+IF(BE27="16+",ATR_LL16,IF(BE27="sí",ATR_LL,0))+ATR_FAROS*(BF27="sí")+ATR_TINT*(BG27="sí")-ATR_CHAPA*(BE27="chapa"))) | DR27: =EST_W_MOD*(BB27-1)/4*100+EST_W_ATR*DQ27 | DS27: =IF(BA27="",NEUTRO,IFERROR(VLOOKUP(BA27,COLOR_TBL,2,0)+0,NEUTRO)) | DT27: =MAX(0,MIN(100,100*N(BM27)/RV_N_FULL)) | DU27: =IF(OR(BN27="",N(BO27)<RV_DIAS_MIN),NEUTRO,MAX(0,MIN(100,100*(RV_DIAS_CERO-BN27)/(RV_DIAS_CERO-RV_DIAS_FULL)))) | DV27: =RV_W_LIQ*DT27+RV_W_DIAS*DU27+RV_W_ETQ*DC27 | DW27: =IFERROR(VLOOKUP(L27,CARR_PEN_TBL,2,0),0) | DX27: =W_FIAB*CS27+W_PRECIO*CU27+W_KMEDAD*CY27+W_ESTADO*DB27+W_USO*DK27+W_SEGURIDAD*DM27+W_SEGVIAL*DP27+W_ESTETICA*DR27+W_COLOR*DS27+W_REVENTA*DV27-DW27-EG27 | DY27: =IF(N(I27)>0,I27,IFERROR(ROUND(_xlfn.NUMBERVALUE(LEFT(G27,FIND(" ",G27&" ")-1),".")*1000,0),99999)) | DZ27: =IF(R27="profesional",0,IF(O27<CUOTA_VALOR_MAX,IF(BW27>ITP_TRAMO_ALTO,SUMIFS(CF_CUOTA,CF_MAS,ITP_TRAMO_ALTO,CF_CCMIN,"<="&DY27,CF_CCMAX,">="&DY27),IF(BW27>ITP_TRAMO_BAJO,SUMIFS(CF_CUOTA,CF_MAS,ITP_TRAMO_BAJO,CF_CCMIN,"<="&DY27,CF_CCMAX,">="&DY27),O27*ITP_TIPO)),O27*ITP_TIPO)) | EA27: =IF(R27="profesional",N(AK27),0) | EB27: =IF(AND(R27="profesional",ISNUMBER(AK27),AL27="sí"),0,TASA_DGT) | EC27: =INFORME_DGT | ED27: =O27+EA27+DZ27+EB27+EC27 | EE27: =ED27+N(DF27) | EF27: =MAX(0,ED27-TOTAL_MAX) | EG27: =EF27/100*PEN_100 | EH27: =IF(R27="particular",ED27+IF(AND(DA27<>"cadena",X27<>"sí"),RES_CORREA,0)+IF(AND(BJ27<>"sí",BW27>=RES_NEUM_EDAD),RES_NEUM,0),"") | EI27: =IF(ED27<=TOTAL_MAX,"sí",IF(ED27<=TECHO,"negociar","no")) | EJ27: =ROUND(DX27,9) | EK27: =IF(EI27<>"no",SUMPRODUCT(($EI$2:$EI$209<>"no")*($EJ$2:$EJ$209>EJ27))+SUMPRODUCT(($EI$2:EI27<>"no")*($EJ$2:EJ27=EJ27)),"")
